digital_logic/verilog_files/syn_counter/ff.sv
`timescale 1ns/10ps
 

module tb();
reg D = 0, EN=0, G = 0, CLK = 0, S = 0, R = 0;
reg Q1_latch, Q1_latch_sr, Q2_ff, Q3_ff_en, Q4_ff_en_sr, Q5_bloq, Q5_n_bloq;

initial
begin
	$display("Comecou o teste");
	$dumpfile("test.vcd");
	$dumpvars(0,tb);    
	$timeformat(-9, 2, " ns", 20);
	#10ns;
	D = 1;
	#10ns;
	D = 0;
	#10ns;
	D = 1;
	#10ns;
	G = 1;
	#2ns;
	D = 0;
	#10ns;
	D = 1;
	#10ns;
	D = 0;
	#2ns;
	EN= 1;
	#10ns;
	D = 1;
	#10ns;
	D = 0;
	#10ns;
	D = 1;
	#2ns;
	S = 1;
	#10ns;
	D = 0;
	#2ns;
	G = 0;
	#10ns;
	EN= 0;
	#2ns;
	D = 1;
	#2ns;
	R = 1;
	#10ns;
	D = 0;
	#10ns;
	D = 1;
	#2ns;
	S = 0;
	#10ns;
	D = 0;
	#10ns;
	$finish();
end

always
begin
	#4ns;
	CLK = !CLK;
end

// Latch tipo D
always@(G, D)
if(G)
	Q1_latch = D; // não requer else! Caso contrario mantém o valor
    
// Latch tipo D, SET e RESET
always@(G, D)
if(S)
	Q1_latch_sr = 1;
else
	if(R)
    	Q1_latch_sr = 0;
	else
    	if(G)
        	Q1_latch_sr = D; // não requer else! Caso contrario mantém o valor
    
// Flip-flop tipo D
always@(posedge CLK)
	Q2_ff <= D; // não requer else! Caso contrario mantém o valor

// Flip-flop tipo D com habilitador
always@(posedge CLK)
if (EN)
	Q3_ff_en <= D; // não requer else! Caso contrario mantém o valor
    
// Flip-flop tipo D com habilitador, SET e RESET
always@(posedge CLK, posedge R, posedge S)
if(S)
	Q4_ff_en_sr <= 1;
else
	if(R)
    	Q4_ff_en_sr <= 0;
	else
    	if (EN)
        	Q4_ff_en_sr <= D; // não requer else! Caso contrario mantém o valor
    
    
// Flip-flop tipo D com habilitador - exemplo atribuição bloqueante e não bloqueante
always@(posedge CLK)
begin
	$display("=-=-=-=-=-=-=-=-=-=-=-=-=-=-=-=-=-=-=-=-=-=-=");
	$display("(%t)EN= %b D=%b",$time, EN, D);
	$display("(%t)Antes Q5_bloq vale %b",$time, Q5_bloq);
	$display("(%t)Antes Q5_bloq_n_bloq vale %b",$time, Q5_n_bloq);
	if (EN)
	begin
    	Q5_bloq = D;
    	Q5_n_bloq <= D;    	 
    	$display("(%t)Logo apos Q5_bloq vale %b",$time, Q5_bloq);
    	$display("(%t)Logo apos Q5_n_bloq vale %b",$time, Q5_n_bloq);
	end
	#1;
	$display("(%t)No passo seguinte de sim Q5_bloq vale %b",$time, Q5_bloq);
	$display("(%t)No passo seguinte de sim Q5_n_bloq vale %b",$time, Q5_n_bloq);
end

endmodule

digital_logic/verilog_files/test.vcd
$date
    Nov 21, 2024  08:54:52
$end
$version
    TOOL:	xmsim(64)	22.09-s013
$end
$timescale
    10 ps
$end

$scope module tb $end
$var reg       1 !    D $end
$var reg       1 "    EN $end
$var reg       1 #    G $end
$var reg       1 $    CLK $end
$var reg       1 %    S $end
$var reg       1 &    R $end
$var reg       1 '    Q1_latch $end
$var reg       1 (    Q1_latch_sr $end
$var reg       1 )    Q2_ff $end
$var reg       1 *    Q3_ff_en $end
$var reg       1 +    Q4_ff_en_sr $end
$var reg       1 ,    Q5_bloq $end
$var reg       1 -    Q5_n_bloq $end
$upscope $end

$enddefinitions $end
$dumpvars
0!
0"
0#
0$
0%
0&
x'
x(
x)
x*
x+
x,
x-
$end
#400
1$
0)
#800
0$
#1000
1!
#1200
1$
1)
#1600
0$
#2000
0!
1$
0)
#2400
0$
#2800
1$
#3000
1!
#3200
0$
#3600
1$
1)
#4000
1#
0$
1'
1(
#4200
0!
0'
0(
#4400
1$
0)
#4800
0$
#5200
1!
1$
1'
1(
1)
#5600
0$
#6000
1$
#6200
0!
0'
0(
#6400
0$
1"
#6800
1$
0,
0)
0*
0+
0-
#7200
0$
#7400
1!
1'
1(
#7600
1$
1,
1)
1*
1+
1-
#8000
0$
#8400
0!
1$
0'
0(
0,
0)
0*
0+
0-
#8800
0$
#9200
1$
#9400
1!
1'
1(
#9600
0$
1%
1+
#10000
1$
1,
1)
1*
1-
#10400
0$
#10600
0!
0'
#10800
1$
0#
0,
0)
0*
0-
#11200
0$
#11600
1$
#11800
0"
#12000
0$
1!
#12200
1&
#12400
1$
1)
#12800
0$
#13200
0!
1$
0)
#13600
0$
#14000
1$
#14200
1!
#14400
0$
0%
#14800
1$
1)
0+
#15200
0$
#15400
0!
0(
#15600
1$
0)
