verilog_tests/arch_fpga_asic/tarefa_02/q2/LUT3.sv
// $Header: /devl/xcs/repo/env/Databases/CAEInterfaces/verunilibs/data/unisims/LUT3.v,v 1.7 2007/05/23 21:43:39 patrickp Exp $
///////////////////////////////////////////////////////////////////////////////
// Copyright (c) 1995/2004 Xilinx, Inc.
// All Right Reserved.
///////////////////////////////////////////////////////////////////////////////
//   ____  ____
//  /   /\/   /
// /___/  \  /    Vendor : Xilinx
// \   \   \/     Version : 10.1
//  \   \         Description : Xilinx Functional Simulation Library Component
//  /   /                  3-input Look-Up-Table with General Output
// /___/   /\     Filename : LUT3.v
// \   \  /  \    Timestamp : Thu Mar 25 16:42:54 PST 2004
//  \___\/\___\
//
// Revision:
//    03/23/04 - Initial version.
//    02/04/05 - Rev 0.0.1 Replace premitive with function; Remove buf.
//    05/23/07 - Changed timescale to 1 ps / 1 ps.

`timescale  1 ps / 1 ps


module LUT3 (O, I0, I1, I2);

    parameter INIT = 8'h00;

    input I0, I1, I2;

    output logic O;

    logic tmp;
  
    always_ff @(  I2 or  I1 or  I0 )  begin
      tmp =  I0 ^ I1  ^ I2;
      if ( tmp == 0 || tmp == 1)
           O = INIT[{I2, I1, I0}];
      else
           O = lut3_mux4 ( {1'b0, 1'b0, lut3_mux4 (INIT[7:4], {I1, I0}),
                          lut3_mux4 (INIT[3:0], {I1, I0}) }, {1'b0, I2});
    end

  function lut3_mux4;
  input [3:0] d;
  input [1:0] s;

  begin
       if ((s[1]^s[0] ==1) || (s[1]^s[0] ==0))
           lut3_mux4 = d[s];
         else if ((d[0] === d[1]) && (d[2] === d[3]) && (d[0] === d[2]))
           lut3_mux4 = d[0];
         else if ((s[1] == 0) && (d[0] === d[1]))
           lut3_mux4 = d[0];
         else if ((s[1] == 1) && (d[2] === d[3]))
           lut3_mux4 = d[2];
         else if ((s[0] == 0) && (d[0] === d[2]))
           lut3_mux4 = d[0];
         else if ((s[0] == 1) && (d[1] === d[3]))
           lut3_mux4 = d[1];
         else
           lut3_mux4 = 1'bx;
   end
   endfunction

endmodule

verilog_tests/arch_fpga_asic/tarefa_02/q2/OR_3.sv
`timescale 1ns/1ps
module OR_3(A, B, C, OUT);

input logic A, B, C;
output logic OUT;

LUT3 #(.INIT(8'hFE)) OR_0_INST( .I0(A), .I1(B), .I2(C), .O(OUT));

endmodule

verilog_tests/arch_fpga_asic/tarefa_02/q2/AND_3.sv
`timescale 1ns/1ps
module AND_3(A, B, C, OUT);

input logic A, B, C;
output logic OUT;

LUT3 #(.INIT(8'h80)) AND_0_INST( .I0(A), .I1(B), .I2(C), .O(OUT));

endmodule

verilog_tests/arch_fpga_asic/tarefa_02/q2/NOR_3.sv
`timescale 1ns/1ps
module NOR_3(A, B, C, OUT);

input logic A, B, C;
output logic OUT;

LUT3 #(.INIT(8'h1)) OR_0_INST( .I0(A), .I1(B), .I2(C), .O(OUT));

endmodule

verilog_tests/arch_fpga_asic/tarefa_02/q2/Q2_LUT3.sv
`timescale 1ns/1ps
module Q2_LUT3(A3, A2, A1, A0, OUT);

input logic A0, A1, A2, A3;
output logic OUT;

logic nor_0_out, nor_1_out, and_0_out, and_1_out, or_0_out;

NOR_3 NOR_0_INST(.A(A1), .B(A2), .C(A3), .OUT(nor_0_out));
AND_3 AND_0_INST(.A(A1), .B(A2), .C(A3), .OUT(and_0_out));

NOR_3 NOR_1_INST(.A(A0), .B(A2), .C(A3), .OUT(nor_1_out));
AND_3 AND_1_INST(.A(A0), .B(A2), .C(A3), .OUT(and_1_out));


OR_3 OR_0_INST(.A(nor_0_out), .B(and_0_out), .C(nor_1_out), .OUT(or_0_out));
OR_3 OR_1_INST(.A(or_0_out), .B(and_1_out), .C(1'b0), .OUT(OUT));




endmodule

verilog_tests/arch_fpga_asic/tarefa_02/q2/Q2_LUT3_TB.sv
`timescale 1ns/1ps
module Q2_LUT3_TB;
  logic A0, A1, A2, A3, OUT;
  
  Q2_LUT3 UUT(.A3(A3), .A2(A2), .A1(A1), .A0(A0), .OUT(OUT));

  
  initial
    begin
      $dumpfile("dump.vcd");
      $dumpvars(0, UUT);
      // Test case 1
      A0 = 1'b0; A1 = 1'b0; A2 = 1'b0; A3 = 1'b0;
      #10;
      // Test case 2
      A0 = 1'b0; A1 = 1'b0; A2 = 1'b0; A3 = 1'b1;
      #10;
      // Test case 3
      A0 = 1'b0; A1 = 1'b0; A2 = 1'b1; A3 = 1'b0;
      #10;
      // Test case 4
      A0 = 1'b0; A1 = 1'b0; A2 = 1'b1; A3 = 1'b1;
      #10;
      // Test case 5
      A0 = 1'b0; A1 = 1'b1; A2 = 1'b0; A3 = 1'b0;
      #10;
      // Test case 6
      A0 = 1'b0; A1 = 1'b1; A2 = 1'b0; A3 = 1'b1;
      #10;
      // Test case 7
      A0 = 1'b0; A1 = 1'b1; A2 = 1'b1; A3 = 1'b0;
      #10;
      // Test case 8
      A0 = 1'b0; A1 = 1'b1; A2 = 1'b1; A3 = 1'b1;
      #10;
      // Test case 9
      A0 = 1'b1; A1 = 1'b0; A2 = 1'b0; A3 = 1'b0;
      #10;
      // Test case 10
      A0 = 1'b1; A1 = 1'b0; A2 = 1'b0; A3 = 1'b1;
      #10;
      // Test case 11
      A0 = 1'b1; A1 = 1'b0; A2 = 1'b1; A3 = 1'b0;
      #10;
      // Test case 12
      A0 = 1'b1; A1 = 1'b0; A2 = 1'b1; A3 = 1'b1;
      #10;
      // Test case 13
      A0 = 1'b1; A1 = 1'b1; A2 = 1'b0; A3 = 1'b0;
      #10;
      // Test case 14
      A0 = 1'b1; A1 = 1'b1; A2 = 1'b0; A3 = 1'b1;
      #10;
      // Test case 15
      A0 = 1'b1; A1 = 1'b1; A2 = 1'b1; A3 = 1'b0;
      #10;
      // Test case 16
      A0 = 1'b1; A1 = 1'b1; A2 = 1'b1; A3 = 1'b1;
      // #10;

    // $finish;

    end
  
    initial
    begin
      $display("                Tempo     Entradas LUT        Saídas");
      $display("                         A0  A1  A2  A3         OUT");
      $display("                ====   ================       =======");
      $monitor($time,"     %b  %b  %b  %b               %b", A0, A1, A2, A3, OUT);
    end
  
endmodule

verilog_tests/arch_fpga_asic/tarefa_02/q2/dump.vcd
$version Generated by VerilatedVcd $end
$timescale 1ps $end
 $scope module TOP $end
  $scope module Q2_LUT3_TB $end
   $var wire 1 + A0 $end
   $var wire 1 , A1 $end
   $var wire 1 - A2 $end
   $var wire 1 . A3 $end
   $var wire 1 / OUT $end
   $scope module UUT $end
    $var wire 1 + A0 $end
    $var wire 1 , A1 $end
    $var wire 1 - A2 $end
    $var wire 1 . A3 $end
    $var wire 1 / OUT $end
    $var wire 1 # nor_0_out $end
    $var wire 1 ' nor_1_out $end
    $var wire 1 $ and_0_out $end
    $var wire 1 ( and_1_out $end
    $var wire 1 0 or_0_out $end
    $scope module AND_0_INST $end
     $var wire 1 , A $end
     $var wire 1 - B $end
     $var wire 1 . C $end
     $var wire 1 $ OUT $end
     $scope module AND_0_INST $end
      $var wire 8 3 INIT [7:0] $end
      $var wire 1 , I0 $end
      $var wire 1 - I1 $end
      $var wire 1 . I2 $end
      $var wire 1 $ O $end
      $var wire 1 % tmp $end
     $upscope $end
    $upscope $end
    $scope module AND_1_INST $end
     $var wire 1 + A $end
     $var wire 1 - B $end
     $var wire 1 . C $end
     $var wire 1 ( OUT $end
     $scope module AND_0_INST $end
      $var wire 8 3 INIT [7:0] $end
      $var wire 1 + I0 $end
      $var wire 1 - I1 $end
      $var wire 1 . I2 $end
      $var wire 1 ( O $end
      $var wire 1 ) tmp $end
     $upscope $end
    $upscope $end
    $scope module NOR_0_INST $end
     $var wire 1 , A $end
     $var wire 1 - B $end
     $var wire 1 . C $end
     $var wire 1 # OUT $end
     $scope module OR_0_INST $end
      $var wire 8 4 INIT [7:0] $end
      $var wire 1 , I0 $end
      $var wire 1 - I1 $end
      $var wire 1 . I2 $end
      $var wire 1 # O $end
      $var wire 1 & tmp $end
     $upscope $end
    $upscope $end
    $scope module NOR_1_INST $end
     $var wire 1 + A $end
     $var wire 1 - B $end
     $var wire 1 . C $end
     $var wire 1 ' OUT $end
     $scope module OR_0_INST $end
      $var wire 8 4 INIT [7:0] $end
      $var wire 1 + I0 $end
      $var wire 1 - I1 $end
      $var wire 1 . I2 $end
      $var wire 1 ' O $end
      $var wire 1 * tmp $end
     $upscope $end
    $upscope $end
    $scope module OR_0_INST $end
     $var wire 1 # A $end
     $var wire 1 $ B $end
     $var wire 1 ' C $end
     $var wire 1 0 OUT $end
     $scope module OR_0_INST $end
      $var wire 8 5 INIT [7:0] $end
      $var wire 1 # I0 $end
      $var wire 1 $ I1 $end
      $var wire 1 ' I2 $end
      $var wire 1 0 O $end
      $var wire 1 1 tmp $end
     $upscope $end
    $upscope $end
    $scope module OR_1_INST $end
     $var wire 1 0 A $end
     $var wire 1 ( B $end
     $var wire 1 6 C $end
     $var wire 1 / OUT $end
     $scope module OR_0_INST $end
      $var wire 8 5 INIT [7:0] $end
      $var wire 1 0 I0 $end
      $var wire 1 ( I1 $end
      $var wire 1 6 I2 $end
      $var wire 1 / O $end
      $var wire 1 2 tmp $end
     $upscope $end
    $upscope $end
   $upscope $end
  $upscope $end
 $upscope $end
$enddefinitions $end


#0
1#
0$
0%
0&
1'
0(
0)
0*
0+
0,
0-
0.
1/
10
01
12
b10000000 3
b00000001 4
b11111110 5
06
#10000
0#
1%
1&
0'
1)
1*
1.
0/
00
02
#20000
1-
0.
#30000
0%
0&
0)
0*
1.
#40000
1%
1&
1'
1,
0-
0.
1/
10
11
12
#50000
0%
0&
0'
1)
1*
1.
0/
00
01
02
#60000
1-
0.
#70000
1$
1%
1&
0)
0*
1.
1/
10
11
12
#80000
1#
0$
0%
0&
1)
1*
1+
0,
0-
0.
#90000
0#
1%
1&
0)
0*
1.
0/
00
01
02
#100000
1-
0.
#110000
0%
0&
1(
1)
1*
1.
1/
12
#120000
1%
1&
0(
1,
0-
0.
0/
02
#130000
0%
0&
0)
0*
1.
#140000
1-
0.
#150000
1$
1%
1&
1(
1)
1*
1.
1/
10
11
