arch_digital_sys/lab_01/register_files/register8.sv
`timescale 1ns/1ps
module register8(
    input logic clk, reset,
    input logic [7:0]in_word,
    output logic [7:0]out_word
);

always_ff@(posedge clk)begin
    if (~reset)
        begin
            out_word <= 8'b0;
        end
    else
        begin
            out_word <= in_word;
        end
end

endmodule

arch_digital_sys/lab_01/functional_register_generated/register_v2.sv
/* verilator lint_off DECLFILENAME */
`timescale 1ns/1ps
module register8_bank_v2(
    input logic clk, rst, we3,
    input logic [2:0]wa3,
    input logic [2:0]ra1, ra2,
    input logic [7:0]wd3,
    output logic [7:0] rd1, rd2

);

logic [7:0]X_in_word [7:0]; // Eight 8-bit arrays in a UNPACKED way a.k.a not in a contiguous interval of memory;
logic [7:0]X_out_word [7:0]; // Eight 8-bit arrays in a UNPACKED way a.k.a not in a contiguous interval of memory;

genvar i;
generate
    for(i=0; i<8; i=i+1) begin
        register8 X(.clk(clk), .reset(1'b1), .in_word(X_in_word[i]), .out_word(X_out_word[i]));
    end
endgenerate

always_ff @(posedge clk) begin
    if(~rst) begin
            int ind;
            for(ind=0; ind<8; ind=ind+1) begin
                X_in_word[ind] <= 8'b0;
            end
    end
     
    else if(we3) begin
        X_in_word[wa3] <= wd3;
    end
end


always_comb 
begin
    rd1 = X_out_word[ra1];
    rd2 = X_out_word[ra2];
end



endmodule

arch_digital_sys/lab_01/functional_register_generated/register8_bank_tb.sv
/* verilator lint_off DECLFILENAME */
`timescale 1ns/1ps
module register8_bank_tb();

    logic test_clk, test_reset, we3;
    logic [7:0] wd3;
    logic [2:0] wa3, ra1, ra2;
    logic [7:0] rd1, rd2;


    register8_bank_v2 dut(
        .clk(test_clk),
        .rst(test_reset),
        .we3(we3),
        .wa3(wa3),
        .ra1(ra1),
        .ra2(ra2),
        .wd3(wd3),
        .rd1(rd1),
        .rd2(rd2)
    );

    initial begin
        test_clk = 1'b0;
        forever begin
            #5 test_clk = ~test_clk;
        end
    end

    initial begin
        $dumpfile("register8_bank_tb.vcd");
        $dumpvars(0, register8_bank_tb);
        @(posedge test_clk);
        test_reset = 1'b0;
        #10 
        test_reset = 1'b1;
        #10

        //Test Case 0
        // ra1 = 3'b000;
        // ra2 = 3'b000;
        assert(rd1 == 8'h00 && rd2 == 8'h00) else $fatal(0,"Test Case 0 failed");
        #10


        /* 
             Set #1 of tests: Writing on registers
                Test Cases 1 to 9 covers the writing process on each of the registers, X1 to X7, present on the register bank. 
                Some tests to cover the writing withtou premission cases were also created. 
                Further tests should be presented on the next sets test cases.
        */


        //Test Case 1 - Write to register X1
        @(posedge test_clk);
        we3 = 1'b1;
        wd3 = 8'hAA;
        wa3 = 3'b001;
        ra1 = 3'b001;
        #20
        we3 = 1'b0;
        #30
        assert(rd1 == 8'hAA && rd2 == 8'h00) else $fatal(1, "Test Case 1 failed");


        //Test Case 2 - Write to register X2
        @(posedge test_clk);
        we3 = 1'b1;
        wd3 = 8'hBB;
        wa3 = 3'b010;
        ra2 = 3'b010;
        #20
        we3 = 1'b0;
        assert(rd1 == 8'hAA && rd2 == 8'hBB) else $fatal(2, "Test Case 2 failed");

        //Test Case 3 - Write to register X1 with no permission to write enabled.
        @(posedge test_clk);
        we3 = 1'b0;
        wd3 = 8'hFF;
        wa3 = 3'b001;
        #10
        assert(rd1 == 8'hAA && rd2 == 8'hBB) else $fatal(3, "Test Case 3 failed");

        //Test Case 4 - Write to register X3 with rd2 unchanged from the previous test case.
        @(posedge test_clk);
        we3 = 1'b1;
        wd3 = 8'hCC;
        wa3 = 3'b011; //==> Register X3
        ra1 = 3'b011;
        #20
        we3 = 1'b0;
        assert(rd1 == 8'hCC && rd2 == 8'hBB) else $fatal(4, "Test Case 4 failed");

        //Test Case 5 - Write to register X4 with rd1 unchanged from the previous test case.
        @(posedge test_clk);
        we3 = 1'b1;
        wd3 = 8'hDD;
        wa3 = 3'b100; //==> Register X4
        ra2 = 3'b100;
        #20
        we3 = 1'b0;
        assert(rd1 == 8'hCC && rd2 == 8'hDD) else $fatal(5, "Test Case 5 failed");


        //Test Case 6 - Write to register X4 with no permission to write on it.
        @(posedge test_clk);
        we3 = 1'b0;
        wd3 = 8'hFF;
        wa3 = 3'b100;
        #10
        assert(rd1 == 8'hCC && rd2 == 8'hDD) else $fatal(6, "Test Case 6 failed");

        //Test Case 7 - Write to register X5 with rd2 unchanged from X4 register writing test case.
        @(posedge test_clk);
        we3 = 1'b1;
        wd3 = 8'hEE;
        wa3 = 3'b101; //==> Register X5
        ra1 = 3'b101;
        #20
        we3 = 1'b0;
        assert(rd1 == 8'hEE && rd2 == 8'hDD) else $fatal(7, "Test Case 7 failed");

        //Test Case 8 - Write to register X6 with rd1 unchanged from the previous test case.
        @(posedge test_clk);
        we3 = 1'b1;
        wd3 = 8'hFF;
        wa3 = 3'b110; //==> Register X6
        ra2 = 3'b110;
        #20
        we3 = 1'b0;
        assert(rd1 == 8'hEE && rd2 == 8'hFF) else $fatal(8, "Test Case 8 failed");

        //Test Case 9 - Write to register X7 with rd2 unchanged from the previous test case.
        @(posedge test_clk);
        we3 = 1'b1;
        wd3 = 8'h11;
        wa3 = 3'b111; //==> Register X7
        ra1 = 3'b111;
        #20
        we3 = 1'b0;
        assert(rd1 == 8'h11 && rd2 == 8'hFF) else $fatal(9, "Test Case 9 failed");


        /*
            Set #2: Reading from the previous set registers.
                This set of test cases covers the reading of the values previously set on the register
                of the register bank being tested.
                All the values read must match the values set on the test cases above.
        */

        //Test Case 10 - Reading the current value from the registers X1 and X2
        @(posedge test_clk);
        ra1 = 3'b001; //Register X1
        ra2 = 3'b010; //Register X2
        #10
        assert(rd1 == 8'hAA && rd2 == 8'hBB) else $fatal(10, "Test Case 10 failed");

        //Test Case 11 - Reading the current value from the registers X3 and X4
        @(posedge test_clk);
        ra1 = 3'b011; //Register X3
        ra2 = 3'b100; //Register X4
        #10
        assert(rd1 == 8'hCC && rd2 == 8'hDD) else $fatal(11, "Test Case 11 failed");

        //Test Case 12 - Reading the current value from the registers X5 and X6
        @(posedge test_clk);
        ra1 = 3'b101; //Register X5
        ra2 = 3'b110; //Register X6
        #10
        assert(rd1 == 8'hEE && rd2 == 8'hFF) else $fatal(12, "Test Case 12 failed");

        //Test Case 13 - Reading the current value from the registers X7 and X0
        @(posedge test_clk);
        ra1 = 3'b111; //Register X7
        ra2 = 3'b000; //Register X1
        #10
        assert(rd1 == 8'h11 && rd2 == 8'h00) else $fatal(13, "Test Case 13 failed");

        /* 
            Set#3: Resetting all the registers from the register bank
                The next set of tests covers a bulk reset on all of the registers from the
                register bank under test, followed by assertions that the registers were
                zeroed indeed.
        */

        @(posedge test_clk);
        //Setting the reset process.
        test_reset = 1'b0;
        we3 = 1'b0;
        #10
        test_reset = 1'b1;
        $display($time, "HERE");
        #10

        //Test Case 14 - Reading the current value from the registers X1 and X2 after the reset process.
        @(posedge test_clk);
        ra1 = 3'b001; //Register X1
        ra2 = 3'b010; //Register X2
        #10
        assert(rd1 == 8'h00 && rd2 == 8'h00) else $fatal(14, "Test Case 14 failed ", $time);

        //Test Case 15 - Reading the current value from the registers X3 and X4 after the reset process.
        @(posedge test_clk);
        ra1 = 3'b011; //Register X3
        ra2 = 3'b100; //Register X4
        #10
        assert(rd1 == 8'h00 && rd2 == 8'h00) else $fatal(15, "Test Case 15 failed");

        //Test Case 16 - Reading the current value from the registers X5 and X6 after the reset process.
        @(posedge test_clk);
        ra1 = 3'b101; //Register X5
        ra2 = 3'b110; //Register X6
        #10
        assert(rd1 == 8'h00 && rd2 == 8'h00) else $fatal(16, "Test Case 16 failed");

        //Test Case 17 - Reading the current value from the registers X7 and X1 after the reset process.
        @(posedge test_clk);
        ra1 = 3'b111; //Register X7
        ra2 = 3'b000; //Register X0
        #10
        $display($time, "HERE");
        assert(rd1 == 8'h00 && rd2 == 8'h00) else $fatal(17, "Test Case 17 failed");

        #10; 
        $display($time, "HERE");
        $finish;
    end

    initial
    begin
      $display("                Tempo               Entradas LUT                                    Saídas");
      $display("                         clk  rst  we3   wa3   ra1    ra2        wd3                rd1         rd2");
      $display("                ====   =================================================        =====================");
      /* $monitor($time,"      %b    %b    %b    %b   %b    %b      %b         %b      %b", test_clk, test_reset, we3, 
                                                                    wa3, ra1, ra2, wd3, 
                                                                    rd1, rd2);
 */    end

    always@(posedge test_clk)begin
      $display($time,"      %b    %b    %b    %b   %b    %b      %b         %b      %b", test_clk, test_reset, we3, 
                                                                    wa3, ra1, ra2, wd3, 
                                                                    rd1, rd2);
    end



endmodule

arch_digital_sys/lab_01/functional_register_generated/register8_bank_tb.vcd
$version Generated by VerilatedVcd $end
$timescale 1ps $end
 $scope module TOP $end
  $scope module register8_bank_tb $end
   $var wire 1 J test_clk $end
   $var wire 1 # test_reset $end
   $var wire 1 $ we3 $end
   $var wire 8 % wd3 [7:0] $end
   $var wire 3 & wa3 [2:0] $end
   $var wire 3 ' ra1 [2:0] $end
   $var wire 3 ( ra2 [2:0] $end
   $var wire 8 K rd1 [7:0] $end
   $var wire 8 L rd2 [7:0] $end
   $scope module dut $end
    $var wire 1 J clk $end
    $var wire 1 # rst $end
    $var wire 1 $ we3 $end
    $var wire 3 & wa3 [2:0] $end
    $var wire 3 ' ra1 [2:0] $end
    $var wire 3 ( ra2 [2:0] $end
    $var wire 8 % wd3 [7:0] $end
    $var wire 8 K rd1 [7:0] $end
    $var wire 8 L rd2 [7:0] $end
    $var wire 8 ) X_in_word[0] [7:0] $end
    $var wire 8 * X_in_word[1] [7:0] $end
    $var wire 8 + X_in_word[2] [7:0] $end
    $var wire 8 , X_in_word[3] [7:0] $end
    $var wire 8 - X_in_word[4] [7:0] $end
    $var wire 8 . X_in_word[5] [7:0] $end
    $var wire 8 / X_in_word[6] [7:0] $end
    $var wire 8 0 X_in_word[7] [7:0] $end
    $var wire 8 1 X_out_word[0] [7:0] $end
    $var wire 8 2 X_out_word[1] [7:0] $end
    $var wire 8 3 X_out_word[2] [7:0] $end
    $var wire 8 4 X_out_word[3] [7:0] $end
    $var wire 8 5 X_out_word[4] [7:0] $end
    $var wire 8 6 X_out_word[5] [7:0] $end
    $var wire 8 7 X_out_word[6] [7:0] $end
    $var wire 8 8 X_out_word[7] [7:0] $end
    $scope module genblk1[0] $end
     $scope module X $end
      $var wire 1 J clk $end
      $var wire 1 M reset $end
      $var wire 8 9 in_word [7:0] $end
      $var wire 8 : out_word [7:0] $end
     $upscope $end
    $upscope $end
    $scope module genblk1[1] $end
     $scope module X $end
      $var wire 1 J clk $end
      $var wire 1 M reset $end
      $var wire 8 ; in_word [7:0] $end
      $var wire 8 < out_word [7:0] $end
     $upscope $end
    $upscope $end
    $scope module genblk1[2] $end
     $scope module X $end
      $var wire 1 J clk $end
      $var wire 1 M reset $end
      $var wire 8 = in_word [7:0] $end
      $var wire 8 > out_word [7:0] $end
     $upscope $end
    $upscope $end
    $scope module genblk1[3] $end
     $scope module X $end
      $var wire 1 J clk $end
      $var wire 1 M reset $end
      $var wire 8 ? in_word [7:0] $end
      $var wire 8 @ out_word [7:0] $end
     $upscope $end
    $upscope $end
    $scope module genblk1[4] $end
     $scope module X $end
      $var wire 1 J clk $end
      $var wire 1 M reset $end
      $var wire 8 A in_word [7:0] $end
      $var wire 8 B out_word [7:0] $end
     $upscope $end
    $upscope $end
    $scope module genblk1[5] $end
     $scope module X $end
      $var wire 1 J clk $end
      $var wire 1 M reset $end
      $var wire 8 C in_word [7:0] $end
      $var wire 8 D out_word [7:0] $end
     $upscope $end
    $upscope $end
    $scope module genblk1[6] $end
     $scope module X $end
      $var wire 1 J clk $end
      $var wire 1 M reset $end
      $var wire 8 E in_word [7:0] $end
      $var wire 8 F out_word [7:0] $end
     $upscope $end
    $upscope $end
    $scope module genblk1[7] $end
     $scope module X $end
      $var wire 1 J clk $end
      $var wire 1 M reset $end
      $var wire 8 G in_word [7:0] $end
      $var wire 8 H out_word [7:0] $end
     $upscope $end
    $upscope $end
    $scope module unnamedblk1 $end
     $var wire 32 I ind [31:0] $end
    $upscope $end
   $upscope $end
  $upscope $end
 $upscope $end
$enddefinitions $end


#0
0#
0$
b00000000 %
b000 &
b000 '
b000 (
b00000000 )
b00000000 *
b00000000 +
b00000000 ,
b00000000 -
b00000000 .
b00000000 /
b00000000 0
b00000000 1
b00000000 2
b00000000 3
b00000000 4
b00000000 5
b00000000 6
b00000000 7
b00000000 8
b00000000 9
b00000000 :
b00000000 ;
b00000000 <
b00000000 =
b00000000 >
b00000000 ?
b00000000 @
b00000000 A
b00000000 B
b00000000 C
b00000000 D
b00000000 E
b00000000 F
b00000000 G
b00000000 H
b00000000000000000000000000000000 I
0J
b00000000 K
b00000000 L
1M
#5000
b00000000000000000000000000001000 I
1J
#10000
0J
#15000
1#
1J
#20000
0J
#25000
1J
#30000
0J
#35000
1J
#40000
0J
#45000
1$
b10101010 %
b001 &
b001 '
b10101010 *
b10101010 ;
1J
#50000
0J
#55000
b10101010 2
b10101010 <
1J
b10101010 K
#60000
0J
#65000
0$
1J
#70000
0J
#75000
1J
#80000
0J
#85000
1J
#90000
0J
#95000
1J
#100000
0J
#105000
1$
b10111011 %
b010 &
b010 (
b10111011 +
b10111011 =
1J
#110000
0J
#115000
b10111011 3
b10111011 >
1J
b10111011 L
#120000
0J
#125000
0$
1J
#130000
0J
#135000
b11111111 %
b001 &
1J
#140000
0J
#145000
1J
#150000
0J
#155000
1$
b11001100 %
b011 &
b011 '
b11001100 ,
b11001100 ?
1J
b00000000 K
#160000
0J
#165000
b11001100 4
b11001100 @
1J
b11001100 K
#170000
0J
#175000
0$
1J
#180000
0J
#185000
1$
b11011101 %
b100 &
b100 (
b11011101 -
b11011101 A
1J
b00000000 L
#190000
0J
#195000
b11011101 5
b11011101 B
1J
b11011101 L
#200000
0J
#205000
0$
1J
#210000
0J
#215000
b11111111 %
1J
#220000
0J
#225000
1J
#230000
0J
#235000
1$
b11101110 %
b101 &
b101 '
b11101110 .
b11101110 C
1J
b00000000 K
#240000
0J
#245000
b11101110 6
b11101110 D
1J
b11101110 K
#250000
0J
#255000
0$
1J
#260000
0J
#265000
1$
b11111111 %
b110 &
b110 (
b11111111 /
b11111111 E
1J
b00000000 L
#270000
0J
#275000
b11111111 7
b11111111 F
1J
b11111111 L
#280000
0J
#285000
0$
1J
#290000
0J
#295000
1$
b00010001 %
b111 &
b111 '
b00010001 0
b00010001 G
1J
b00000000 K
#300000
0J
#305000
b00010001 8
b00010001 H
1J
b00010001 K
#310000
0J
#315000
0$
1J
#320000
0J
#325000
b001 '
b010 (
1J
b10101010 K
b10111011 L
#330000
0J
#335000
1J
#340000
0J
#345000
b011 '
b100 (
1J
b11001100 K
b11011101 L
#350000
0J
#355000
1J
#360000
0J
#365000
b101 '
b110 (
1J
b11101110 K
b11111111 L
#370000
0J
#375000
1J
#380000
0J
#385000
b111 '
b000 (
1J
b00010001 K
b00000000 L
#390000
0J
#395000
1J
#400000
0J
#405000
0#
b00000000 *
b00000000 +
b00000000 ,
b00000000 -
b00000000 .
b00000000 /
b00000000 0
b00000000 ;
b00000000 =
b00000000 ?
b00000000 A
b00000000 C
b00000000 E
b00000000 G
1J
#410000
0J
#415000
1#
b00000000 2
b00000000 3
b00000000 4
b00000000 5
b00000000 6
b00000000 7
b00000000 8
b00000000 <
b00000000 >
b00000000 @
b00000000 B
b00000000 D
b00000000 F
b00000000 H
1J
b00000000 K
#420000
0J
#425000
1J
#430000
0J
#435000
b001 '
b010 (
1J
#440000
0J
#445000
1J
#450000
0J
#455000
b011 '
b100 (
1J
#460000
0J
#465000
1J
#470000
0J
#475000
b101 '
b110 (
1J
#480000
0J
#485000
1J
#490000
0J
#495000
b111 '
b000 (
1J
