hdl_intro_files/practice_04/custom_ula.sv
`timescale 1ns/1ps
module custom_ula(
    input logic [7:0] SrcA, SrcB,
    input logic [2:0] ULAControl,
    output logic [7:0] ULAResult,
    output logic FlagZ
);

always_comb begin
    case(ULAControl)
        3'b000: //Adds
            begin
                ULAResult = SrcA + SrcB;
                FlagZ = (ULAResult == 8'b0) ? 1'b1 : 1'b0;
            end
        3'b001: //Subtracts
            begin
                ULAResult = SrcA + ~SrcB + 1;
                FlagZ = (ULAResult == 8'b0) ? 1'b1 : 1'b0;
            end
        3'b010: //ANDs
            begin
                ULAResult = SrcA & SrcB;
                FlagZ = (ULAResult == 8'b0) ? 1'b1 : 1'b0;
            end
        3'b011: //ORs
            begin
                ULAResult = SrcA | SrcB;
                FlagZ = (ULAResult == 8'b0) ? 1'b1 : 1'b0;
            end
        3'b101: //Sets less than (SLT)
            begin
                ULAResult = (SrcA < SrcB) ? 8'hFF : 8'h00;
                FlagZ = (ULAResult == 8'b0) ? 1'b1 : 1'b0;
            end

        default:
            begin
                ULAResult = 8'b0;
                FlagZ = 1'b1;
            end
    endcase
    
end

endmodule

hdl_intro_files/practice_04/muxULAsrc.sv
`timescale 1ns/1ps

module muxULAsrc(
    input logic select_src,
    input logic [7:0] w_rd2, constante,
    output logic [7:0] w_SrcB
);

always_comb 
begin
    w_SrcB = select_src ? constante : w_rd2;
end


endmodule

hdl_intro_files/practice_04/register8.sv
`timescale 1ns/1ps
module register8(
    input logic clk, reset,
    input logic [7:0]in_word,
    output logic [7:0]out_word
);

always_ff@(posedge clk)begin
    if (reset)
        begin
            out_word <= 8'b0;
        end
    else
        begin
            out_word <= in_word;
        end
end

endmodule

hdl_intro_files/practice_04/register8_bank.sv
`timescale 1ns/1ps
module register8_bank(
    input logic clk, rst, we3,
    input logic [2:0]wa3,
    input logic [2:0]ra1, ra2,
    input logic [7:0]wd3,
    output logic [7:0] rd1, rd2

);

logic [7:0]X_in_word [7:0]; // Eight 8-bit arrays in a UNPACKED way a.k.a not in a contiguous interval of memory;
logic [7:0]X_out_word [7:0]; // Eight 8-bit arrays in a UNPACKED way a.k.a not in a contiguous interval of memory;

genvar i;
generate
    for(i=0; i<8; i=i+1) begin
        register8 X(.clk(clk), .reset(1'b1), .in_word(X_in_word[i]), .out_word(X_out_word[i]));
    end
endgenerate

always_ff @(posedge clk) begin
    if(~rst) begin
            int ind;
            for(ind=0; ind<8; ind=ind+1) begin
                X_in_word[ind] <= 8'b0;
            end
    end
     
    else if(we3) begin
        X_in_word[wa3] <= wd3;
    end
end


always_comb 
begin
    rd1 = X_out_word[ra1];
    rd2 = X_out_word[ra2];
end



endmodule

hdl_intro_files/practice_04/datapath101.sv
`timescale 1ns/1ps

module datapath101(
    input logic [2:0]ra1,
    input logic [2:0]ra2,
    input logic [2:0]wa3,
    input logic we3,
    input logic [7:0]wd3,
    input logic [7:0]constante,
    input logic [2:0]ULAControl,
    input logic select_src,
    
    input logic clk, rst,

    output logic [7:0] ULAResult,
    output logic FlagZ

);

logic [7:0] w_rd1SrcA;
logic [7:0] w_rd2;
logic [7:0] w_SrcB;

register8_bank reg8_bank_inst(
    .clk(clk),
    .rst(rst),
    .we3(we3),
    .wa3(wa3),
    .ra1(ra1),
    .ra2(ra2),
    .wd3(wd3),
    .rd1(w_rd1SrcA),
    .rd2(w_rd2)
);

muxULAsrc muxULAsrc_inst(
    .select_src(select_src),
    .constante(constante),
    .w_rd2(w_rd2),
    .w_SrcB(w_SrcB)
);

custom_ula ula_inst(
    .SrcA(w_rd1SrcA),
    .SrcB(w_SrcB),
    .ULAControl(ULAControl),
    .ULAResult(ULAResult),
    .FlagZ(FlagZ)
);




    
endmodule

hdl_intro_files/practice_04/datapath101_tb.sv
`timescale 1ns/1ps
module datapath101_tb();

    logic [2:0] mocked_ra1 = 3'b000;
    logic [2:0] mocked_ra2 = 3'b000;
    logic[2:0] mocked_wa3 = 3'b000;
    logic mocked_we3 = 1'b0;
    logic [7:0] mocked_wd3 = 'b0;
    logic [7:0] mock_constante = 'b0;
    logic [2:0] mock_ULAControl = 3'b000;
    logic mock_select_src = 1'b0;

    logic test_clk, test_reset;
    logic [7:0] dut_ULAResult;
    logic dut_FlagZ;
    
    datapath101 DUT(
        .ra1(mocked_ra1),
        .ra2(mocked_ra2),
        .wa3(mocked_wa3),
        .we3(mocked_we3),
        .wd3(mocked_wd3),
        .constante(mock_constante),
        .ULAControl(mock_ULAControl),
        .select_src(mock_select_src),

        .clk(test_clk),
        .rst(test_reset),
        
        .ULAResult(dut_ULAResult),
        .FlagZ(dut_FlagZ)
    );

    initial begin
        test_clk = 1'b0;
        forever begin
            #5 test_clk = ~test_clk;
        end
    end

    initial begin
        $dumpfile("datapath101_tb.vcd");
        $dumpvars(0, datapath101_tb);

        @(posedge test_clk);
        test_reset = 1'b0;
        #10 
        test_reset = 1'b1;
        #10

        //Test Case 0
        assert(dut_ULAResult == 8'h00 && dut_FlagZ == 1'b1 && DUT.w_rd1SrcA == 8'b0) else $fatal(0, "Test Case 0 failed");
        #10


        /* 
             Set #1 of tests: Writing on registers
                Test Cases 1 to 9 covers the writing process on each of the registers, X1 to X7, present on the register bank. 
                Some tests to cover the writing withtou premission cases were also created. 
                Further tests should be presented on the next sets test cases.
        */


        //Test Case 1 - Write to register X1
        @(posedge test_clk);
        mocked_we3 = 1'b1;
        mocked_wd3 = 8'h5A;
        mocked_wa3 = 3'b001; //==> Register X1
        #30
        mocked_we3 = 1'b0;
        assert(dut_ULAResult == 8'h00 && dut_FlagZ == 1'b1) else $fatal(1, "Test Case 1 failed");

        
        //Test Case 2 - Write to register X2
        @(posedge test_clk);
        mocked_we3 = 1'b1;
        mocked_wd3 = 8'h5B;
        mocked_wa3 = 3'b010;   //==> Register X2
        #20
        mocked_we3 = 1'b0;
        assert(dut_ULAResult == 8'h00 && dut_FlagZ == 1'b1) else $fatal(2, "Test Case 2 failed");

        //Test Case 3 - Write to register X3.
        @(posedge test_clk);
        mocked_we3 = 1'b1;
        mocked_wd3 = 8'h5C;
        mocked_wa3 = 3'b011; //==> Register X3
        #20
        mocked_we3 = 1'b0;
        assert(dut_ULAResult == 8'h00 && dut_FlagZ == 1'b1) else $fatal(3, "Test Case 3 failed");
        
        //Test Case 4 - Write to register X4 with rd1 unchanged from the previous test case.
        @(posedge test_clk);
        mocked_we3 = 1'b1;
        mocked_wd3 = 8'h5D;
        mocked_wa3 = 3'b100; //==> Register X4
        #20
        mocked_we3 = 1'b0;
        assert(dut_ULAResult == 8'h00 && dut_FlagZ == 1'b1) else $fatal(4, "Test Case 4 failed");

        //Test Case 5 - Write to register X5.
        @(posedge test_clk);
        mocked_we3 = 1'b1;
        mocked_wd3 = 8'h5E;
        mocked_wa3 = 3'b101; //==> Register X5
        #20
        mocked_we3 = 1'b0;
        assert(dut_ULAResult == 8'h00 && dut_FlagZ == 1'b1) else $fatal(5, "Test Case 5 failed");

        //Test Case 6 - Write to register X6.
        @(posedge test_clk);
        mocked_we3 = 1'b1;
        mocked_wd3 = 8'h5F;
        mocked_wa3 = 3'b110; //==> Register X6
        #20
        mocked_we3 = 1'b0;
        assert(dut_ULAResult == 8'h00 && dut_FlagZ == 1'b1) else $fatal(6, "Test Case 6 failed");

        //Test Case 6 - Write to register X7.
        @(posedge test_clk);
        mocked_we3 = 1'b1;
        mocked_wd3 = 8'h50;
        mocked_wa3 = 3'b111; //==> Register X7
        #20
        mocked_we3 = 1'b0;
        assert(dut_ULAResult == 8'h00 && dut_FlagZ == 1'b1) else $fatal(6, "Test Case 6 failed");

        

        /*
            Set #2: Adding two numbers previously stored on registers.
                This set of test cases aims to verify the correctness of the addition
                arithmetic operation between two numbers previously stored on the register bank.
        */
        
        //Test Case 7 - Reading and adding the values from registers X1 and X2
        @(posedge test_clk);
        mocked_ra1 = 3'b001; //==> Register X1
        mocked_ra2 = 3'b010; //==> Register X2
        mock_select_src = 1'b0;
        mock_ULAControl = 3'b000; //==> Addition operation
        $display("HERE: ", $time);
        #30
        assert(dut_ULAResult == 8'hB5 && dut_FlagZ == 1'b0) else $fatal(7, "Test Case 7 failed ", $time);

        //Test Case 8 - Reading and adding the values from registers X3 and X4
        @(posedge test_clk);
        mocked_ra1 = 3'b011; //==> Register X3
        mocked_ra2 = 3'b100; //==> Register X4
        mock_select_src = 1'b0;
        mock_ULAControl = 3'b000; //==> Addition operation
        #10
        assert(dut_ULAResult == 8'hB9 && dut_FlagZ == 1'b0) else $fatal(8, "Test Case 8 failed");

        //Test Case 9 - Reading and adding the values from registers X5 and X6
        @(posedge test_clk);
        mocked_ra1 = 3'b101; //==> Register X5
        mocked_ra2 = 3'b110; //==> Register X6
        mock_select_src = 1'b0;
        mock_ULAControl = 3'b000; //==> Addition operation
        #10
        assert(dut_ULAResult == 8'hBD && dut_FlagZ == 1'b0) else $fatal(9, "Test Case 9 failed");

        //Test Case 10 - Reading and adding the values from registers X7 and X0
        @(posedge test_clk);
        mocked_ra1 = 3'b111; //==> Register X7
        mocked_ra2 = 3'b000; //==> Register X0
        mock_select_src = 1'b0;
        mock_ULAControl = 3'b000; //==> Addition operation
        #10
        assert(dut_ULAResult == 8'h50 && dut_FlagZ == 1'b0) else $fatal(10, "Test Case 10 failed");

        //Test Case 11 - Reading and adding the values from registers X7 and variable constante
        @(posedge test_clk);
        mocked_ra1 = 3'b111; //==> Register X7
        mock_constante = 8'hAF; //==> Constant value
        mock_select_src = 1'b1; //==> Selecting the constant value
        mock_ULAControl = 3'b000; //==> Addition operation
        #10
        assert(dut_ULAResult == 8'hFF && dut_FlagZ == 1'b0) else $fatal(11, "Test Case 11 failed");

        /* 
            Set#3: Subtraction between two numbers previously stored on registers.
                This set of test cases aims to verify the correctness of the subtraction
                arithmetic operation between two numbers previously stored on the register bank.
        */

        //Test Case 12 - Reading and subtracting the values from registers X3 and X1 where X1 < X3
        @(posedge test_clk);
        mocked_ra1 = 3'b011; //==> Register X3
        mocked_ra2 = 3'b001; //==> Register X1
        mock_select_src = 1'b0;
        mock_ULAControl = 3'b001; //==> Subtraction operation
        #10
        assert(dut_ULAResult == 8'h02 && dut_FlagZ == 1'b0) else $fatal(12, "Test Case 12 failed");

        //Test Case 13 - Reading and subtracting the values from registers X1 and X3 where X1 < X3
        @(posedge test_clk);
        mocked_ra1 = 3'b001; //==> Register X1
        mocked_ra2 = 3'b011; //==> Register X3
        mock_select_src = 1'b0;
        mock_ULAControl = 3'b001; //==> Subtraction operation
        #10
        assert(dut_ULAResult == 8'hFE && dut_FlagZ == 1'b0) else $fatal(13, "Test Case 13 failed");

        //Test Case 14 - Reading and subtracting the values from registers X3 and variable constante
        //               where X3 > constante.
        @(posedge test_clk);
        mocked_ra1 = 3'b011; //==> Register X3
        mock_constante = 8'h40; //==> Constant value
        mock_select_src = 1'b1; //==> Selecting the constant value
        mock_ULAControl = 3'b001; //==> Subtraction operation
        #10
        assert(dut_ULAResult == 8'h1C && dut_FlagZ == 1'b0) else $fatal(14, "Test Case 14 failed");

        //Test Case 15 - Reading and subtracting the values from registers X3 and variable constante
        //               where X3 < constante.
        @(posedge test_clk);
        mocked_ra1 = 3'b011; //==> Register X3
        mock_constante = 8'h60; //==> Constant value
        mock_select_src = 1'b1; //==> Selecting the constant value
        mock_ULAControl = 3'b001; //==> Subtraction operation
        #10
        assert(dut_ULAResult == 8'hFC && dut_FlagZ == 1'b0) else $fatal(15, "Test Case 15 failed");


        /* 
            Set#4: Logical AND between two numbers previously stored on registers.
                This set of test cases aims to verify the correctness of the logical AND
                operation between two numbers previously stored on the register bank.
        */

        //Test Case 16 - Reading and ANDing the values from registers X5 and X2
        @(posedge test_clk);
        mocked_ra1 = 3'b101; //==> Register X5
        mocked_ra2 = 3'b010; //==> Register X2
        mock_select_src = 1'b0;
        mock_ULAControl = 3'b010; //==> AND operation
        #10
        assert(dut_ULAResult == 8'h5A && dut_FlagZ == 1'b0) else $fatal(16, "Test Case 16 failed");

        //Test Case 17 - Reading and ANDing the values from registers X0 and X5
        @(posedge test_clk);
        mocked_ra1 = 3'b000; //==> Register X0
        mocked_ra2 = 3'b101; //==> Register X5
        mock_select_src = 1'b0;
        mock_ULAControl = 3'b010; //==> AND operation
        #10
        assert(dut_ULAResult == 8'h00 && dut_FlagZ == 1'b1) else $fatal(17, "Test Case 17 failed");

        //Test Case 18 - Reading and ANDing the values from registers X4 and variable constante
        //               where constante == 0xFF
        @(posedge test_clk);
        mocked_ra1 = 3'b100; //==> Register X4
        mock_select_src = 1'b1; // ==> Select constante value
        mock_constante = 8'hFF; //==> Constant value
        mock_ULAControl = 3'b010; //==> AND operation
        #10
        assert(dut_ULAResult == 8'h5D && dut_FlagZ == 1'b0) else $fatal(18, "Test Case 18 failed");

        //Test Case 19 - Reading and ANDing the values from registers X4 and variable constante
        //               where constante == 0x00
        @(posedge test_clk);
        mocked_ra1 = 3'b100; //==> Register X4
        mock_select_src = 1'b1; // ==> Select constante value
        mock_constante = 8'h00; //==> Constant value
        mock_ULAControl = 3'b010; //==> AND operation
        #10
        assert(dut_ULAResult == 8'h00 && dut_FlagZ == 1'b1) else $fatal(19, "Test Case 19 failed");

        /* 
            Set #5: Logical OR between two numbers previously stored on registers.
                This set of test cases aims to verify the correctness of the logical AND
                operation between two numbers previously stored on the register bank.
        */

        //Test Case 20 - Reading and ORing the values from registers X6 and X2
        @(posedge test_clk);
        mocked_ra1 = 3'b110; //==> Register X6
        mocked_ra2 = 3'b010; //==> Register X2
        mock_select_src = 1'b0;
        mock_ULAControl = 3'b011; //==> OR operation
        #10
        assert(dut_ULAResult == 8'h5F && dut_FlagZ == 1'b0) else $fatal(20, "Test Case 20 failed");

        //Test Case 21 - Reading and ORing the values from registers X1 and X4
        @(posedge test_clk);
        mocked_ra1 = 3'b001; //==> Register X1
        mocked_ra2 = 3'b100; //==> Register X4
        mock_select_src = 1'b0;
        mock_ULAControl = 3'b011; //==> OR operation
        #10
        assert(dut_ULAResult == 8'h5F && dut_FlagZ == 1'b0) else $fatal(21, "Test Case 21 failed");

        //Test Case 22 - Reading and ORing the values from registers X3 and variable constante
        //               where constante == 0xFF
        @(posedge test_clk);
        mocked_ra1 = 3'b011; //==> Register X3
        mock_select_src = 1'b1; // ==> Select constante value
        mock_constante = 8'hFF; //==> Constant value
        mock_ULAControl = 3'b011; //==> OR operation
        #10
        assert(dut_ULAResult == 8'hFF && dut_FlagZ == 1'b0) else $fatal(22, "Test Case 22 failed");

        //Test Case 23 - Reading and ORing the values from registers X6 and variable constante
        //               where constante == 0x00
        @(posedge test_clk);
        mocked_ra1 = 3'b110; //==> Register X6
        mock_select_src = 1'b1; // ==> Select constante value
        mock_constante = 8'h00; //==> Constant value
        mock_ULAControl = 3'b011; //==> OR operation
        #10
        assert(dut_ULAResult == 8'h5F && dut_FlagZ == 1'b0) else $fatal(23, "Test Case 23 failed");

        /* 
            Set #6: Sets less than (SLT) between two numbers previously stored on registers.
                This set of test cases aims to verify the correctness of the SLT
                operation between two numbers previously stored on the register bank.
        */

        //Test Case 24 - Reading and SLT the values from registers X6 and X4
        @(posedge test_clk);
        mocked_ra1 = 3'b110; //==> Register X6
        mocked_ra2 = 3'b100; //==> Register X4
        mock_select_src = 1'b0;
        mock_ULAControl = 3'b101; //==> SLT operation
        #10
        assert(dut_ULAResult == 8'h00 && dut_FlagZ == 1'b1) else $fatal(24, "Test Case 24 failed");

        //Test Case 25 - Reading and SLT the values from registers X4 and X6
        @(posedge test_clk);
        mocked_ra1 = 3'b100; //==> Register X4
        mocked_ra2 = 3'b110; //==> Register X6
        mock_select_src = 1'b0;
        mock_ULAControl = 3'b101; //==> SLT operation
        #10
        assert(dut_ULAResult == 8'hFF && dut_FlagZ == 1'b0) else $fatal(25, "Test Case 25 failed");

        //Test Case 26 - Reading and SLT the values from registers X3 and variable constante
        //               where constante == 0xFF
        @(posedge test_clk);
        mocked_ra1 = 3'b011; //==> Register X3
        mock_select_src = 1'b1; // ==> Select constante value
        mock_constante = 8'hFF; //==> Constant value
        mock_ULAControl = 3'b101; //==> SLT operation
        #10
        assert(dut_ULAResult == 8'hFF && dut_FlagZ == 1'b0) else $fatal(26, "Test Case 26 failed");

        //Test Case 27 - Reading and SLT the values from registers X7 and variable constante
        //               where constante == 0x00
        @(posedge test_clk);
        mocked_ra1 = 3'b111; //==> Register X7
        mock_select_src = 1'b1; // ==> Select constante value
        mock_constante = 8'h00; //==> Constant value
        mock_ULAControl = 3'b101; //==> SLT operation
        #10
        assert(dut_ULAResult == 8'h00 && dut_FlagZ == 1'b1) else $fatal(27, "Test Case 27 failed");

        #10 $finish;
    end

    initial
    begin
      $display("                Tempo               Entradas LUT                                                                                                                            Saídas");
      $display("                         clk  rst  mocked_we3   mocked_wa3   mocked_ra1  mocked_ra2     mocked_wd3   mock_constante    mock_select_src     mock_ULAControl              Result   FlagZ");
      $display("                ====   ====================================================================================================================================   |   ==========================");
      /* $monitor($time,"      %b    %b    %b    %b   %b    %b      %b         %b      %b", test_clk, test_reset, mocked_we3, 
                                                                    mocked_wa3, mocked_ra1, mocked_ra2, mocked_wd3, 
                                                                    rd1, rd2);
 */    end

    always@(posedge test_clk or negedge test_clk)begin
      $display($time,"      %b    %b        %b          %b           %b         %b            %h            %h                  %b                  %b          |           %h      %b", 
                                                                    test_clk, test_reset, mocked_we3, 
                                                                    mocked_wa3, mocked_ra1, mocked_ra2, mocked_wd3, mock_constante, 
                                                                    mock_select_src, mock_ULAControl, dut_ULAResult, dut_FlagZ);
    end



endmodule

hdl_intro_files/practice_04/datapath101_tb.vcd
$version Generated by VerilatedVcd $end
$timescale 1ps $end
 $scope module TOP $end
  $scope module datapath101_tb $end
   $var wire 3 # mocked_ra1 [2:0] $end
   $var wire 3 $ mocked_ra2 [2:0] $end
   $var wire 3 % mocked_wa3 [2:0] $end
   $var wire 1 & mocked_we3 $end
   $var wire 8 ' mocked_wd3 [7:0] $end
   $var wire 8 ( mock_constante [7:0] $end
   $var wire 3 ) mock_ULAControl [2:0] $end
   $var wire 1 * mock_select_src $end
   $var wire 1 M test_clk $end
   $var wire 1 + test_reset $end
   $var wire 8 N dut_ULAResult [7:0] $end
   $var wire 1 O dut_FlagZ $end
   $scope module DUT $end
    $var wire 3 # ra1 [2:0] $end
    $var wire 3 $ ra2 [2:0] $end
    $var wire 3 % wa3 [2:0] $end
    $var wire 1 & we3 $end
    $var wire 8 ' wd3 [7:0] $end
    $var wire 8 ( constante [7:0] $end
    $var wire 3 ) ULAControl [2:0] $end
    $var wire 1 * select_src $end
    $var wire 1 M clk $end
    $var wire 1 + rst $end
    $var wire 8 N ULAResult [7:0] $end
    $var wire 1 O FlagZ $end
    $var wire 8 P w_rd1SrcA [7:0] $end
    $var wire 8 Q w_rd2 [7:0] $end
    $var wire 8 R w_SrcB [7:0] $end
    $scope module muxULAsrc_inst $end
     $var wire 1 * select_src $end
     $var wire 8 Q w_rd2 [7:0] $end
     $var wire 8 ( constante [7:0] $end
     $var wire 8 R w_SrcB [7:0] $end
    $upscope $end
    $scope module reg8_bank_inst $end
     $var wire 1 M clk $end
     $var wire 1 + rst $end
     $var wire 1 & we3 $end
     $var wire 3 % wa3 [2:0] $end
     $var wire 3 # ra1 [2:0] $end
     $var wire 3 $ ra2 [2:0] $end
     $var wire 8 ' wd3 [7:0] $end
     $var wire 8 P rd1 [7:0] $end
     $var wire 8 Q rd2 [7:0] $end
     $var wire 8 , X_in_word[0] [7:0] $end
     $var wire 8 - X_in_word[1] [7:0] $end
     $var wire 8 . X_in_word[2] [7:0] $end
     $var wire 8 / X_in_word[3] [7:0] $end
     $var wire 8 0 X_in_word[4] [7:0] $end
     $var wire 8 1 X_in_word[5] [7:0] $end
     $var wire 8 2 X_in_word[6] [7:0] $end
     $var wire 8 3 X_in_word[7] [7:0] $end
     $var wire 8 4 X_out_word[0] [7:0] $end
     $var wire 8 5 X_out_word[1] [7:0] $end
     $var wire 8 6 X_out_word[2] [7:0] $end
     $var wire 8 7 X_out_word[3] [7:0] $end
     $var wire 8 8 X_out_word[4] [7:0] $end
     $var wire 8 9 X_out_word[5] [7:0] $end
     $var wire 8 : X_out_word[6] [7:0] $end
     $var wire 8 ; X_out_word[7] [7:0] $end
     $scope module genblk1[0] $end
      $scope module X $end
       $var wire 1 M clk $end
       $var wire 1 S reset $end
       $var wire 8 < in_word [7:0] $end
       $var wire 8 = out_word [7:0] $end
      $upscope $end
     $upscope $end
     $scope module genblk1[1] $end
      $scope module X $end
       $var wire 1 M clk $end
       $var wire 1 S reset $end
       $var wire 8 > in_word [7:0] $end
       $var wire 8 ? out_word [7:0] $end
      $upscope $end
     $upscope $end
     $scope module genblk1[2] $end
      $scope module X $end
       $var wire 1 M clk $end
       $var wire 1 S reset $end
       $var wire 8 @ in_word [7:0] $end
       $var wire 8 A out_word [7:0] $end
      $upscope $end
     $upscope $end
     $scope module genblk1[3] $end
      $scope module X $end
       $var wire 1 M clk $end
       $var wire 1 S reset $end
       $var wire 8 B in_word [7:0] $end
       $var wire 8 C out_word [7:0] $end
      $upscope $end
     $upscope $end
     $scope module genblk1[4] $end
      $scope module X $end
       $var wire 1 M clk $end
       $var wire 1 S reset $end
       $var wire 8 D in_word [7:0] $end
       $var wire 8 E out_word [7:0] $end
      $upscope $end
     $upscope $end
     $scope module genblk1[5] $end
      $scope module X $end
       $var wire 1 M clk $end
       $var wire 1 S reset $end
       $var wire 8 F in_word [7:0] $end
       $var wire 8 G out_word [7:0] $end
      $upscope $end
     $upscope $end
     $scope module genblk1[6] $end
      $scope module X $end
       $var wire 1 M clk $end
       $var wire 1 S reset $end
       $var wire 8 H in_word [7:0] $end
       $var wire 8 I out_word [7:0] $end
      $upscope $end
     $upscope $end
     $scope module genblk1[7] $end
      $scope module X $end
       $var wire 1 M clk $end
       $var wire 1 S reset $end
       $var wire 8 J in_word [7:0] $end
       $var wire 8 K out_word [7:0] $end
      $upscope $end
     $upscope $end
     $scope module unnamedblk1 $end
      $var wire 32 L ind [31:0] $end
     $upscope $end
    $upscope $end
    $scope module ula_inst $end
     $var wire 8 P SrcA [7:0] $end
     $var wire 8 R SrcB [7:0] $end
     $var wire 3 ) ULAControl [2:0] $end
     $var wire 8 N ULAResult [7:0] $end
     $var wire 1 O FlagZ $end
    $upscope $end
   $upscope $end
  $upscope $end
 $upscope $end
$enddefinitions $end


#0
b000 #
b000 $
b000 %
0&
b00000000 '
b00000000 (
b000 )
0*
0+
b00000000 ,
b00000000 -
b00000000 .
b00000000 /
b00000000 0
b00000000 1
b00000000 2
b00000000 3
b00000000 4
b00000000 5
b00000000 6
b00000000 7
b00000000 8
b00000000 9
b00000000 :
b00000000 ;
b00000000 <
b00000000 =
b00000000 >
b00000000 ?
b00000000 @
b00000000 A
b00000000 B
b00000000 C
b00000000 D
b00000000 E
b00000000 F
b00000000 G
b00000000 H
b00000000 I
b00000000 J
b00000000 K
b00000000000000000000000000000000 L
0M
b00000000 N
1O
b00000000 P
b00000000 Q
b00000000 R
1S
#5000
b00000000000000000000000000001000 L
1M
#10000
0M
#15000
1+
1M
#20000
0M
#25000
1M
#30000
0M
#35000
1M
#40000
0M
#45000
b001 %
1&
b01011010 '
b01011010 -
b01011010 >
1M
#50000
0M
#55000
b01011010 5
b01011010 ?
1M
#60000
0M
#65000
1M
#70000
0M
#75000
0&
1M
#80000
0M
#85000
b010 %
1&
b01011011 '
b01011011 .
b01011011 @
1M
#90000
0M
#95000
b01011011 6
b01011011 A
1M
#100000
0M
#105000
0&
1M
#110000
0M
#115000
b011 %
1&
b01011100 '
b01011100 /
b01011100 B
1M
#120000
0M
#125000
b01011100 7
b01011100 C
1M
#130000
0M
#135000
0&
1M
#140000
0M
#145000
b100 %
1&
b01011101 '
b01011101 0
b01011101 D
1M
#150000
0M
#155000
b01011101 8
b01011101 E
1M
#160000
0M
#165000
0&
1M
#170000
0M
#175000
b101 %
1&
b01011110 '
b01011110 1
b01011110 F
1M
#180000
0M
#185000
b01011110 9
b01011110 G
1M
#190000
0M
#195000
0&
1M
#200000
0M
#205000
b110 %
1&
b01011111 '
b01011111 2
b01011111 H
1M
#210000
0M
#215000
b01011111 :
b01011111 I
1M
#220000
0M
#225000
0&
1M
#230000
0M
#235000
b111 %
1&
b01010000 '
b01010000 3
b01010000 J
1M
#240000
0M
#245000
b01010000 ;
b01010000 K
1M
#250000
0M
#255000
0&
1M
#260000
0M
#265000
b001 #
b010 $
1M
b10110101 N
0O
b01011010 P
b01011011 Q
b01011011 R
#270000
0M
#275000
1M
#280000
0M
#285000
1M
#290000
0M
#295000
1M
#300000
0M
#305000
b011 #
b100 $
1M
b10111001 N
b01011100 P
b01011101 Q
b01011101 R
#310000
0M
#315000
1M
#320000
0M
#325000
b101 #
b110 $
1M
b10111101 N
b01011110 P
b01011111 Q
b01011111 R
#330000
0M
#335000
1M
#340000
0M
#345000
b111 #
b000 $
1M
b01010000 N
b01010000 P
b00000000 Q
b00000000 R
#350000
0M
#355000
1M
#360000
0M
#365000
b10101111 (
1*
1M
b11111111 N
b10101111 R
#370000
0M
#375000
1M
#380000
0M
#385000
b011 #
b001 $
b001 )
0*
1M
b00000010 N
b01011100 P
b01011010 Q
b01011010 R
#390000
0M
#395000
1M
#400000
0M
#405000
b001 #
b011 $
1M
b11111110 N
b01011010 P
b01011100 Q
b01011100 R
#410000
0M
#415000
1M
#420000
0M
#425000
b011 #
b01000000 (
1*
1M
b00011100 N
b01011100 P
b01000000 R
#430000
0M
#435000
1M
#440000
0M
#445000
b01100000 (
1M
b11111100 N
b01100000 R
#450000
0M
#455000
1M
#460000
0M
#465000
b101 #
b010 $
b010 )
0*
1M
b01011010 N
b01011110 P
b01011011 Q
b01011011 R
#470000
0M
#475000
1M
#480000
0M
#485000
b000 #
b101 $
1M
b00000000 N
1O
b00000000 P
b01011110 Q
b01011110 R
#490000
0M
#495000
1M
#500000
0M
#505000
b100 #
b11111111 (
1*
1M
b01011101 N
0O
b01011101 P
b11111111 R
#510000
0M
#515000
1M
#520000
0M
#525000
b00000000 (
1M
b00000000 N
1O
b00000000 R
#530000
0M
#535000
1M
#540000
0M
#545000
b110 #
b010 $
b011 )
0*
1M
b01011111 N
0O
b01011111 P
b01011011 Q
b01011011 R
#550000
0M
#555000
1M
#560000
0M
#565000
b001 #
b100 $
1M
b01011010 P
b01011101 Q
b01011101 R
#570000
0M
#575000
1M
#580000
0M
#585000
b011 #
b11111111 (
1*
1M
b11111111 N
b01011100 P
b11111111 R
#590000
0M
#595000
1M
#600000
0M
#605000
b110 #
b00000000 (
1M
b01011111 N
b01011111 P
b00000000 R
#610000
0M
#615000
1M
#620000
0M
#625000
b101 )
0*
1M
b00000000 N
1O
b01011101 R
#630000
0M
#635000
1M
#640000
0M
#645000
b100 #
b110 $
1M
b11111111 N
0O
b01011101 P
b01011111 Q
b01011111 R
#650000
0M
#655000
1M
#660000
0M
#665000
b011 #
b11111111 (
1*
1M
b01011100 P
b11111111 R
#670000
0M
#675000
1M
#680000
0M
#685000
b111 #
b00000000 (
1M
b00000000 N
1O
b01010000 P
b00000000 R
