digital_logic/prova-logica-digital/decoder_uart/decodificador_UART.sv
module decodificador_UART(
    input clk,              // relogio do sistema - assumimos 
    // período do relógioc igual ao período do bit da interface serial
    input reset,            // quando em nível alto reseta
    input RX,               // entrada de dados seriais
    output [7:0] dado,      // dado recebido
    output reg dado_valido, // indicador de dado recebido e válido 
    output reg erro         // indicador de erro no recebimento e dado não válido
    );
   
typedef enum {AGUARDA_LIVRE=0, PARADO=1, 
              REC_D0=2, REC_D1=3, REC_D2=4, REC_D3=5, REC_D4=6, REC_D5=7, REC_D6=8, REC_D7=9, 
              REC_PARIDADE=10, SUCESSO=11, ERRO=12} estado_tipo;

estado_tipo prox_etapa;    // sinal que contém o próximo estado a ser registrado
estado_tipo etapa_atual_ff;// registrador do estado atual

reg [7:0] dado_ff_s, dado_s; // dado recebido de forma serial

assign dado = dado_ff_s;


always_comb
begin : gera_proximo_estado
    dado_s = dado_ff_s;
    dado_valido = 0; // por padrão não tem dado válido
    erro = 0;        // por padrão não tem erro
    prox_etapa = etapa_atual_ff; // mantem estado atual se nada for mudado
    if(reset)
        prox_etapa = AGUARDA_LIVRE;   // volta ao início
    else
        case(etapa_atual_ff)
        AGUARDA_LIVRE: // inicio
            if(RX)
                prox_etapa = PARADO; // avança
        PARADO: // 
            if(!RX)
                prox_etapa = REC_D0; // avança
        REC_D0: // 
            begin
                prox_etapa = REC_D1; 
                dado_s[0] = RX;
            end
        REC_D1: // 
            begin
                prox_etapa = REC_D2;  
                dado_s[1] = RX;
            end
        REC_D2: // 
            begin
                prox_etapa = REC_D3;  
                dado_s[2] = RX;
            end
        REC_D3: // 
            begin
                prox_etapa = REC_D4;  
                dado_s[3] = RX;
            end
        REC_D4: // 
            begin
                prox_etapa = REC_D5; 
                dado_s[4] = RX;
            end 
        REC_D5: // 
            begin
                prox_etapa = REC_D6;  
                dado_s[5] = RX;
            end
        REC_D6: // 
            begin
                prox_etapa = REC_D7;  
                dado_s[6] = RX;
            end
        REC_D7: // 
            begin
                prox_etapa = REC_PARIDADE;  
                dado_s[7] = RX;
            end
        REC_PARIDADE: // 
            begin
                if( !(RX ^(^dado_ff_s)) )   // se XOR de dados recebidos + paridade == 0 correta
                    prox_etapa = SUCESSO; 
                else    // senão erro de paridade
                    prox_etapa = ERRO;
            end                    
        SUCESSO: // 
            begin
                dado_valido = 1;
                if(RX) // stop correto, volta ao início
                    prox_etapa = PARADO; 
                else    // senão erro de parada
                    prox_etapa = ERRO;   
            end                    
        ERRO: // 
            begin
                erro = 1;
                prox_etapa = PARADO; 
            end
        endcase
end

always@(posedge clk)
begin : atualiza_estado_atual
    etapa_atual_ff <= prox_etapa;
    dado_ff_s      <= dado_s;
end


endmodule

digital_logic/misc/codificador_UART.sv
`timescale 1ns/10ps
module codificador_UART(
    input clk,              // relogio do sistema - assumimos 
    // período do relógioc igual ao período do bit da interface serial
    input reset,            // quando em nível alto reseta
    input [7:0] dado,       // entrada de dados paralelos
    input dado_valido,      // indicador de dado válido para iniciar a transmissão
    input stop_1_2,         // em nível lógico baixo gera 1 stop bit, em alto 2 stop bits
    output reg TX,          // dado transmitido
    output reg transmitindo,// indicador de que iniciou uma transmissão
    output reg fim          // indicador de fim de transmissao
    );
   
typedef enum {AGUARDA_DADO=0, GERA_START=1, 
              TRANS_D0=2, TRANS_D1=3, TRANS_D2=4, TRANS_D3=5, TRANS_D4=6, TRANS_D5=7, TRANS_D6=8, TRANS_D7=9, 
              TRANS_PARIDADE=10, GERA_STOP1=11,GERA_STOP2=12} estado_tipo;

estado_tipo prox_etapa;    // sinal que contém o próximo estado a ser registrado
estado_tipo etapa_atual_ff;// registrador do estado atual

always@(reset, etapa_atual_ff, stop_1_2, dado, dado_valido ) // ou always_comb
begin : gera_proximo_estado
    TX = 1;          // por padrão saída em nível alto
    transmitindo = 1; // por padrão está transmitindo
    fim = 0;         // por padrão
    
    prox_etapa = etapa_atual_ff; // mantem estado atual se nada for mudado
    if(reset)
    begin
        prox_etapa = AGUARDA_DADO;   // volta ao início
        transmitindo = 0;
    end
    else
        case(etapa_atual_ff)
        AGUARDA_DADO: // inicio
            begin
                transmitindo = 0;
                if(dado_valido)
                    prox_etapa = GERA_START; // 
            end
        GERA_START:
            begin
                TX = 0; // start é um bit em nível lógico baixo
                prox_etapa = TRANS_D0; // avança
            end
        TRANS_D0: // 
            begin
                prox_etapa = TRANS_D1; 
                TX = dado[0];
            end
        TRANS_D1: // 
            begin
                prox_etapa = TRANS_D2;  
                TX = dado[1];
            end
        TRANS_D2: // 
            begin
                prox_etapa = TRANS_D3; 
                TX = dado[2];
            end
        TRANS_D3: // 
            begin
                prox_etapa = TRANS_D4;
                TX = dado[3];
            end
        TRANS_D4: // 
            begin
                prox_etapa = TRANS_D5;
                TX = dado[4];
            end 
        TRANS_D5: // 
            begin
                prox_etapa = TRANS_D6;  
                TX = dado[5];
            end
        TRANS_D6: // 
            begin
                prox_etapa = TRANS_D7;  
                TX = dado[6];
            end
        TRANS_D7: // 
            begin
                prox_etapa = TRANS_PARIDADE; 
                TX = dado[7];
            end
        TRANS_PARIDADE: // 
            begin
                TX = (^dado);   // XOR de dados transmitidos
                prox_etapa = GERA_STOP1;
            end         
        GERA_STOP1: // 
            begin
                TX = 1;   // stop é nível lógico alto
                fim = 1;
                transmitindo = 1;
                if(stop_1_2) // 1 ou 2 stops?
                    prox_etapa = GERA_STOP2; 
                else 
                begin
                    if(dado_valido)
                        prox_etapa = GERA_START; // 
                    else    // senão espera novo dado válido
                        prox_etapa = AGUARDA_DADO; 
                end
            end                    
        GERA_STOP2: // 
            begin
                TX = 1;   // stop é nível lógico alto
                transmitindo = 1;
                if(dado_valido)
                    prox_etapa = GERA_START; // 
                else    // senão espera novo dado válido
                    prox_etapa = AGUARDA_DADO;   
            end                   
        endcase
end

always@(posedge clk)
begin : atualiza_estado_atual
    etapa_atual_ff <= prox_etapa;
end


endmodule

digital_logic/misc/aula_09/tb_uart.sv
`timescale 1ns/10ps
 
module tb();
    reg clk=0, reset=0;
    wire TXRX_s;
    reg stop_1_2=0, dado_valido_tx=0;
    reg [7:0] dado_tx=0;
    wire dado_valido_rx, erro_rx, transmitindo, fim;
    wire [7:0] dado_rx;
initial 
begin
    $display("Comecou o teste");
    $dumpfile("test.vcd");
    $dumpvars(0,tb);    
    $timeformat(-9, 2, " ns", 20);
	#10ns;
	reset = 1;
	#50ns;
	reset = 0;
    #20ns;
        
	while(1)
    begin
        while($urandom_range(0,1))
            @(posedge clk); // espera proxima subida do clock antes de seguir
        
        dado_tx = $urandom_range(0,255);
        stop_1_2 = $urandom_range(0,1);
        @(posedge clk); // espera proxima subida do clock antes de seguir
        #2ns;
        @(posedge clk); // espera proxima subida do clock antes de seguir
        #2ns;
        dado_valido_tx = 1;
        $display("(%t) =-=-=-=-=-=-=-=-=-=-=-=-=-=-=-=-=-=-=-=-=",$time);
        $display("(%t) Dado a ser codificado TX: b%b",$time, dado_tx);
        @(posedge clk); // espera proxima subida do clock antes de seguir
        #2ns;
        dado_valido_tx = 0;
        @(negedge fim);
        
    end
	$finish();
end

initial
    #(10000ns) $finish();

always
begin
    #10ns;
    clk = !clk;
end

codificador_UART U1(
    .clk(clk),
    .reset(reset),
    .dado(dado_tx),
    .dado_valido(dado_valido_tx),
    .stop_1_2(stop_1_2),
    .TX(TXRX_s),
    .transmitindo(transmitindo),
    .fim(fim)
    );
    
decodificador_UART U2(
    .clk(clk),
    .reset(reset),
    .RX(TXRX_s),
    .dado(dado_rx),
    .dado_valido(dado_valido_rx),
    .erro(erro_rx)
    );
    
    // Monitora saídas do codificador UART
    always@(posedge transmitindo)
        $display("(%t) Inicio da transmissao UART. ",$time);
        
    always@(posedge fim)
        $display("(%t) Fim da transmissao UART. ",$time);
    
    
    // Monitora saídas do decodificador UART
    always@(posedge erro_rx)
        $display("(%t) Erro RX! ",$time);
    
    always@(posedge dado_valido_rx)
        $display("(%t) Dado valido RX: Dado RX b%b",$time, dado_rx);
    

endmodule


//    iverilog -o MeuProjeto -g2012 fontes/tb_uart.sv fontes/codificador_UART.sv fontes/decodificador_UART.sv

digital_logic/misc/test.vcd
$date
    Nov 26, 2024  10:03:25
$end
$version
    TOOL:	xmsim(64)	22.09-s013
$end
$timescale
    10 ps
$end

$scope module tb $end
$var reg       1 !    clk $end
$var reg       1 "    reset $end
$var wire      1 #    TXRX_s  $end
$var reg       1 $    stop_1_2 $end
$var reg       1 %    dado_valido_tx $end
$var reg       8 &    dado_tx [7:0] $end
$var wire      1 '    dado_valido_rx  $end
$var wire      1 (    erro_rx  $end
$var wire      1 )    transmitindo  $end
$var wire      1 *    fim  $end
$var wire      8 +    dado_rx [7:0] $end

$scope module U1 $end
$var wire      1 ,    clk  $end
$var wire      1 -    reset  $end
$var wire      8 .    dado [7:0] $end
$var wire      1 /    dado_valido  $end
$var wire      1 0    stop_1_2  $end
$var reg       1 1    TX $end
$var reg       1 2    transmitindo $end
$var reg       1 3    fim $end
$var reg      32 4    prox_etapa [31:0] $end
$var reg      32 5    etapa_atual_ff [31:0] $end
$upscope $end


$scope module U2 $end
$var wire      1 6    clk  $end
$var wire      1 7    reset  $end
$var wire      1 #    RX  $end
$var wire      8 +    dado [7:0] $end
$var reg       1 8    dado_valido $end
$var reg       1 9    erro $end
$var reg      32 :    prox_etapa [31:0] $end
$var reg      32 ;    etapa_atual_ff [31:0] $end
$var reg       8 <    dado_ff_s [7:0] $end
$var reg       8 =    dado_s [7:0] $end
$upscope $end

$upscope $end

$enddefinitions $end
$dumpvars
0!
0"
1#
0$
0%
b0 &
0'
0(
0)
0*
bx +
0,
0-
b0 .
0/
00
11
02
03
b0 4
b0 5
06
07
08
09
b1 :
b0 ;
bx <
bx =
$end
#1000
1"
1!
16
1,
17
1-
b0 :
12
02
b1 ;
b1 :
b0 :
#2000
0!
06
0,
#3000
1!
16
1,
b0 ;
#4000
0!
06
0,
#5000
1!
16
1,
#6000
0"
0!
06
0,
07
0-
b1 :
12
02
#7000
1!
16
1,
b1 ;
#8000
b11101 &
0!
06
0,
b11101 .
12
02
#9000
1!
16
1,
#10000
0!
06
0,
#11000
1!
16
1,
#11200
1%
1/
12
02
b1 4
#12000
0!
06
0,
#13000
1!
16
1,
b1 5
12
01
b10 4
0#
1)
b10 :
#13200
0%
0/
11
b1 4
01
b10 4
#14000
0!
06
0,
#15000
1!
16
1,
b10 ;
b10 5
b11 :
bx0 =
11
b11 4
1#
bx =
b10 :
b11 :
bx1 =
#16000
0!
06
0,
#17000
1!
16
1,
b11 ;
bx1 <
b11 5
b100 :
bx11 =
b100 4
01
0#
bx1 +
bx1 =
b11 :
b100 :
bx01 =
#18000
0!
06
0,
#19000
1!
16
1,
b100 ;
bx01 <
b100 5
b101 :
bx001 =
11
b101 4
1#
bx01 +
bx01 =
b100 :
b101 :
bx101 =
#20000
0!
06
0,
#21000
1!
16
1,
b101 ;
bx101 <
b101 5
b110 :
bx1101 =
b110 4
bx101 +
#22000
0!
06
0,
#23000
1!
16
1,
b110 ;
bx1101 <
b110 5
b111 :
bx11101 =
b111 4
bx1101 +
#24000
0!
06
0,
#25000
1!
16
1,
b111 ;
bx11101 <
b111 5
b1000 :
bx111101 =
b1000 4
01
0#
bx11101 +
bx11101 =
b111 :
b1000 :
bx011101 =
#26000
0!
06
0,
#27000
1!
16
1,
b1000 ;
bx011101 <
b1000 5
b1001 :
bx0011101 =
11
b1001 4
01
bx011101 +
#28000
0!
06
0,
#29000
1!
16
1,
b1001 ;
bx0011101 <
b1001 5
b1010 :
b11101 =
11
b1010 4
01
bx0011101 +
#30000
0!
06
0,
#31000
1!
16
1,
b1010 ;
b11101 <
b1010 5
b1011 :
11
01
b1011 4
b11101 +
#32000
0!
06
0,
#33000
1!
16
1,
b1011 ;
b1011 5
18
b1100 :
11
13
b0 4
1*
1#
1'
08
b1011 :
18
b1 :
#34000
0!
06
0,
#35000
1!
16
1,
b1 ;
b0 5
08
03
02
0)
0*
0'
#36000
0!
06
0,
#37000
1!
b10011 &
b10011 .
16
1,
12
02
#38000
0!
06
0,
#39000
1!
16
1,
#40000
0!
06
0,
#41000
1!
16
1,
#41200
1%
1/
12
02
b1 4
#42000
0!
06
0,
#43000
1!
16
1,
b1 5
12
01
b10 4
0#
1)
b10 :
#43200
0%
0/
11
b1 4
01
b10 4
#44000
0!
06
0,
#45000
1!
16
1,
b10 ;
b10 5
b11 :
b11100 =
11
b11 4
1#
b11101 =
b10 :
b11 :
#46000
0!
06
0,
#47000
1!
16
1,
b11 ;
b11 5
b100 :
b11111 =
b100 4
#48000
0!
06
0,
#49000
1!
16
1,
b100 ;
b11111 <
b100 5
b101 :
b101 4
01
0#
b11111 +
b100 :
b101 :
b11011 =
#50000
0!
06
0,
#51000
1!
16
1,
b101 ;
b11011 <
b101 5
b110 :
b10011 =
11
b110 4
01
b11011 +
#52000
0!
06
0,
#53000
1!
16
1,
b110 ;
b10011 <
b110 5
b111 :
b11 =
11
b111 4
1#
b10011 +
b10011 =
b110 :
b111 :
#54000
0!
06
0,
#55000
1!
16
1,
b111 ;
b111 5
b1000 :
b110011 =
b1000 4
01
0#
b10011 =
b111 :
b1000 :
#56000
0!
06
0,
#57000
1!
16
1,
b1000 ;
b1000 5
b1001 :
11
b1001 4
01
#58000
0!
06
0,
#59000
1!
16
1,
b1001 ;
b1001 5
b1010 :
11
b1010 4
01
#60000
0!
06
0,
#61000
1!
16
1,
b1010 ;
b1010 5
b1100 :
11
b1011 4
1#
b1010 :
b1011 :
#62000
0!
06
0,
#63000
1!
16
1,
b1011 ;
b1011 5
18
b1 :
13
b0 4
1*
1'
#64000
0!
06
0,
#65000
1!
16
1,
b1 ;
b0 5
08
03
02
0)
0*
0'
#66000
0!
06
0,
#67000
1!
16
1,
#68000
0!
06
0,
#69000
1!
b10100011 &
1$
10
b10100011 .
16
1,
12
02
#70000
0!
06
0,
#71000
1!
16
1,
#72000
0!
06
0,
#73000
1!
16
1,
#73200
1%
1/
12
02
b1 4
#74000
0!
06
0,
#75000
1!
16
1,
b1 5
12
01
b10 4
0#
1)
b10 :
#75200
0%
0/
11
b1 4
01
b10 4
#76000
0!
06
0,
#77000
1!
16
1,
b10 ;
b10 5
b11 :
b10010 =
11
b11 4
1#
b10011 =
b10 :
b11 :
#78000
0!
06
0,
#79000
1!
16
1,
b11 ;
b11 5
b100 :
b100 4
#80000
0!
06
0,
#81000
1!
16
1,
b100 ;
b100 5
b101 :
b10111 =
b101 4
01
0#
b10011 =
b100 :
b101 :
#82000
0!
06
0,
#83000
1!
16
1,
b101 ;
b101 5
b110 :
11
b110 4
01
#84000
0!
06
0,
#85000
1!
16
1,
b110 ;
b110 5
b111 :
b11 =
11
b111 4
01
#86000
0!
06
0,
#87000
1!
16
1,
b111 ;
b11 <
b111 5
b1000 :
11
b1000 4
1#
b11 +
b111 :
b1000 :
b100011 =
#88000
0!
06
0,
#89000
1!
16
1,
b1000 ;
b100011 <
b1000 5
b1001 :
b1100011 =
b1001 4
01
0#
b100011 +
b100011 =
b1000 :
b1001 :
#90000
0!
06
0,
#91000
1!
16
1,
b1001 ;
b1001 5
b1010 :
11
b1010 4
1#
b1001 :
b1010 :
b10100011 =
#92000
0!
06
0,
#93000
1!
16
1,
b1010 ;
b10100011 <
b1010 5
b1100 :
01
b1011 4
0#
b10100011 +
b1010 :
b1011 :
#94000
0!
06
0,
#95000
1!
16
1,
b1011 ;
b1011 5
18
b1100 :
11
13
b1100 4
1*
1#
1'
08
b1011 :
18
b1 :
#96000
0!
06
0,
#97000
1!
16
1,
b1 ;
b1100 5
08
03
b0 4
0*
0'
b10000001 &
b10000001 .
b1100 4
b0 4
#98000
0!
06
0,
#99000
1!
16
1,
b0 5
02
0)
#100000
0!
06
0,
#101000
1!
16
1,
#101200
1%
1/
12
02
b1 4
#102000
0!
06
0,
#103000
1!
16
1,
b1 5
12
01
b10 4
0#
1)
b10 :
#103200
0%
0/
11
b1 4
01
b10 4
#104000
0!
06
0,
#105000
1!
16
1,
b10 ;
b10 5
b11 :
b10100010 =
11
b11 4
1#
b10100011 =
b10 :
b11 :
#106000
0!
06
0,
#107000
1!
16
1,
b11 ;
b11 5
b100 :
b100 4
01
0#
b11 :
b100 :
b10100001 =
#108000
0!
06
0,
#109000
1!
16
1,
b100 ;
b10100001 <
b100 5
b101 :
11
b101 4
01
b10100001 +
#110000
0!
06
0,
#111000
1!
16
1,
b101 ;
b101 5
b110 :
11
b110 4
01
#112000
0!
06
0,
#113000
1!
16
1,
b110 ;
b110 5
b111 :
11
b111 4
01
#114000
0!
06
0,
#115000
1!
16
1,
b111 ;
b111 5
b1000 :
b10000001 =
11
b1000 4
01
#116000
0!
06
0,
#117000
1!
16
1,
b1000 ;
b10000001 <
b1000 5
b1001 :
11
b1001 4
01
b10000001 +
#118000
0!
06
0,
#119000
1!
16
1,
b1001 ;
b1001 5
b1010 :
b1 =
11
b1010 4
1#
b10000001 =
b1001 :
b1010 :
#120000
0!
06
0,
#121000
1!
16
1,
b1010 ;
b1010 5
b1100 :
01
b1011 4
0#
b1010 :
b1011 :
#122000
0!
06
0,
#123000
1!
16
1,
b1011 ;
b1011 5
18
b1100 :
11
13
b1100 4
1*
1#
1'
08
b1011 :
18
b1 :
#124000
0!
06
0,
#125000
1!
16
1,
b1 ;
b1100 5
08
03
b0 4
0*
0'
#126000
0!
06
0,
#127000
1!
b1110101 &
0$
00
b1110101 .
16
1,
b1100 4
b0 4
b0 5
02
0)
#128000
0!
06
0,
#129000
1!
16
1,
#130000
0!
06
0,
#131000
1!
16
1,
#131200
1%
1/
12
02
b1 4
#132000
0!
06
0,
#133000
1!
16
1,
b1 5
12
01
b10 4
0#
1)
b10 :
#133200
0%
0/
11
b1 4
01
b10 4
#134000
0!
06
0,
#135000
1!
16
1,
b10 ;
b10 5
b11 :
b10000000 =
11
b11 4
1#
b10000001 =
b10 :
b11 :
#136000
0!
06
0,
#137000
1!
16
1,
b11 ;
b11 5
b100 :
b10000011 =
b100 4
01
0#
b10000001 =
b11 :
b100 :
#138000
0!
06
0,
#139000
1!
16
1,
b100 ;
b100 5
b101 :
11
b101 4
1#
b100 :
b101 :
b10000101 =
#140000
0!
06
0,
#141000
1!
16
1,
b101 ;
b10000101 <
b101 5
b110 :
b10001101 =
b110 4
01
0#
b10000101 +
b10000101 =
b101 :
b110 :
#142000
0!
06
0,
#143000
1!
16
1,
b110 ;
b110 5
b111 :
11
b111 4
1#
b110 :
b111 :
b10010101 =
#144000
0!
06
0,
#145000
1!
16
1,
b111 ;
b10010101 <
b111 5
b1000 :
b10110101 =
b1000 4
b10010101 +
#146000
0!
06
0,
#147000
1!
16
1,
b1000 ;
b10110101 <
b1000 5
b1001 :
b11110101 =
b1001 4
b10110101 +
#148000
0!
06
0,
#149000
1!
16
1,
b1001 ;
b11110101 <
b1001 5
b1010 :
b1010 4
01
0#
b11110101 +
b1001 :
b1010 :
b1110101 =
#150000
0!
06
0,
#151000
1!
16
1,
b1010 ;
b1110101 <
b1010 5
b1100 :
11
b1011 4
1#
b1110101 +
b1010 :
b1011 :
#152000
0!
06
0,
#153000
1!
16
1,
b1011 ;
b1011 5
18
b1 :
13
b0 4
1*
1'
#154000
0!
06
0,
#155000
1!
16
1,
b1 ;
b0 5
08
03
02
0)
0*
0'
b10111110 &
1$
10
b10111110 .
12
02
#156000
0!
06
0,
#157000
1!
16
1,
#158000
0!
06
0,
#159000
1!
16
1,
#159200
1%
1/
12
02
b1 4
#160000
0!
06
0,
#161000
1!
16
1,
b1 5
12
01
b10 4
0#
1)
b10 :
#161200
0%
0/
11
b1 4
01
b10 4
#162000
0!
06
0,
#163000
1!
16
1,
b10 ;
b10 5
b11 :
b1110100 =
11
b11 4
01
#164000
0!
06
0,
#165000
1!
16
1,
b11 ;
b1110100 <
b11 5
b100 :
11
b100 4
1#
b1110100 +
b11 :
b100 :
b1110110 =
#166000
0!
06
0,
#167000
1!
16
1,
b100 ;
b1110110 <
b100 5
b101 :
b101 4
b1110110 +
#168000
0!
06
0,
#169000
1!
16
1,
b101 ;
b101 5
b110 :
b1111110 =
b110 4
#170000
0!
06
0,
#171000
1!
16
1,
b110 ;
b1111110 <
b110 5
b111 :
b111 4
b1111110 +
#172000
0!
06
0,
#173000
1!
16
1,
b111 ;
b111 5
b1000 :
b1000 4
#174000
0!
06
0,
#175000
1!
16
1,
b1000 ;
b1000 5
b1001 :
b1001 4
01
0#
b1000 :
b1001 :
b111110 =
#176000
0!
06
0,
#177000
1!
16
1,
b1001 ;
b111110 <
b1001 5
b1010 :
11
b1010 4
1#
b111110 +
b1001 :
b1010 :
b10111110 =
#178000
0!
06
0,
#179000
1!
16
1,
b1010 ;
b10111110 <
b1010 5
b1100 :
01
b1011 4
0#
b10111110 +
b1010 :
b1011 :
#180000
0!
06
0,
#181000
1!
16
1,
b1011 ;
b1011 5
18
b1100 :
11
13
b1100 4
1*
1#
1'
08
b1011 :
18
b1 :
#182000
0!
06
0,
#183000
1!
16
1,
b1 ;
b1100 5
08
03
b0 4
0*
0'
b10111101 &
b10111101 .
b1100 4
b0 4
#184000
0!
06
0,
#185000
1!
16
1,
b0 5
02
0)
#186000
0!
06
0,
#187000
1!
16
1,
#187200
1%
1/
12
02
b1 4
#188000
0!
06
0,
#189000
1!
16
1,
b1 5
12
01
b10 4
0#
1)
b10 :
#189200
0%
0/
11
b1 4
01
b10 4
#190000
0!
06
0,
#191000
1!
16
1,
b10 ;
b10 5
b11 :
11
b11 4
1#
b10 :
b11 :
b10111111 =
#192000
0!
06
0,
#193000
1!
16
1,
b11 ;
b10111111 <
b11 5
b100 :
b100 4
01
0#
b10111111 +
b11 :
b100 :
b10111101 =
#194000
0!
06
0,
#195000
1!
16
1,
b100 ;
b10111101 <
b100 5
b101 :
b10111001 =
11
b101 4
1#
b10111101 +
b10111101 =
b100 :
b101 :
#196000
0!
06
0,
#197000
1!
16
1,
b101 ;
b101 5
b110 :
b110 4
#198000
0!
06
0,
#199000
1!
16
1,
b110 ;
b110 5
b111 :
b111 4
#200000
0!
06
0,
#201000
1!
16
1,
b111 ;
b111 5
b1000 :
b1000 4
#202000
0!
06
0,
#203000
1!
16
1,
b1000 ;
b1000 5
b1001 :
b11111101 =
b1001 4
01
0#
b10111101 =
b1000 :
b1001 :
#204000
0!
06
0,
#205000
1!
16
1,
b1001 ;
b1001 5
b1010 :
b111101 =
11
b1010 4
1#
b10111101 =
b1001 :
b1010 :
#206000
0!
06
0,
#207000
1!
16
1,
b1010 ;
b1010 5
b1100 :
01
b1011 4
0#
b1010 :
b1011 :
#208000
0!
06
0,
#209000
1!
16
1,
b1011 ;
b1011 5
18
b1100 :
11
13
b1100 4
1*
1#
1'
08
b1011 :
18
b1 :
#210000
0!
06
0,
#211000
1!
16
1,
b1 ;
b1100 5
08
03
b0 4
0*
0'
#212000
0!
06
0,
#213000
1!
16
1,
b0 5
02
0)
#214000
0!
06
0,
#215000
1!
b10101001 &
0$
00
b10101001 .
16
1,
12
02
#216000
0!
06
0,
#217000
1!
16
1,
#218000
0!
06
0,
#219000
1!
16
1,
#219200
1%
1/
12
02
b1 4
#220000
0!
06
0,
#221000
1!
16
1,
b1 5
12
01
b10 4
0#
1)
b10 :
#221200
0%
0/
11
b1 4
01
b10 4
#222000
0!
06
0,
#223000
1!
16
1,
b10 ;
b10 5
b11 :
b10111100 =
11
b11 4
1#
b10111101 =
b10 :
b11 :
#224000
0!
06
0,
#225000
1!
16
1,
b11 ;
b11 5
b100 :
b10111111 =
b100 4
01
0#
b10111101 =
b11 :
b100 :
#226000
0!
06
0,
#227000
1!
16
1,
b100 ;
b100 5
b101 :
b10111001 =
11
b101 4
01
#228000
0!
06
0,
#229000
1!
16
1,
b101 ;
b10111001 <
b101 5
b110 :
b10110001 =
11
b110 4
1#
b10111001 +
b10111001 =
b101 :
b110 :
#230000
0!
06
0,
#231000
1!
16
1,
b110 ;
b110 5
b111 :
b111 4
01
0#
b110 :
b111 :
b10101001 =
#232000
0!
06
0,
#233000
1!
16
1,
b111 ;
b10101001 <
b111 5
b1000 :
b10001001 =
11
b1000 4
1#
b10101001 +
b10101001 =
b111 :
b1000 :
#234000
0!
06
0,
#235000
1!
16
1,
b1000 ;
b1000 5
b1001 :
b11101001 =
b1001 4
01
0#
b10101001 =
b1000 :
b1001 :
#236000
0!
06
0,
#237000
1!
16
1,
b1001 ;
b1001 5
b1010 :
b101001 =
11
b1010 4
1#
b10101001 =
b1001 :
b1010 :
#238000
0!
06
0,
#239000
1!
16
1,
b1010 ;
b1010 5
b1100 :
01
b1011 4
0#
b1010 :
b1011 :
#240000
0!
06
0,
#241000
1!
16
1,
b1011 ;
b1011 5
18
b1100 :
11
13
b0 4
1*
1#
1'
08
b1011 :
18
b1 :
#242000
0!
06
0,
#243000
1!
16
1,
b1 ;
b0 5
08
03
02
0)
0*
0'
#244000
0!
06
0,
#245000
1!
b1000111 &
1$
10
b1000111 .
16
1,
12
02
#246000
0!
06
0,
#247000
1!
16
1,
#248000
0!
06
0,
#249000
1!
16
1,
#249200
1%
1/
12
02
b1 4
#250000
0!
06
0,
#251000
1!
16
1,
b1 5
12
01
b10 4
0#
1)
b10 :
#251200
0%
0/
11
b1 4
01
b10 4
#252000
0!
06
0,
#253000
1!
16
1,
b10 ;
b10 5
b11 :
b10101000 =
11
b11 4
1#
b10101001 =
b10 :
b11 :
#254000
0!
06
0,
#255000
1!
16
1,
b11 ;
b11 5
b100 :
b10101011 =
b100 4
#256000
0!
06
0,
#257000
1!
16
1,
b100 ;
b10101011 <
b100 5
b101 :
b10101111 =
b101 4
b10101011 +
#258000
0!
06
0,
#259000
1!
16
1,
b101 ;
b10101111 <
b101 5
b110 :
b110 4
01
0#
b10101111 +
b101 :
b110 :
b10100111 =
#260000
0!
06
0,
#261000
1!
16
1,
b110 ;
b10100111 <
b110 5
b111 :
11
b111 4
01
b10100111 +
#262000
0!
06
0,
#263000
1!
16
1,
b111 ;
b111 5
b1000 :
b10000111 =
11
b1000 4
01
#264000
0!
06
0,
#265000
1!
16
1,
b1000 ;
b10000111 <
b1000 5
b1001 :
11
b1001 4
1#
b10000111 +
b1000 :
b1001 :
b11000111 =
#266000
0!
06
0,
#267000
1!
16
1,
b1001 ;
b11000111 <
b1001 5
b1010 :
b1010 4
01
0#
b11000111 +
b1001 :
b1010 :
b1000111 =
#268000
0!
06
0,
#269000
1!
16
1,
b1010 ;
b1000111 <
b1010 5
b1011 :
11
01
b1011 4
b1000111 +
#270000
0!
06
0,
#271000
1!
16
1,
b1011 ;
b1011 5
18
b1100 :
11
13
b1100 4
1*
1#
1'
08
b1011 :
18
b1 :
#272000
0!
06
0,
#273000
1!
16
1,
b1 ;
b1100 5
08
03
b0 4
0*
0'
#274000
0!
06
0,
#275000
1!
b10010101 &
0$
00
b10010101 .
16
1,
b1100 4
b0 4
b0 5
02
0)
#276000
0!
06
0,
#277000
1!
16
1,
#278000
0!
06
0,
#279000
1!
16
1,
#279200
1%
1/
12
02
b1 4
#280000
0!
06
0,
#281000
1!
16
1,
b1 5
12
01
b10 4
0#
1)
b10 :
#281200
0%
0/
11
b1 4
01
b10 4
#282000
0!
06
0,
#283000
1!
16
1,
b10 ;
b10 5
b11 :
b1000110 =
11
b11 4
1#
b1000111 =
b10 :
b11 :
#284000
0!
06
0,
#285000
1!
16
1,
b11 ;
b11 5
b100 :
b100 4
01
0#
b11 :
b100 :
b1000101 =
#286000
0!
06
0,
#287000
1!
16
1,
b100 ;
b1000101 <
b100 5
b101 :
b1000001 =
11
b101 4
1#
b1000101 +
b1000101 =
b100 :
b101 :
#288000
0!
06
0,
#289000
1!
16
1,
b101 ;
b101 5
b110 :
b1001101 =
b110 4
01
0#
b1000101 =
b101 :
b110 :
#290000
0!
06
0,
#291000
1!
16
1,
b110 ;
b110 5
b111 :
11
b111 4
1#
b110 :
b111 :
b1010101 =
#292000
0!
06
0,
#293000
1!
16
1,
b111 ;
b1010101 <
b111 5
b1000 :
b1110101 =
b1000 4
01
0#
b1010101 +
b1010101 =
b111 :
b1000 :
#294000
0!
06
0,
#295000
1!
16
1,
b1000 ;
b1000 5
b1001 :
b10101 =
11
b1001 4
01
#296000
0!
06
0,
#297000
1!
16
1,
b1001 ;
b10101 <
b1001 5
b1010 :
11
b1010 4
1#
b10101 +
b1001 :
b1010 :
b10010101 =
#298000
0!
06
0,
#299000
1!
16
1,
b1010 ;
b10010101 <
b1010 5
b1100 :
01
b1011 4
0#
b10010101 +
b1010 :
b1011 :
#300000
0!
06
0,
#301000
1!
16
1,
b1011 ;
b1011 5
18
b1100 :
11
13
b0 4
1*
1#
1'
08
b1011 :
18
b1 :
#302000
0!
06
0,
#303000
1!
16
1,
b1 ;
b0 5
08
03
02
0)
0*
0'
b1111 &
b1111 .
12
02
#304000
0!
06
0,
#305000
1!
16
1,
#306000
0!
06
0,
#307000
1!
16
1,
#307200
1%
1/
12
02
b1 4
#308000
0!
06
0,
#309000
1!
16
1,
b1 5
12
01
b10 4
0#
1)
b10 :
#309200
0%
0/
11
b1 4
01
b10 4
#310000
0!
06
0,
#311000
1!
16
1,
b10 ;
b10 5
b11 :
b10010100 =
11
b11 4
1#
b10010101 =
b10 :
b11 :
#312000
0!
06
0,
#313000
1!
16
1,
b11 ;
b11 5
b100 :
b10010111 =
b100 4
#314000
0!
06
0,
#315000
1!
16
1,
b100 ;
b10010111 <
b100 5
b101 :
b101 4
b10010111 +
#316000
0!
06
0,
#317000
1!
16
1,
b101 ;
b101 5
b110 :
b10011111 =
b110 4
#318000
0!
06
0,
