digital_logic/verilog_files/PT2262-PT2272-enc_dec/oscillator/clock_n_divider.sv
/* verilator lint_off DECLFILENAME */
`timescale 1us/1ns
module CLOCK_N_DIVIDER#(
    parameter DIVIDER = 2
)(
    input logic INPUT_CLK, RST,
    output logic OUTPUT_CLK
);


// int divider_index = int'(DIVIDER)/2;
/*
    Downclocking ratio. 
    Take a frequency division by 2 as an example. 
    The OUTPUT_CLK will be changed at every INPUT_CLK cycle. Take OUTPUT_CLK as 0 at the beginning.
    INPUTK_CLK will toggles from 1 to 0 and finishes a cyle, while OUTPUT_CLK will remain 0. At the beginning
    of the next cycle of INPUT_CLK, OUTPUT_CLK switchs to 1. The same process at every INPUT_CLK cycle.

    Our DIVIDER was initially 2. To achieve the above effect, we need to divide it by 2. 
*/
logic [15:0] divider_index_ceil = DIVIDER/2;
logic [15:0] clk_cycle_counting;

always_ff @(posedge INPUT_CLK) begin : FREQUENCY_DIVIDER
    if(~RST) begin
        clk_cycle_counting <= 0;
        OUTPUT_CLK <= 0;
    end
    else begin
            if(clk_cycle_counting < divider_index_ceil) begin
                clk_cycle_counting <= clk_cycle_counting + 1;
            end else begin
                clk_cycle_counting <= 1;
                OUTPUT_CLK <= ~OUTPUT_CLK;
            end
    end

end

    
endmodule

digital_logic/verilog_files/PT2262-PT2272-enc_dec/oscillator/clock_n_divider_tb.sv
/* verilator lint_off DECLFILENAME */
/* verilator lint_off UNUSEDSIGNAL */
`timescale 1us/1ns
module CLOCK_N_DIVIDER_TB();

    logic mock_INPUT_CLK, mock_RST;
    logic dut_OUTPUT_CLK;

    //Instantiating the Device Under Test (DUT)
    CLOCK_N_DIVIDER #(
        .DIVIDER(250)
    )DUT(
        .INPUT_CLK(mock_INPUT_CLK), 
        .RST(mock_RST), 
        .OUTPUT_CLK(dut_OUTPUT_CLK) 
    );

    initial begin
        mock_INPUT_CLK = 0;
        forever begin
            // #0.5us mock_INPUT_CLK = ~mock_INPUT_CLK; // 1us CLK Period == 1MHz CLK Frequency
            #165ns mock_INPUT_CLK = ~mock_INPUT_CLK; // 330ns CLK Period == 3MHz CLK Frequency
            // #5us mock_INPUT_CLK = ~mock_INPUT_CLK; // 10us CLK Period == 100kHz CLK Frequency
            // #50us mock_INPUT_CLK = ~mock_INPUT_CLK; // 100us CLK Period == 10kHz CLK Frequency
            // #500us mock_INPUT_CLK = ~mock_INPUT_CLK; // 1000us CLK Period == 1kHz CLK Frequency
        end
    end


    initial begin
        $dumpfile("CLOCK_N_DIVIDER_TB.vcd");
        $dumpvars(0, CLOCK_N_DIVIDER_TB);

        // Initialize Inputs
        @(posedge mock_INPUT_CLK);
        mock_RST = 0;

        // Wait for rst to be finished
        @(posedge mock_INPUT_CLK);
        @(posedge mock_INPUT_CLK);
        @(posedge mock_INPUT_CLK);
        mock_RST = 1;

        for(int i = 0; i < 750; i++) begin
            @(posedge mock_INPUT_CLK);
            // #1ns;
        end
        $finish;
    end


endmodule

digital_logic/verilog_files/PT2262-PT2272-enc_dec/oscillator/CLOCK_N_DIVIDER_TB.vcd
$version Generated by VerilatedVcd $end
$timescale 1ns $end
 $scope module TOP $end
  $scope module CLOCK_N_DIVIDER_TB $end
   $var wire 1 # mock_INPUT_CLK $end
   $var wire 1 $ mock_RST $end
   $var wire 1 % dut_OUTPUT_CLK $end
   $scope module DUT $end
    $var wire 32 ( DIVIDER [31:0] $end
    $var wire 1 # INPUT_CLK $end
    $var wire 1 $ RST $end
    $var wire 1 % OUTPUT_CLK $end
    $var wire 16 ) divider_index_ceil [15:0] $end
    $var wire 16 & clk_cycle_counting [15:0] $end
   $upscope $end
   $scope module unnamedblk1 $end
    $var wire 32 ' i [31:0] $end
   $upscope $end
  $upscope $end
 $upscope $end
$enddefinitions $end


#0
0#
0$
0%
b0000000000000000 &
b00000000000000000000000000000000 '
b00000000000000000000000011111010 (
b0000000001111101 )
#165
1#
#330
0#
#495
1#
#660
0#
#825
1#
#990
0#
#1155
1#
1$
b0000000000000001 &
#1320
0#
#1485
1#
b0000000000000010 &
b00000000000000000000000000000001 '
#1650
0#
#1815
1#
b0000000000000011 &
b00000000000000000000000000000010 '
#1980
0#
#2145
1#
b0000000000000100 &
b00000000000000000000000000000011 '
#2310
0#
#2475
1#
b0000000000000101 &
b00000000000000000000000000000100 '
#2640
0#
#2805
1#
b0000000000000110 &
b00000000000000000000000000000101 '
#2970
0#
#3135
1#
b0000000000000111 &
b00000000000000000000000000000110 '
#3300
0#
#3465
1#
b0000000000001000 &
b00000000000000000000000000000111 '
#3630
0#
#3795
1#
b0000000000001001 &
b00000000000000000000000000001000 '
#3960
0#
#4125
1#
b0000000000001010 &
b00000000000000000000000000001001 '
#4290
0#
#4455
1#
b0000000000001011 &
b00000000000000000000000000001010 '
#4620
0#
#4785
1#
b0000000000001100 &
b00000000000000000000000000001011 '
#4950
0#
#5115
1#
b0000000000001101 &
b00000000000000000000000000001100 '
#5280
0#
#5445
1#
b0000000000001110 &
b00000000000000000000000000001101 '
#5610
0#
#5775
1#
b0000000000001111 &
b00000000000000000000000000001110 '
#5940
0#
#6105
1#
b0000000000010000 &
b00000000000000000000000000001111 '
#6270
0#
#6435
1#
b0000000000010001 &
b00000000000000000000000000010000 '
#6600
0#
#6765
1#
b0000000000010010 &
b00000000000000000000000000010001 '
#6930
0#
#7095
1#
b0000000000010011 &
b00000000000000000000000000010010 '
#7260
0#
#7425
1#
b0000000000010100 &
b00000000000000000000000000010011 '
#7590
0#
#7755
1#
b0000000000010101 &
b00000000000000000000000000010100 '
#7920
0#
#8085
1#
b0000000000010110 &
b00000000000000000000000000010101 '
#8250
0#
#8415
1#
b0000000000010111 &
b00000000000000000000000000010110 '
#8580
0#
#8745
1#
b0000000000011000 &
b00000000000000000000000000010111 '
#8910
0#
#9075
1#
b0000000000011001 &
b00000000000000000000000000011000 '
#9240
0#
#9405
1#
b0000000000011010 &
b00000000000000000000000000011001 '
#9570
0#
#9735
1#
b0000000000011011 &
b00000000000000000000000000011010 '
#9900
0#
#10065
1#
b0000000000011100 &
b00000000000000000000000000011011 '
#10230
0#
#10395
1#
b0000000000011101 &
b00000000000000000000000000011100 '
#10560
0#
#10725
1#
b0000000000011110 &
b00000000000000000000000000011101 '
#10890
0#
#11055
1#
b0000000000011111 &
b00000000000000000000000000011110 '
#11220
0#
#11385
1#
b0000000000100000 &
b00000000000000000000000000011111 '
#11550
0#
#11715
1#
b0000000000100001 &
b00000000000000000000000000100000 '
#11880
0#
#12045
1#
b0000000000100010 &
b00000000000000000000000000100001 '
#12210
0#
#12375
1#
b0000000000100011 &
b00000000000000000000000000100010 '
#12540
0#
#12705
1#
b0000000000100100 &
b00000000000000000000000000100011 '
#12870
0#
#13035
1#
b0000000000100101 &
b00000000000000000000000000100100 '
#13200
0#
#13365
1#
b0000000000100110 &
b00000000000000000000000000100101 '
#13530
0#
#13695
1#
b0000000000100111 &
b00000000000000000000000000100110 '
#13860
0#
#14025
1#
b0000000000101000 &
b00000000000000000000000000100111 '
#14190
0#
#14355
1#
b0000000000101001 &
b00000000000000000000000000101000 '
#14520
0#
#14685
1#
b0000000000101010 &
b00000000000000000000000000101001 '
#14850
0#
#15015
1#
b0000000000101011 &
b00000000000000000000000000101010 '
#15180
0#
#15345
1#
b0000000000101100 &
b00000000000000000000000000101011 '
#15510
0#
#15675
1#
b0000000000101101 &
b00000000000000000000000000101100 '
#15840
0#
#16005
1#
b0000000000101110 &
b00000000000000000000000000101101 '
#16170
0#
#16335
1#
b0000000000101111 &
b00000000000000000000000000101110 '
#16500
0#
#16665
1#
b0000000000110000 &
b00000000000000000000000000101111 '
#16830
0#
#16995
1#
b0000000000110001 &
b00000000000000000000000000110000 '
#17160
0#
#17325
1#
b0000000000110010 &
b00000000000000000000000000110001 '
#17490
0#
#17655
1#
b0000000000110011 &
b00000000000000000000000000110010 '
#17820
0#
#17985
1#
b0000000000110100 &
b00000000000000000000000000110011 '
#18150
0#
#18315
1#
b0000000000110101 &
b00000000000000000000000000110100 '
#18480
0#
#18645
1#
b0000000000110110 &
b00000000000000000000000000110101 '
#18810
0#
#18975
1#
b0000000000110111 &
b00000000000000000000000000110110 '
#19140
0#
#19305
1#
b0000000000111000 &
b00000000000000000000000000110111 '
#19470
0#
#19635
1#
b0000000000111001 &
b00000000000000000000000000111000 '
#19800
0#
#19965
1#
b0000000000111010 &
b00000000000000000000000000111001 '
#20130
0#
#20295
1#
b0000000000111011 &
b00000000000000000000000000111010 '
#20460
0#
#20625
1#
b0000000000111100 &
b00000000000000000000000000111011 '
#20790
0#
#20955
1#
b0000000000111101 &
b00000000000000000000000000111100 '
#21120
0#
#21285
1#
b0000000000111110 &
b00000000000000000000000000111101 '
#21450
0#
#21615
1#
b0000000000111111 &
b00000000000000000000000000111110 '
#21780
0#
#21945
1#
b0000000001000000 &
b00000000000000000000000000111111 '
#22110
0#
#22275
1#
b0000000001000001 &
b00000000000000000000000001000000 '
#22440
0#
#22605
1#
b0000000001000010 &
b00000000000000000000000001000001 '
#22770
0#
#22935
1#
b0000000001000011 &
b00000000000000000000000001000010 '
#23100
0#
#23265
1#
b0000000001000100 &
b00000000000000000000000001000011 '
#23430
0#
#23595
1#
b0000000001000101 &
b00000000000000000000000001000100 '
#23760
0#
#23925
1#
b0000000001000110 &
b00000000000000000000000001000101 '
#24090
0#
#24255
1#
b0000000001000111 &
b00000000000000000000000001000110 '
#24420
0#
#24585
1#
b0000000001001000 &
b00000000000000000000000001000111 '
#24750
0#
#24915
1#
b0000000001001001 &
b00000000000000000000000001001000 '
#25080
0#
#25245
1#
b0000000001001010 &
b00000000000000000000000001001001 '
#25410
0#
#25575
1#
b0000000001001011 &
b00000000000000000000000001001010 '
#25740
0#
#25905
1#
b0000000001001100 &
b00000000000000000000000001001011 '
#26070
0#
#26235
1#
b0000000001001101 &
b00000000000000000000000001001100 '
#26400
0#
#26565
1#
b0000000001001110 &
b00000000000000000000000001001101 '
#26730
0#
#26895
1#
b0000000001001111 &
b00000000000000000000000001001110 '
#27060
0#
#27225
1#
b0000000001010000 &
b00000000000000000000000001001111 '
#27390
0#
#27555
1#
b0000000001010001 &
b00000000000000000000000001010000 '
#27720
0#
#27885
1#
b0000000001010010 &
b00000000000000000000000001010001 '
#28050
0#
#28215
1#
b0000000001010011 &
b00000000000000000000000001010010 '
#28380
0#
#28545
1#
b0000000001010100 &
b00000000000000000000000001010011 '
#28710
0#
#28875
1#
b0000000001010101 &
b00000000000000000000000001010100 '
#29040
0#
#29205
1#
b0000000001010110 &
b00000000000000000000000001010101 '
#29370
0#
#29535
1#
b0000000001010111 &
b00000000000000000000000001010110 '
#29700
0#
#29865
1#
b0000000001011000 &
b00000000000000000000000001010111 '
#30030
0#
#30195
1#
b0000000001011001 &
b00000000000000000000000001011000 '
#30360
0#
#30525
1#
b0000000001011010 &
b00000000000000000000000001011001 '
#30690
0#
#30855
1#
b0000000001011011 &
b00000000000000000000000001011010 '
#31020
0#
#31185
1#
b0000000001011100 &
b00000000000000000000000001011011 '
#31350
0#
#31515
1#
b0000000001011101 &
b00000000000000000000000001011100 '
#31680
0#
#31845
1#
b0000000001011110 &
b00000000000000000000000001011101 '
#32010
0#
#32175
1#
b0000000001011111 &
b00000000000000000000000001011110 '
#32340
0#
#32505
1#
b0000000001100000 &
b00000000000000000000000001011111 '
#32670
0#
#32835
1#
b0000000001100001 &
b00000000000000000000000001100000 '
#33000
0#
#33165
1#
b0000000001100010 &
b00000000000000000000000001100001 '
#33330
0#
#33495
1#
b0000000001100011 &
b00000000000000000000000001100010 '
#33660
0#
#33825
1#
b0000000001100100 &
b00000000000000000000000001100011 '
#33990
0#
#34155
1#
b0000000001100101 &
b00000000000000000000000001100100 '
#34320
0#
#34485
1#
b0000000001100110 &
b00000000000000000000000001100101 '
#34650
0#
#34815
1#
b0000000001100111 &
b00000000000000000000000001100110 '
#34980
0#
#35145
1#
b0000000001101000 &
b00000000000000000000000001100111 '
#35310
0#
#35475
1#
b0000000001101001 &
b00000000000000000000000001101000 '
#35640
0#
#35805
1#
b0000000001101010 &
b00000000000000000000000001101001 '
#35970
0#
#36135
1#
b0000000001101011 &
b00000000000000000000000001101010 '
#36300
0#
#36465
1#
b0000000001101100 &
b00000000000000000000000001101011 '
#36630
0#
#36795
1#
b0000000001101101 &
b00000000000000000000000001101100 '
#36960
0#
#37125
1#
b0000000001101110 &
b00000000000000000000000001101101 '
#37290
0#
#37455
1#
b0000000001101111 &
b00000000000000000000000001101110 '
#37620
0#
#37785
1#
b0000000001110000 &
b00000000000000000000000001101111 '
#37950
0#
#38115
1#
b0000000001110001 &
b00000000000000000000000001110000 '
#38280
0#
#38445
1#
b0000000001110010 &
b00000000000000000000000001110001 '
#38610
0#
#38775
1#
b0000000001110011 &
b00000000000000000000000001110010 '
#38940
0#
#39105
1#
b0000000001110100 &
b00000000000000000000000001110011 '
#39270
0#
#39435
1#
b0000000001110101 &
b00000000000000000000000001110100 '
#39600
0#
#39765
1#
b0000000001110110 &
b00000000000000000000000001110101 '
#39930
0#
#40095
1#
b0000000001110111 &
b00000000000000000000000001110110 '
#40260
0#
#40425
1#
b0000000001111000 &
b00000000000000000000000001110111 '
#40590
0#
#40755
1#
b0000000001111001 &
b00000000000000000000000001111000 '
#40920
0#
#41085
1#
b0000000001111010 &
b00000000000000000000000001111001 '
#41250
0#
#41415
1#
b0000000001111011 &
b00000000000000000000000001111010 '
#41580
0#
#41745
1#
b0000000001111100 &
b00000000000000000000000001111011 '
#41910
0#
#42075
1#
b0000000001111101 &
b00000000000000000000000001111100 '
#42240
0#
#42405
1#
1%
b0000000000000001 &
b00000000000000000000000001111101 '
#42570
0#
#42735
1#
b0000000000000010 &
b00000000000000000000000001111110 '
#42900
0#
#43065
1#
b0000000000000011 &
b00000000000000000000000001111111 '
#43230
0#
#43395
1#
b0000000000000100 &
b00000000000000000000000010000000 '
#43560
0#
#43725
1#
b0000000000000101 &
b00000000000000000000000010000001 '
#43890
0#
#44055
1#
b0000000000000110 &
b00000000000000000000000010000010 '
#44220
0#
#44385
1#
b0000000000000111 &
b00000000000000000000000010000011 '
#44550
0#
#44715
1#
b0000000000001000 &
b00000000000000000000000010000100 '
#44880
0#
#45045
1#
b0000000000001001 &
b00000000000000000000000010000101 '
#45210
0#
#45375
1#
b0000000000001010 &
b00000000000000000000000010000110 '
#45540
0#
#45705
1#
b0000000000001011 &
b00000000000000000000000010000111 '
#45870
0#
#46035
1#
b0000000000001100 &
b00000000000000000000000010001000 '
#46200
0#
#46365
1#
b0000000000001101 &
b00000000000000000000000010001001 '
#46530
0#
#46695
1#
b0000000000001110 &
b00000000000000000000000010001010 '
#46860
0#
#47025
1#
b0000000000001111 &
b00000000000000000000000010001011 '
#47190
0#
#47355
1#
b0000000000010000 &
b00000000000000000000000010001100 '
#47520
0#
#47685
1#
b0000000000010001 &
b00000000000000000000000010001101 '
#47850
0#
#48015
1#
b0000000000010010 &
b00000000000000000000000010001110 '
#48180
0#
#48345
1#
b0000000000010011 &
b00000000000000000000000010001111 '
#48510
0#
#48675
1#
b0000000000010100 &
b00000000000000000000000010010000 '
#48840
0#
#49005
1#
b0000000000010101 &
b00000000000000000000000010010001 '
#49170
0#
#49335
1#
b0000000000010110 &
b00000000000000000000000010010010 '
#49500
0#
#49665
1#
b0000000000010111 &
b00000000000000000000000010010011 '
#49830
0#
#49995
1#
b0000000000011000 &
b00000000000000000000000010010100 '
#50160
0#
#50325
1#
b0000000000011001 &
b00000000000000000000000010010101 '
#50490
0#
#50655
1#
b0000000000011010 &
b00000000000000000000000010010110 '
#50820
0#
#50985
1#
b0000000000011011 &
b00000000000000000000000010010111 '
#51150
0#
#51315
1#
b0000000000011100 &
b00000000000000000000000010011000 '
#51480
0#
#51645
1#
b0000000000011101 &
b00000000000000000000000010011001 '
#51810
0#
#51975
1#
b0000000000011110 &
b00000000000000000000000010011010 '
#52140
0#
#52305
1#
b0000000000011111 &
b00000000000000000000000010011011 '
#52470
0#
#52635
1#
b0000000000100000 &
b00000000000000000000000010011100 '
#52800
0#
#52965
1#
b0000000000100001 &
b00000000000000000000000010011101 '
#53130
0#
#53295
1#
b0000000000100010 &
b00000000000000000000000010011110 '
#53460
0#
#53625
1#
b0000000000100011 &
b00000000000000000000000010011111 '
#53790
0#
#53955
1#
b0000000000100100 &
b00000000000000000000000010100000 '
#54120
0#
#54285
1#
b0000000000100101 &
b00000000000000000000000010100001 '
#54450
0#
#54615
1#
b0000000000100110 &
b00000000000000000000000010100010 '
#54780
0#
#54945
1#
b0000000000100111 &
b00000000000000000000000010100011 '
#55110
0#
#55275
1#
b0000000000101000 &
b00000000000000000000000010100100 '
#55440
0#
#55605
1#
b0000000000101001 &
b00000000000000000000000010100101 '
#55770
0#
#55935
1#
b0000000000101010 &
b00000000000000000000000010100110 '
#56100
0#
#56265
1#
b0000000000101011 &
b00000000000000000000000010100111 '
#56430
0#
#56595
1#
b0000000000101100 &
b00000000000000000000000010101000 '
#56760
0#
#56925
1#
b0000000000101101 &
b00000000000000000000000010101001 '
#57090
0#
#57255
1#
b0000000000101110 &
b00000000000000000000000010101010 '
#57420
0#
#57585
1#
b0000000000101111 &
b00000000000000000000000010101011 '
#57750
0#
#57915
1#
b0000000000110000 &
b00000000000000000000000010101100 '
#58080
0#
#58245
1#
b0000000000110001 &
b00000000000000000000000010101101 '
#58410
0#
#58575
1#
b0000000000110010 &
b00000000000000000000000010101110 '
#58740
0#
#58905
1#
b0000000000110011 &
b00000000000000000000000010101111 '
#59070
0#
#59235
1#
b0000000000110100 &
b00000000000000000000000010110000 '
#59400
0#
#59565
1#
b0000000000110101 &
b00000000000000000000000010110001 '
#59730
0#
#59895
1#
b0000000000110110 &
b00000000000000000000000010110010 '
#60060
0#
#60225
1#
b0000000000110111 &
b00000000000000000000000010110011 '
#60390
0#
#60555
1#
b0000000000111000 &
b00000000000000000000000010110100 '
#60720
0#
#60885
1#
b0000000000111001 &
b00000000000000000000000010110101 '
#61050
0#
#61215
1#
b0000000000111010 &
b00000000000000000000000010110110 '
#61380
0#
#61545
1#
b0000000000111011 &
b00000000000000000000000010110111 '
#61710
0#
#61875
1#
b0000000000111100 &
b00000000000000000000000010111000 '
#62040
0#
#62205
1#
b0000000000111101 &
b00000000000000000000000010111001 '
#62370
0#
#62535
1#
b0000000000111110 &
b00000000000000000000000010111010 '
#62700
0#
#62865
1#
b0000000000111111 &
b00000000000000000000000010111011 '
#63030
0#
#63195
1#
b0000000001000000 &
b00000000000000000000000010111100 '
#63360
0#
#63525
1#
b0000000001000001 &
b00000000000000000000000010111101 '
#63690
0#
#63855
1#
b0000000001000010 &
b00000000000000000000000010111110 '
#64020
0#
#64185
1#
b0000000001000011 &
b00000000000000000000000010111111 '
#64350
0#
#64515
1#
b0000000001000100 &
b00000000000000000000000011000000 '
#64680
0#
#64845
1#
b0000000001000101 &
b00000000000000000000000011000001 '
#65010
0#
#65175
1#
b0000000001000110 &
b00000000000000000000000011000010 '
#65340
0#
#65505
1#
b0000000001000111 &
b00000000000000000000000011000011 '
#65670
0#
#65835
1#
b0000000001001000 &
b00000000000000000000000011000100 '
#66000
0#
#66165
1#
b0000000001001001 &
b00000000000000000000000011000101 '
#66330
0#
#66495
1#
b0000000001001010 &
b00000000000000000000000011000110 '
#66660
0#
#66825
1#
b0000000001001011 &
b00000000000000000000000011000111 '
#66990
0#
#67155
1#
b0000000001001100 &
b00000000000000000000000011001000 '
#67320
0#
#67485
1#
b0000000001001101 &
b00000000000000000000000011001001 '
#67650
0#
#67815
1#
b0000000001001110 &
b00000000000000000000000011001010 '
#67980
0#
#68145
1#
b0000000001001111 &
b00000000000000000000000011001011 '
#68310
0#
#68475
1#
b0000000001010000 &
b00000000000000000000000011001100 '
#68640
0#
#68805
1#
b0000000001010001 &
b00000000000000000000000011001101 '
#68970
0#
#69135
1#
b0000000001010010 &
b00000000000000000000000011001110 '
#69300
0#
#69465
1#
b0000000001010011 &
b00000000000000000000000011001111 '
#69630
0#
#69795
1#
b0000000001010100 &
b00000000000000000000000011010000 '
#69960
0#
#70125
1#
b0000000001010101 &
b00000000000000000000000011010001 '
#70290
0#
#70455
1#
b0000000001010110 &
b00000000000000000000000011010010 '
#70620
0#
#70785
1#
b0000000001010111 &
b00000000000000000000000011010011 '
#70950
0#
#71115
1#
b0000000001011000 &
b00000000000000000000000011010100 '
#71280
0#
#71445
1#
b0000000001011001 &
b00000000000000000000000011010101 '
#71610
0#
#71775
1#
b0000000001011010 &
b00000000000000000000000011010110 '
#71940
0#
#72105
1#
b0000000001011011 &
b00000000000000000000000011010111 '
#72270
0#
#72435
1#
b0000000001011100 &
b00000000000000000000000011011000 '
#72600
0#
#72765
1#
b0000000001011101 &
b00000000000000000000000011011001 '
#72930
0#
#73095
1#
b0000000001011110 &
b00000000000000000000000011011010 '
#73260
0#
#73425
1#
b0000000001011111 &
b00000000000000000000000011011011 '
#73590
0#
#73755
1#
b0000000001100000 &
b00000000000000000000000011011100 '
#73920
0#
#74085
1#
b0000000001100001 &
b00000000000000000000000011011101 '
#74250
0#
#74415
1#
b0000000001100010 &
b00000000000000000000000011011110 '
#74580
0#
#74745
1#
b0000000001100011 &
b00000000000000000000000011011111 '
#74910
0#
#75075
1#
b0000000001100100 &
b00000000000000000000000011100000 '
#75240
0#
#75405
1#
b0000000001100101 &
b00000000000000000000000011100001 '
#75570
0#
#75735
1#
b0000000001100110 &
b00000000000000000000000011100010 '
#75900
0#
#76065
1#
b0000000001100111 &
b00000000000000000000000011100011 '
#76230
0#
#76395
1#
b0000000001101000 &
b00000000000000000000000011100100 '
#76560
0#
#76725
1#
b0000000001101001 &
b00000000000000000000000011100101 '
#76890
0#
#77055
1#
b0000000001101010 &
b00000000000000000000000011100110 '
#77220
0#
#77385
1#
b0000000001101011 &
b00000000000000000000000011100111 '
#77550
0#
#77715
1#
b0000000001101100 &
b00000000000000000000000011101000 '
#77880
0#
#78045
1#
b0000000001101101 &
b00000000000000000000000011101001 '
#78210
0#
#78375
1#
b0000000001101110 &
b00000000000000000000000011101010 '
#78540
0#
#78705
1#
b0000000001101111 &
b00000000000000000000000011101011 '
#78870
0#
#79035
1#
b0000000001110000 &
b00000000000000000000000011101100 '
#79200
0#
#79365
1#
b0000000001110001 &
b00000000000000000000000011101101 '
#79530
0#
#79695
1#
b0000000001110010 &
b00000000000000000000000011101110 '
#79860
0#
#80025
1#
b0000000001110011 &
b00000000000000000000000011101111 '
#80190
0#
#80355
1#
b0000000001110100 &
b00000000000000000000000011110000 '
#80520
0#
#80685
1#
b0000000001110101 &
b00000000000000000000000011110001 '
#80850
0#
#81015
1#
b0000000001110110 &
b00000000000000000000000011110010 '
#81180
0#
#81345
1#
b0000000001110111 &
b00000000000000000000000011110011 '
#81510
0#
#81675
1#
b0000000001111000 &
b00000000000000000000000011110100 '
#81840
0#
#82005
1#
b0000000001111001 &
b00000000000000000000000011110101 '
#82170
0#
#82335
1#
b0000000001111010 &
b00000000000000000000000011110110 '
#82500
0#
#82665
1#
b0000000001111011 &
b00000000000000000000000011110111 '
#82830
0#
#82995
1#
b0000000001111100 &
b00000000000000000000000011111000 '
#83160
0#
#83325
1#
b0000000001111101 &
b00000000000000000000000011111001 '
#83490
0#
#83655
1#
0%
b0000000000000001 &
b00000000000000000000000011111010 '
#83820
0#
#83985
1#
b0000000000000010 &
b00000000000000000000000011111011 '
#84150
0#
#84315
1#
b0000000000000011 &
b00000000000000000000000011111100 '
#84480
0#
#84645
1#
b0000000000000100 &
b00000000000000000000000011111101 '
#84810
0#
#84975
1#
b0000000000000101 &
b00000000000000000000000011111110 '
#85140
0#
#85305
1#
b0000000000000110 &
b00000000000000000000000011111111 '
#85470
0#
#85635
1#
b0000000000000111 &
b00000000000000000000000100000000 '
#85800
0#
#85965
1#
b0000000000001000 &
b00000000000000000000000100000001 '
#86130
0#
#86295
1#
b0000000000001001 &
b00000000000000000000000100000010 '
#86460
0#
#86625
1#
b0000000000001010 &
b00000000000000000000000100000011 '
#86790
0#
#86955
1#
b0000000000001011 &
b00000000000000000000000100000100 '
#87120
0#
#87285
1#
b0000000000001100 &
b00000000000000000000000100000101 '
#87450
0#
#87615
1#
b0000000000001101 &
b00000000000000000000000100000110 '
#87780
0#
#87945
1#
b0000000000001110 &
b00000000000000000000000100000111 '
#88110
0#
#88275
1#
b0000000000001111 &
b00000000000000000000000100001000 '
#88440
0#
#88605
1#
b0000000000010000 &
b00000000000000000000000100001001 '
#88770
0#
#88935
1#
b0000000000010001 &
b00000000000000000000000100001010 '
#89100
0#
#89265
1#
b0000000000010010 &
b00000000000000000000000100001011 '
#89430
0#
#89595
1#
b0000000000010011 &
b00000000000000000000000100001100 '
#89760
0#
#89925
1#
b0000000000010100 &
b00000000000000000000000100001101 '
#90090
0#
#90255
1#
b0000000000010101 &
b00000000000000000000000100001110 '
#90420
0#
#90585
1#
b0000000000010110 &
b00000000000000000000000100001111 '
#90750
0#
#90915
1#
b0000000000010111 &
b00000000000000000000000100010000 '
#91080
0#
#91245
1#
b0000000000011000 &
b00000000000000000000000100010001 '
#91410
0#
#91575
1#
b0000000000011001 &
b00000000000000000000000100010010 '
#91740
0#
#91905
1#
b0000000000011010 &
b00000000000000000000000100010011 '
#92070
0#
#92235
1#
b0000000000011011 &
b00000000000000000000000100010100 '
#92400
0#
#92565
1#
b0000000000011100 &
b00000000000000000000000100010101 '
#92730
0#
#92895
1#
b0000000000011101 &
b00000000000000000000000100010110 '
#93060
0#
#93225
1#
b0000000000011110 &
b00000000000000000000000100010111 '
#93390
0#
#93555
1#
b0000000000011111 &
b00000000000000000000000100011000 '
#93720
0#
#93885
1#
b0000000000100000 &
b00000000000000000000000100011001 '
#94050
0#
#94215
1#
b0000000000100001 &
b00000000000000000000000100011010 '
#94380
0#
#94545
1#
b0000000000100010 &
b00000000000000000000000100011011 '
#94710
0#
#94875
1#
b0000000000100011 &
b00000000000000000000000100011100 '
#95040
0#
#95205
1#
b0000000000100100 &
b00000000000000000000000100011101 '
#95370
0#
#95535
1#
b0000000000100101 &
b00000000000000000000000100011110 '
#95700
0#
#95865
1#
b0000000000100110 &
b00000000000000000000000100011111 '
#96030
0#
#96195
1#
b0000000000100111 &
b00000000000000000000000100100000 '
#96360
0#
#96525
1#
b0000000000101000 &
b00000000000000000000000100100001 '
#96690
0#
#96855
1#
b0000000000101001 &
b00000000000000000000000100100010 '
#97020
0#
#97185
1#
b0000000000101010 &
b00000000000000000000000100100011 '
#97350
0#
#97515
1#
b0000000000101011 &
b00000000000000000000000100100100 '
#97680
0#
#97845
1#
b0000000000101100 &
b00000000000000000000000100100101 '
#98010
0#
#98175
1#
b0000000000101101 &
b00000000000000000000000100100110 '
#98340
0#
#98505
1#
b0000000000101110 &
b00000000000000000000000100100111 '
#98670
0#
#98835
1#
b0000000000101111 &
b00000000000000000000000100101000 '
#99000
0#
#99165
1#
b0000000000110000 &
b00000000000000000000000100101001 '
#99330
0#
#99495
1#
b0000000000110001 &
b00000000000000000000000100101010 '
#99660
0#
#99825
1#
b0000000000110010 &
b00000000000000000000000100101011 '
#99990
0#
#100155
1#
b0000000000110011 &
b00000000000000000000000100101100 '
#100320
0#
#100485
1#
b0000000000110100 &
b00000000000000000000000100101101 '
#100650
0#
#100815
1#
b0000000000110101 &
b00000000000000000000000100101110 '
#100980
0#
#101145
1#
b0000000000110110 &
b00000000000000000000000100101111 '
#101310
0#
#101475
1#
b0000000000110111 &
b00000000000000000000000100110000 '
#101640
0#
#101805
1#
b0000000000111000 &
b00000000000000000000000100110001 '
#101970
0#
#102135
1#
b0000000000111001 &
b00000000000000000000000100110010 '
#102300
0#
#102465
1#
b0000000000111010 &
b00000000000000000000000100110011 '
#102630
0#
#102795
1#
b0000000000111011 &
b00000000000000000000000100110100 '
#102960
0#
#103125
1#
b0000000000111100 &
b00000000000000000000000100110101 '
#103290
0#
#103455
1#
b0000000000111101 &
b00000000000000000000000100110110 '
#103620
0#
#103785
1#
b0000000000111110 &
b00000000000000000000000100110111 '
#103950
0#
#104115
1#
b0000000000111111 &
b00000000000000000000000100111000 '
#104280
0#
#104445
1#
b0000000001000000 &
b00000000000000000000000100111001 '
#104610
0#
#104775
1#
b0000000001000001 &
b00000000000000000000000100111010 '
#104940
0#
#105105
1#
b0000000001000010 &
b00000000000000000000000100111011 '
#105270
0#
#105435
1#
b0000000001000011 &
b00000000000000000000000100111100 '
#105600
0#
#105765
1#
b0000000001000100 &
b00000000000000000000000100111101 '
#105930
0#
#106095
1#
b0000000001000101 &
b00000000000000000000000100111110 '
#106260
0#
#106425
1#
b0000000001000110 &
b00000000000000000000000100111111 '
#106590
0#
#106755
1#
b0000000001000111 &
b00000000000000000000000101000000 '
#106920
0#
#107085
1#
b0000000001001000 &
b00000000000000000000000101000001 '
#107250
0#
#107415
1#
b0000000001001001 &
b00000000000000000000000101000010 '
#107580
0#
#107745
1#
b0000000001001010 &
b00000000000000000000000101000011 '
#107910
0#
#108075
1#
b0000000001001011 &
b00000000000000000000000101000100 '
#108240
0#
#108405
1#
b0000000001001100 &
b00000000000000000000000101000101 '
#108570
0#
#108735
1#
b0000000001001101 &
b00000000000000000000000101000110 '
#108900
0#
#109065
1#
b0000000001001110 &
b00000000000000000000000101000111 '
#109230
0#
#109395
1#
b0000000001001111 &
b00000000000000000000000101001000 '
#109560
0#
#109725
1#
b0000000001010000 &
b00000000000000000000000101001001 '
#109890
0#
#110055
1#
b0000000001010001 &
b00000000000000000000000101001010 '
#110220
0#
#110385
1#
b0000000001010010 &
b00000000000000000000000101001011 '
#110550
0#
#110715
1#
b0000000001010011 &
b00000000000000000000000101001100 '
#110880
0#
