hdl_intro_files/practice_02/shiftreg_op.sv
`timescale 1ns/1ps
module shiftreg_op#(parameter N=4)(
	input logic enable,
  	input logic shift_in,
  	input logic [N-1:0]d,
	input logic [1:0]OP,  
  	output logic [N-1:0]q,
  	output logic shift_out_right, shift_out_left 
);

	always_ff @(posedge enable)begin
		case (OP)
			2'b01: begin
				q <= {q[N-2:0], shift_in}; //shift left
			end
			2'b10: begin
			q <= {shift_in, q[N-1:1]}; //shift right
			end
			2'b11: begin 
				q <= d; 
			end  
			default: q <= q;
		endcase
	end
	assign shift_out_left = q[N-1];
	assign shift_out_right = q[0];

endmodule

hdl_intro_files/practice_02/shiftreg_op_tb.sv
`timescale 1ns/1ps
module shiftreg_op_tb();

    // Parameters
    parameter N = 4;

    // Inputs
    logic enable;
    logic shift_in;
    logic [N-1:0] d;
    logic [1:0] OP;

    // Outputs
    logic [N-1:0] q;
    logic shift_out_right;
    logic shift_out_left;

    // Instantiate the Unit Under Test (UUT)
    shiftreg_op #(N) uut (
        .enable(enable),
        .shift_in(shift_in),
        .d(d),
        .OP(OP),
        .q(q),
        .shift_out_right(shift_out_right),
        .shift_out_left(shift_out_left)
    );

    initial begin
        enable = 1'b0;
        forever #5 enable = ~enable;
    end

    // Testbench variables
    initial begin
        $dumpfile("shiftreg_dump.vcd");
        $dumpvars(0, shiftreg_op_tb);
        // Initialize Inputs
        // enable = 1'b0;
        shift_in = 1'b0;
        d = 4'b0;
        OP = 2'b0;

        // Wait for global reset
        #5;

        // Test case 1: Load data
        d = 4'b1010;
        OP = 2'b11;
        // enable = 1;
        #10;
        // enable = 0;
        assert(q == 4'b1010 && shift_out_left == 1'b1 && shift_out_right == 1'b0) else $fatal("Test case 1 failed");

        // Test case 2: Shift right with serial shift_in equal to 0
        shift_in = 0;
        OP = 2'b10;
        #10;
        // #5;
        // enable = 1;
        // #5;
        // enable = 0;
        assert(q == 4'b0101 && shift_out_right == 1'b1) else $fatal("Test case 2 failed");
        
        // Test case 3: Shift right with serial shift_in equal to 0
        shift_in = 0;
        OP = 2'b10;
        #10;
        // #5;
        // enable = 1;
        // #5;
        // enable = 0;
        assert(q == 4'b0010 && shift_out_right == 1'b0) else $fatal("Test case 3 failed");

        // Test case 4: Shift right with serial shift_in equal to 0
        shift_in = 0;
        OP = 2'b10;
        #10;
        // #5;
        // enable = 1;
        // #5;
        // enable = 0;
        assert(q == 4'b0001 && shift_out_right == 1'b1) else $fatal("Test case 4 failed");

        // Test case 5: Shift right with serial shift_in equal to 0
        shift_in = 0;
        OP = 2'b10;
        #10;
        // #5;
        // enable = 1;
        // #5;
        // enable = 0;
        assert(q == 4'b0000 && shift_out_right == 1'b0) else $fatal("Test case 5 failed");


        // Test case 6: Load data again
        OP = 2'b11;
        d = 4'b1010;
        #10;
        // #5;
        // enable = 1;
        // #5;
        // enable = 0;
        assert(q == 4'b1010 && shift_out_left == 1'b1 && shift_out_right == 1'b0) else $fatal("Test case 6 failed");

        // Test case 7: Shift left with serial shift_in equal to 0
        shift_in = 0;
        OP = 2'b01;
        #10;
        // #5;
        // enable = 1;
        // #5;
        // enable = 0;
        assert(q == 4'b0100 && shift_out_left == 1'b0) else $fatal("Test case 7 failed");

        // Test case 8: Shift left with serial shift_in equal to 0
        shift_in = 0;
        OP = 2'b01;
        #10;
        // #5;
        // enable = 1;
        // #5;
        // enable = 0;
        assert(q == 4'b1000 && shift_out_left == 1'b1) else $fatal("Test case 8 failed");

        // Test case 9: Shift left with serial shift_in equal to 0
        shift_in = 0;
        OP = 2'b01;
        #10;
        // #5;
        // enable = 1;
        // #5;
        // enable = 0;
        assert(q == 4'b0000 && shift_out_left == 1'b0) else $fatal("Test case 9 failed");

        // Test case 10: Load data again
        d = 4'b1111;
        OP = 2'b11;
        #10;
        // #5;
        // enable = 1;
        // #5;
        // enable = 0;
        assert(q == 4'b1111 && shift_out_left == 1'b1 && shift_out_right == 1'b1) else $fatal("Test case 10 failed");

        // Test case 11: No operation
        OP = 2'b00;
        #10;
        // #5;
        // enable = 1;
        // #5;
        // enable = 0;
        assert(q == 4'b1111 && shift_out_left == 1'b1 && shift_out_right == 1'b1) else $fatal("Test case 11 failed");


        // Test case 12: Shift left with serial shift_in equal to 0 and input all ones
        shift_in = 0;
        OP = 2'b01;
        #10;
        // #5;
        // enable = 1;
        // #5;
        // enable = 0;
        assert(q == 4'b1110 && shift_out_left == 1'b1) else $fatal("Test case 12 failed");

        // Test case 13: Shift left with serial shift_in equal to 0 and input that was all ones
        shift_in = 0;
        OP = 2'b01;
        #10;
        // #5;
        // enable = 1;
        // #5;
        // enable = 0;
        assert(q == 4'b1100 && shift_out_left == 1'b1) else $fatal("Test case 13 failed");

        // Test case 14: Shift left with serial shift_in equal to 0 and input that was all ones
        shift_in = 0;
        OP = 2'b01;
        #10;
        // #5;
        // enable = 1;
        // #5;
        // enable = 0;
        assert(q == 4'b1000 && shift_out_left == 1'b1) else $fatal("Test case 14 failed");

        // Test case 15: Shift left with serial shift_in equal to 0 and input that was all ones
        shift_in = 0;
        OP = 2'b01;
        #10;
        // #5;
        // enable = 1;
        // #5;
        // enable = 0;
        assert(q == 4'b0000 && shift_out_left == 1'b0) else $fatal("Test case 15 failed");

        $display("All test cases passed.");
        $finish;
    end

    initial
    begin
      $display("                Tempo     Entradas LUT                                  Saídas");
      $display("                         enable  shift_in  d   OP            q     shift_out_left  shift_out_right");
      $display("                ====   ============================      ==========================================");
      $monitor($time,"       %b      %b      %b  %b          %b         %b              %b", enable, shift_in, d, OP, q, shift_out_left, shift_out_right);
    end

endmodule

hdl_intro_files/practice_02/shiftreg_dump.vcd
$version Generated by VerilatedVcd $end
$timescale 1ps $end
 $scope module TOP $end
  $scope module shiftreg_op_tb $end
   $var wire 32 * N [31:0] $end
   $var wire 1 & enable $end
   $var wire 1 ' shift_in $end
   $var wire 4 ( d [3:0] $end
   $var wire 2 ) OP [1:0] $end
   $var wire 4 # q [3:0] $end
   $var wire 1 $ shift_out_right $end
   $var wire 1 % shift_out_left $end
   $scope module uut $end
    $var wire 32 * N [31:0] $end
    $var wire 1 & enable $end
    $var wire 1 ' shift_in $end
    $var wire 4 ( d [3:0] $end
    $var wire 2 ) OP [1:0] $end
    $var wire 4 # q [3:0] $end
    $var wire 1 $ shift_out_right $end
    $var wire 1 % shift_out_left $end
   $upscope $end
  $upscope $end
 $upscope $end
$enddefinitions $end


#0
b0000 #
0$
0%
0&
0'
b0000 (
b00 )
b00000000000000000000000000000100 *
#5000
b1010 #
1%
1&
b1010 (
b11 )
#10000
0&
#15000
b0101 #
1$
0%
1&
b10 )
#20000
0&
#25000
b0010 #
0$
1&
#30000
0&
#35000
b0001 #
1$
1&
#40000
0&
#45000
b0000 #
0$
1&
#50000
0&
#55000
b1010 #
1%
1&
b11 )
#60000
0&
#65000
b0100 #
0%
1&
b01 )
#70000
0&
#75000
b1000 #
1%
1&
#80000
0&
#85000
b0000 #
0%
1&
#90000
0&
#95000
b1111 #
1$
1%
1&
b1111 (
b11 )
#100000
0&
#105000
1&
b00 )
#110000
0&
#115000
b1110 #
0$
1&
b01 )
#120000
0&
#125000
b1100 #
1&
#130000
0&
#135000
b1000 #
1&
#140000
0&
#145000
b0000 #
0%
1&
#150000
0&
#155000
1&
