digital_logic/misc/aula_08/semaphore_ctrl.sv
`timescale 1ns/10ps
module semaphore_ctrl (
    input logic clk, reset, pulso,
    output logic vermelho, amarelo, verde
);

logic [1:0] estado_atual_ff, proximo_estado;
logic pulso_atual, pulso_anterior;

always_ff @(clk) begin : state_handler
    estado_atual_ff <= proximo_estado;
    pulso_anterior <= pulso;
end

always_ff @(pulso) begin
    pulso_atual <= pulso;
end

always_comb begin : semaphore_fsm
    proximo_estado = estado_atual_ff;
    vermelho = 1;
    amarelo = 1;
    verde = 0;

    if (reset)
        proximo_estado = 2'b00;

    else begin
            case(estado_atual_ff)
                2'b00: begin
                    vermelho = 1;
                    amarelo = 1;
                    verde = 0;
                    proximo_estado = 2'b11;
                end

                2'b01: begin
                    vermelho = 0;
                    amarelo = 0;
                    verde = 1;
                    if (pulso_atual && !pulso_anterior)
                        proximo_estado = 2'b10;
                end

                2'b10: begin
                    vermelho = 0;
                    amarelo = 1;
                    verde = 0;
                    if (pulso_atual && !pulso_anterior)
                        proximo_estado = 2'b11;
                end

                2'b11: begin
                    vermelho = 1;
                    amarelo = 0;
                    verde = 0;
                    if (pulso_atual && !pulso_anterior)
                        proximo_estado = 2'b01;
                end
            endcase
        end

end



endmodule

digital_logic/misc/aula_08/semaphore_ctrl_tb.sv
/* verilator lint_off PINMISSING */
/* verilator lint_off BLKSEQ */
/* verilator lint_off SYNCASYNCNET */
`timescale 1ns/10ps
 
module semaphore_ctrl_tb();
reg clk=0, reset=0, pulso=0;

initial 
begin
    $display("Comecou o teste");
    $dumpfile("test.vcd");
    $dumpvars(0,semaphore_ctrl);    
    $timeformat(-9, 2, " ns", 20);
	#10ns;
	reset = 1;
	#50ns;
	reset = 0;
    #20ns;
        
	while(1)
    begin
        pulso = 1;
        @(posedge clk); // espera proxima subida do clock antes de seguir
        #2ns;
        pulso = 0;
        // #($urandom_range(20,30));
        #20ns;
    end
	$finish();
end

initial
    #1000 $finish();

always
begin
    #10ns;
    clk = !clk;
end

semaphore_ctrl U1(
    .clk(clk),
    .pulso(pulso),
    .reset(reset)
    );

endmodule


//    $display("(%t) %b",$time, clk);

digital_logic/misc/aula_08/test.vcd
$version Generated by VerilatedVcd $end
$timescale 10ps $end
 $scope module TOP $end
  $scope module semaphore_ctrl_tb $end
   $var wire 1 # clk $end
   $var wire 1 $ reset $end
   $var wire 1 % pulso $end
   $scope module U1 $end
    $var wire 1 # clk $end
    $var wire 1 $ reset $end
    $var wire 1 % pulso $end
    $var wire 1 & vermelho $end
    $var wire 1 ' amarelo $end
    $var wire 1 ( verde $end
    $var wire 2 ) estado_atual_ff [1:0] $end
    $var wire 2 * proximo_estado [1:0] $end
    $var wire 1 + pulso_atual $end
    $var wire 1 , pulso_anterior $end
   $upscope $end
  $upscope $end
 $upscope $end
$enddefinitions $end


#0
0#
0$
0%
1&
0'
0(
b11 )
b11 *
0+
0,
#1000
1#
1$
1'
b00 )
b00 *
#2000
0#
#3000
1#
#4000
0#
#5000
1#
#6000
0#
0$
0'
b11 )
b11 *
#7000
1#
#8000
0#
1%
1+
1,
#9000
1#
#9200
0%
0+
#10000
0#
0,
#11000
1#
#11200
1%
b01 *
1+
#12000
0#
0&
1(
b01 )
1,
#13000
1#
#13200
0%
0+
#14000
0#
0,
#15000
1#
#15200
1%
b10 *
1+
#16000
0#
1'
0(
b10 )
1,
#17000
1#
#17200
0%
0+
#18000
0#
0,
#19000
1#
#19200
1%
b11 *
1+
#20000
0#
1&
0'
b11 )
1,
#21000
1#
#21200
0%
0+
#22000
0#
0,
#23000
1#
#23200
1%
b01 *
1+
#24000
0#
0&
1(
b01 )
1,
#25000
1#
#25200
0%
0+
#26000
0#
0,
#27000
1#
#27200
1%
b10 *
1+
#28000
0#
1'
0(
b10 )
1,
#29000
1#
#29200
0%
0+
#30000
0#
0,
#31000
1#
#31200
1%
b11 *
1+
#32000
0#
1&
0'
b11 )
1,
#33000
1#
#33200
0%
0+
#34000
0#
0,
#35000
1#
#35200
1%
b01 *
1+
#36000
0#
0&
1(
b01 )
1,
#37000
1#
#37200
0%
0+
#38000
0#
0,
#39000
1#
#39200
1%
b10 *
1+
#40000
0#
1'
0(
b10 )
1,
#41000
1#
#41200
0%
0+
#42000
0#
0,
#43000
1#
#43200
1%
b11 *
1+
#44000
0#
1&
0'
b11 )
1,
#45000
1#
#45200
0%
0+
#46000
0#
0,
#47000
1#
#47200
1%
b01 *
1+
#48000
0#
0&
1(
b01 )
1,
#49000
1#
#49200
0%
0+
#50000
0#
0,
#51000
1#
#51200
1%
b10 *
1+
#52000
0#
1'
0(
b10 )
1,
#53000
1#
#53200
0%
0+
#54000
0#
0,
#55000
1#
#55200
1%
b11 *
1+
#56000
0#
1&
0'
b11 )
1,
#57000
1#
#57200
0%
0+
#58000
0#
0,
#59000
1#
#59200
1%
b01 *
1+
#60000
0#
0&
1(
b01 )
1,
#61000
1#
#61200
0%
0+
#62000
0#
0,
#63000
1#
#63200
1%
b10 *
1+
#64000
0#
1'
0(
b10 )
1,
#65000
1#
#65200
0%
0+
#66000
0#
0,
#67000
1#
#67200
1%
b11 *
1+
#68000
0#
1&
0'
b11 )
1,
#69000
1#
#69200
0%
0+
#70000
0#
0,
#71000
1#
#71200
1%
b01 *
1+
#72000
0#
0&
1(
b01 )
1,
#73000
1#
#73200
0%
0+
#74000
0#
0,
#75000
1#
#75200
1%
b10 *
1+
#76000
0#
1'
0(
b10 )
1,
#77000
1#
#77200
0%
0+
#78000
0#
0,
#79000
1#
#79200
1%
b11 *
1+
#80000
0#
1&
0'
b11 )
1,
#81000
1#
#81200
0%
0+
#82000
0#
0,
#83000
1#
#83200
1%
b01 *
1+
#84000
0#
0&
1(
b01 )
1,
#85000
1#
#85200
0%
0+
#86000
0#
0,
#87000
1#
#87200
1%
b10 *
1+
#88000
0#
1'
0(
b10 )
1,
#89000
1#
#89200
0%
0+
#90000
0#
0,
#91000
1#
#91200
1%
b11 *
1+
#92000
0#
1&
0'
b11 )
1,
#93000
1#
#93200
0%
0+
#94000
0#
0,
#95000
1#
#95200
1%
b01 *
1+
#96000
0#
0&
1(
b01 )
1,
#97000
1#
#97200
0%
0+
#98000
0#
0,
#99000
1#
#99200
1%
b10 *
1+
#100000
0#
1'
0(
b10 )
1,
