verification_101/final_project/subproj1/alu.sv
/* verilator lint_off UNUSEDSIGNAL */
//--------------------------------------------------------
//ALU Design Version 1.0
//--------------------------------------------------------


/* 
ALU Arithmetic and Logic Operations
----------------------------------------------------------------------
|ALU_Sel|   ALU Operation
----------------------------------------------------------------------
| 0000  |   ALU_Out = A + B;
----------------------------------------------------------------------
| 0001  |   ALU_Out = A - B;
----------------------------------------------------------------------
| 0010  |   ALU_Out = A * B;
----------------------------------------------------------------------
| 0011  |   ALU_Out = A / B;
----------------------------------------------------------------------
*/



//--------------------------------------------------------
// NOTE TO A VERIFICATION ENGINEER:
//
// AS A VERIFICATION ENGINEER, ONE SHOULD NEVER PEEK INTO
// DESIGN AND TRY TO REVERSE ENGINEER WHAT'S HAPPENING.
// JUST FOCUS ON GIVEN SPEC AND BUILD YOUR TESTBENCH ACCORDINGLY.
//--------------------------------------------------------

module alu(
  input clock,
  input reset,
  input [7:0] A,B,  // ALU 8-bit Inputs                 
  input [3:0] ALU_Sel,// ALU Selection
  output reg [7:0] ALU_Out, // ALU 8-bit Output
  output bit CarryOut // Carry Out Flag
);

  reg [7:0] ALU_Result;
  wire [8:0] tmp;

  assign tmp = {1'b0,A} + {1'b0,B};

  
  always @(posedge clock or posedge reset) begin
    if(reset) begin
      ALU_Out  <= 8'd0;
      CarryOut <= 1'd0;
    end
    else begin
      ALU_Out <= ALU_Result;
      CarryOut <= tmp[8];
    end
  end


  always @(*) //introduce a bug here, A B sensitivity only, change ALU_Sel during
    begin
      case(ALU_Sel)
        4'b0000: // Addition
          ALU_Result = A + B ; 
        4'b0001: // Subtraction
          ALU_Result = A - B ;
        4'b0010: // Multiplication
          ALU_Result = A * B;
        4'b0011: // Division
          ALU_Result = A/B;
        default: ALU_Result = 8'hAC ; // Give out random BAD value
      endcase
    end

endmodule

verification_101/final_project/subproj1/alu_auto_tb.sv
module alu_auto_tb();

    logic clock;
    logic reset;
    logic [7:0] A,B;  // ALU 8-bit Inputs                 
    logic [3:0] ALU_Sel;// ALU Selection
    logic [7:0] ALU_Out; // ALU 8-bit Output
    logic CarryOut; // Carry Out Flag

    alu alu_inst(
        .clock(clock),
        .reset(reset),
        .A(A),
        .B(B),
        .ALU_Sel(ALU_Sel),
        .ALU_Out(ALU_Out),
        .CarryOut(CarryOut)
    );

    // Clock generation
    initial begin
        clock = 0;
        forever #5 clock = ~clock;
    end

    // Test vectors
    initial begin

        $dumpfile("alu_auto_tb.vcd");
        $dumpvars(0, alu_auto_tb);

        #10;

        // Initialize Inputs
        reset = 1;
        A = 0;
        B = 0;
        ALU_Sel = 0;

        // Wait for global reset
        #10;
        reset = 0;
        #10;
        
        // Test Addition
        A = 8'h9d;
        B = 8'h60;
        ALU_Sel = 4'b0000;
        #10;
        // $display("Addition: A = %d, B = %d, ALU_Out = %d, CarryOut = %b", A, B, ALU_Out, CarryOut);
        assert(ALU_Out == 8'hfd && CarryOut == 1'b0) else $fatal(1,"Test Case 1 failed");

        A = 8'hb1;
        B = 8'h9f;
        ALU_Sel = 4'b0000;
        #10;
        // $display("Addition: A = %d, B = %d, ALU_Out = %d, CarryOut = %b", A, B, ALU_Out, CarryOut);
        assert(ALU_Out == 8'h50 && CarryOut == 1'b1) else $fatal(1,"Test Case 2 failed");

        A = 8'h97;
        B = 8'h1b;
        ALU_Sel = 4'b0000;
        #10;
        $display("Addition: A = %d, B = %d, ALU_Out = %d, CarryOut = %b", A, B, ALU_Out, CarryOut);
        assert(ALU_Out == 8'hb2 && CarryOut == 1'b0) else $fatal(1,"Test Case 3 failed");

        A = 8'h27;
        B = 8'h18;
        ALU_Sel = 4'b0000;
        #10;
        $display("Addition: A = %d, B = %d, ALU_Out = %d, CarryOut = %b", A, B, ALU_Out, CarryOut);
        assert(ALU_Out == 8'h3f && CarryOut == 1'b0) else $fatal(1,"Test Case 4 failed");

        A = 8'h89;
        B = 8'h38;
        ALU_Sel = 4'b0000;
        #10;
        $display("Addition: A = %d, B = %d, ALU_Out = %d, CarryOut = %b", A, B, ALU_Out, CarryOut);
        assert(ALU_Out == 8'hc1 && CarryOut == 1'b0) else $fatal(1,"Test Case 5 failed");

        // Test Subtraction
        A = 8'h55;
        B = 8'h36;
        ALU_Sel = 4'b0001;
        #10;
        $display("Subtraction: A = %d, B = %d, ALU_Out = %d, CarryOut = %b", A, B, ALU_Out, CarryOut);
        assert(ALU_Out == 8'h1f && CarryOut == 1'b0) else $fatal(1,"Test Case 6 failed");
        
        A = 8'h38;
        B = 8'h10;
        ALU_Sel = 4'b0001;
        #10;
        $display("Subtraction: A = %d, B = %d, ALU_Out = %d, CarryOut = %b", A, B, ALU_Out, CarryOut);
        assert(ALU_Out == 8'h28 && CarryOut == 1'b0) else $fatal(1,"Test Case 7 failed");

        A = 8'hea;
        B = 8'h3c;
        ALU_Sel = 4'b0001;
        #10;
        $display("Subtraction: A = %d, B = %d, ALU_Out = %d, CarryOut = %b", A, B, ALU_Out, CarryOut);
        assert(ALU_Out == 8'hae && CarryOut == 1'b1) else $fatal(1,"Test Case 8 failed");

        A = 8'hc4;
        B = 8'h7b;
        ALU_Sel = 4'b0001;
        #10;
        $display("Subtraction: A = %d, B = %d, ALU_Out = %d, CarryOut = %b", A, B, ALU_Out, CarryOut);
        assert(ALU_Out == 8'h49 && CarryOut == 1'b1) else $fatal(1,"Test Case 9 failed");

        A = 8'h2b;
        B = 8'h6;
        ALU_Sel = 4'b0001;
        #10;
        $display("Subtraction: A = %d, B = %d, ALU_Out = %d, CarryOut = %b", A, B, ALU_Out, CarryOut);
        assert(ALU_Out == 8'h25 && CarryOut == 1'b0) else $fatal(1,"Test Case 10 failed");

        // Test Multiplication
        A = 8'he;
        B = 8'hb;
        ALU_Sel = 4'b0010;
        #10;
        $display("Multiplication: A = %d, B = %d, ALU_Out = %d, CarryOut = %b", A, B, ALU_Out, CarryOut);
        assert(ALU_Out == 8'h9a && CarryOut == 1'b0) else $fatal(1,"Test Case 11 failed");

        A = 8'hc;
        B = 8'h3;
        ALU_Sel = 4'b0010;
        #10;
        $display("Multiplication: A = %d, B = %d, ALU_Out = %d, CarryOut = %b", A, B, ALU_Out, CarryOut);
        assert(ALU_Out == 8'h24 && CarryOut == 1'b0) else $fatal(1,"Test Case 12 failed");

        A = 8'hc;
        B = 8'h3;
        ALU_Sel = 4'b0010;
        #10;
        $display("Multiplication: A = %d, B = %d, ALU_Out = %d, CarryOut = %b", A, B, ALU_Out, CarryOut);
        assert(ALU_Out == 8'h24 && CarryOut == 1'b0) else $fatal(1,"Test Case 13 failed");

        A = 8'hf;
        B = 8'ha;
        ALU_Sel = 4'b0010;
        #10;
        $display("Multiplication: A = %d, B = %d, ALU_Out = %d, CarryOut = %b", A, B, ALU_Out, CarryOut);
        assert(ALU_Out == 8'h96 && CarryOut == 1'b0) else $fatal(1,"Test Case 14 failed");

        A = 8'h0;
        B = 8'h0;
        ALU_Sel = 4'b0010;
        #10;
        $display("Multiplication: A = %d, B = %d, ALU_Out = %d, CarryOut = %b", A, B, ALU_Out, CarryOut);
        assert(ALU_Out == 8'h0 && CarryOut == 1'b0) else $fatal(1,"Test Case 15 failed");

        // Test Division
        A = 8'h24;
        B = 8'h22;
        ALU_Sel = 4'b0011;
        #10;
        $display("Division: A = %d, B = %d, ALU_Out = %d, CarryOut = %b", A, B, ALU_Out, CarryOut);
        assert(ALU_Out == 8'h1) else $fatal(1,"Test Case 17 failed");

        A = 8'h1d;
        B = 8'h4;
        ALU_Sel = 4'b0011;
        #10;
        $display("Division: A = %d, B = %d, ALU_Out = %d, CarryOut = %b", A, B, ALU_Out, CarryOut);
        assert(ALU_Out == 8'h7) else $fatal(1,"Test Case 18 failed");

        A = 8'h13;
        B = 8'h11;
        ALU_Sel = 4'b0011;
        #10;
        $display("Division: A = %d, B = %d, ALU_Out = %d, CarryOut = %b", A, B, ALU_Out, CarryOut);
        assert(ALU_Out == 8'h1) else $fatal(1,"Test Case 19 failed");

        A = 8'hf4;
        B = 8'h2f;
        ALU_Sel = 4'b0011;
        #10;
        $display("Division: A = %d, B = %d, ALU_Out = %d, CarryOut = %b", A, B, ALU_Out, CarryOut);
        assert(ALU_Out == 8'h5) else $fatal(1,"Test Case 20 failed");

        A = 8'hb7;
        B = 8'h5a;
        ALU_Sel = 4'b0011;
        #10;
        $display("Division: A = %d, B = %d, ALU_Out = %d, CarryOut = %b", A, B, ALU_Out, CarryOut);
        assert(ALU_Out == 8'h2) else $fatal(1,"Test Case 21 failed");

        // Test Default Case
        ALU_Sel = 4'b0100;
        #10;
        $display("Default: A = %d, B = %d, ALU_Out = %h, CarryOut = %b", A, B, ALU_Out, CarryOut);
        assert(ALU_Out == 8'hAC) else $fatal(1,"Test Case 22 failed");

        // Finish simulation
        $finish;
    end

endmodule

verification_101/final_project/subproj1/alu_auto_tb.vcd
$date
    Feb 22, 2025  10:57:34
$end
$version
    TOOL:	xmsim(64)	24.09-s001
$end
$timescale
    1 ns
$end

$scope module alu_auto_tb $end
$var reg       1 !    clock $end
$var reg       1 "    reset $end
$var reg       8 #    A [7:0] $end
$var reg       8 $    B [7:0] $end
$var reg       4 %    ALU_Sel [3:0] $end
$var reg       8 &    ALU_Out [7:0] $end
$var reg       1 '    CarryOut $end

$scope module alu_inst $end
$var wire      1 (    clock  $end
$var wire      1 )    reset  $end
$var wire      8 *    A [7:0] $end
$var wire      8 +    B [7:0] $end
$var wire      4 ,    ALU_Sel [3:0] $end
$var reg       8 -    ALU_Out [7:0] $end
$var reg       1 .    CarryOut $end
$var reg       8 /    ALU_Result [7:0] $end
$var wire      9 0    tmp [8:0] $end
$upscope $end

$upscope $end

$enddefinitions $end
$dumpvars
0!
x"
bx #
bx $
bx %
bx &
0'
0(
x)
bx *
bx +
bx ,
bx -
0.
bx /
bx 0
$end
#5
1!
1(
#10
1"
b0 #
b0 $
b0 %
0!
0(
b0 ,
b0 +
b0 *
1)
b0 /
b0 0
b0 -
b0 &
#15
1!
1(
#20
0"
0!
0(
0)
#25
1!
1(
#30
b10011101 #
b1100000 $
0!
0(
b1100000 +
b10011101 *
b11111101 /
b11111101 0
#35
1!
1(
b11111101 -
b11111101 &
#40
b10110001 #
b10011111 $
0!
0(
b10011111 +
b10110001 *
b1010000 /
b101010000 0
#45
1!
1(
b1010000 -
1.
1'
b1010000 &
#50
b10010111 #
b11011 $
0!
0(
b11011 +
b10010111 *
b10110010 /
b10110010 0
#55
1!
1(
b10110010 -
0.
0'
b10110010 &
#60
b100111 #
b11000 $
0!
0(
b11000 +
b100111 *
b111111 /
b111111 0
#65
1!
1(
b111111 -
b111111 &
#70
b10001001 #
b111000 $
0!
0(
b111000 +
b10001001 *
b11000001 /
b11000001 0
#75
1!
1(
b11000001 -
b11000001 &
#80
b1010101 #
b110110 $
b1 %
0!
0(
b1 ,
b110110 +
b1010101 *
b11111 /
b10001011 0
#85
1!
1(
b11111 -
b11111 &
#90
b111000 #
b10000 $
0!
0(
b10000 +
b111000 *
b101000 /
b1001000 0
#95
1!
1(
b101000 -
b101000 &
#100
b11101010 #
b111100 $
0!
0(
b111100 +
b11101010 *
b10101110 /
b100100110 0
#105
1!
1(
b10101110 -
1.
1'
b10101110 &
#110
b11000100 #
b1111011 $
0!
0(
b1111011 +
b11000100 *
b1001001 /
b100111111 0
#115
1!
1(
b1001001 -
b1001001 &
#120
b101011 #
b110 $
0!
0(
b110 +
b101011 *
b100101 /
b110001 0
#125
1!
1(
b100101 -
0.
0'
b100101 &
#130
b1110 #
b1011 $
b10 %
0!
0(
b10 ,
b1011 +
b1110 *
b10011010 /
b11001 0
#135
1!
1(
b10011010 -
b10011010 &
#140
b1100 #
b11 $
0!
0(
b11 +
b1100 *
b100100 /
b1111 0
#145
1!
1(
b100100 -
b100100 &
#150
0!
0(
#155
1!
1(
#160
b1111 #
b1010 $
0!
0(
b1010 +
b1111 *
b10010110 /
b11001 0
#165
1!
1(
b10010110 -
b10010110 &
#170
b0 #
b0 $
0!
0(
b0 +
b0 *
b0 /
b0 0
#175
1!
1(
b0 -
b0 &
#180
b100100 #
b100010 $
b11 %
0!
0(
b11 ,
b100010 +
b100100 *
b1 /
b1000110 0
#185
1!
1(
b1 -
b1 &
#190
b11101 #
b100 $
0!
0(
b100 +
b11101 *
b111 /
b100001 0
#195
1!
1(
b111 -
b111 &
#200
b10011 #
b10001 $
0!
0(
b10001 +
b10011 *
b1 /
b100100 0
#205
1!
1(
b1 -
b1 &
#210
b11110100 #
b101111 $
0!
0(
b101111 +
b11110100 *
b101 /
b100100011 0
#215
1!
1(
b101 -
1.
1'
b101 &
#220
b10110111 #
b1011010 $
0!
0(
b1011010 +
b10110111 *
b10 /
b100010001 0
#225
1!
1(
b10 -
b10 &
#230
b100 %
0!
0(
b100 ,
b10101100 /
#235
1!
1(
b10101100 -
b10101100 &
