hdl_intro_files/practice_03/register8.sv
module register8(
    input logic clk, reset,
    input logic [7:0]in_word,
    output logic [7:0]out_word
);

always_ff@(posedge clk)begin
    if (reset)
        begin
            out_word <= 8'b0;
        end
    else
        begin
            out_word <= in_word;
        end
end

endmodule

hdl_intro_files/practice_03/register8_bank.sv
module register8_bank(
    input logic clk, rst, write_enable,
    input logic [2:0]write_addr,
    input logic [2:0]reg_addr_1, reg_addr_2,
    input logic [7:0]write_data,
    output logic [7:0] reg_data_1, reg_data_2

);

logic [7:0] X0_in_word, X1_in_word, X2_in_word, X3_in_word, X4_in_word, X5_in_word, X6_in_word, X7_in_word;
logic [7:0] X0_out_word, X1_out_word, X2_out_word, X3_out_word, X4_out_word, X5_out_word, X6_out_word, X7_out_word;

logic enable_ff;


register8 X0(.clk(clk), .reset(rst), .in_word(8'b0), .out_word(X0_out_word));
register8 X1(.clk(clk), .reset(rst), .in_word(X1_in_word), .out_word(X1_out_word));
register8 X2(.clk(clk), .reset(rst), .in_word(X2_in_word), .out_word(X2_out_word));
register8 X3(.clk(clk), .reset(rst), .in_word(X3_in_word), .out_word(X3_out_word));
register8 X4(.clk(clk), .reset(rst), .in_word(X4_in_word), .out_word(X4_out_word));
register8 X5(.clk(clk), .reset(rst), .in_word(X5_in_word), .out_word(X5_out_word));
register8 X6(.clk(clk), .reset(rst), .in_word(X6_in_word), .out_word(X6_out_word));
register8 X7(.clk(clk), .reset(rst), .in_word(X7_in_word), .out_word(X7_out_word));


always_ff @(posedge clk) begin
    if(rst) 
        begin
            X1_in_word <= 8'b0;
            X2_in_word <= 8'b0;
            X3_in_word <= 8'b0;
            X4_in_word <= 8'b0;
            X5_in_word <= 8'b0;
            X6_in_word <= 8'b0;
            X7_in_word <= 8'b0;
        end
    else if(write_enable)
        begin
            case(write_addr)
                3'b001:
                    X1_in_word <= write_data;
                3'b010:
                    X2_in_word <= write_data;
                3'b011:
                    X3_in_word <= write_data;
                3'b100:
                    X4_in_word <= write_data;
                3'b101:
                    X5_in_word <= write_data;
                3'b110:
                    X6_in_word <= write_data;
                3'b111:
                    X7_in_word <= write_data;
            endcase
        end
end


always_comb 
begin
    case(reg_addr_1)
        3'b000:
            reg_data_1 = X0_out_word;
        3'b001:
            reg_data_1 = X1_out_word;
        3'b010:
            reg_data_1 = X2_out_word;
        3'b011:
            reg_data_1 = X3_out_word;
        3'b100:
            reg_data_1 = X4_out_word;
        3'b101:
            reg_data_1 = X5_out_word;
        3'b110:
            reg_data_1 = X6_out_word;
        3'b111:
            reg_data_1 = X7_out_word;
        default:
            reg_data_1 = X0_out_word;
    endcase

    case(reg_addr_2)
        3'b000:
            reg_data_2 = X0_out_word;
        3'b001:
            reg_data_2 = X1_out_word;
        3'b010:
            reg_data_2 = X2_out_word;
        3'b011:
            reg_data_2 = X3_out_word;
        3'b100:
            reg_data_2 = X4_out_word;
        3'b101:
            reg_data_2 = X5_out_word;
        3'b110:
            reg_data_2 = X6_out_word;
        3'b111:
            reg_data_2 = X7_out_word;
        default:
            reg_data_2 = X0_out_word;
    endcase 

end



endmodule

hdl_intro_files/practice_03/register8_bank_tb.sv
`timescale 1ns/1ps
module register8_bank_tb();

    logic test_clk, test_reset, write_enable;
    logic [7:0] write_data;
    logic [2:0] write_addr, reg_addr_1, reg_addr_2;
    logic [7:0] reg_data_1, reg_data_2;


    register8_bank dut(
        .clk(test_clk),
        .rst(test_reset),
        .write_enable(write_enable),
        .write_addr(write_addr),
        .reg_addr_1(reg_addr_1),
        .reg_addr_2(reg_addr_2),
        .write_data(write_data),
        .reg_data_1(reg_data_1),
        .reg_data_2(reg_data_2)
    );

    initial begin
        test_clk = 1'b0;
        forever begin
            #5 test_clk = ~test_clk;
        end
    end

    initial begin
        $dumpfile("register8_bank_tb.vcd");
        $dumpvars(0, register8_bank_tb);

        @(posedge test_clk);
        test_reset = 1'b1;
        #5 
        test_reset = 1'b0;
        #5

        //Test Case 0
        assert(reg_data_1 == 8'h00 && reg_data_2 == 8'h00) else $fatal("Test Case 0 failed");
        #5


        /* 
             Set #1 of tests: Writing on registers
                Test Cases 1 to 9 covers the writing process on each of the registers, X1 to X7, present on the register bank. 
                Some tests to cover the writing withtou premission cases were also created. 
                Further tests should be presented on the next sets test cases.
        */


        //Test Case 1 - Write to register X1
        @(posedge test_clk);
        write_enable = 1'b1;
        write_data = 8'hAA;
        write_addr = 3'b001;
        reg_addr_1 = 3'b001;
        #20
        write_enable = 1'b0;
        // #10
        assert(reg_data_1 == 8'hAA && reg_data_2 == 8'h00) else $fatal("Test Case 1 failed");


        //Test Case 2 - Write to register X2
        @(posedge test_clk);
        write_enable = 1'b1;
        write_data = 8'hBB;
        write_addr = 3'b010;
        reg_addr_2 = 3'b010;
        #20
        write_enable = 1'b0;
        assert(reg_data_1 == 8'hAA && reg_data_2 == 8'hBB) else $fatal("Test Case 2 failed");

        //Test Case 3 - Write to register X1 with no permission to write enabled.
        @(posedge test_clk);
        write_enable = 1'b0;
        write_data = 8'hFF;
        write_addr = 3'b001;
        #10
        assert(reg_data_1 == 8'hAA && reg_data_2 == 8'hBB) else $fatal("Test Case 3 failed");

        //Test Case 4 - Write to register X3 with reg_data_2 unchanged from the previous test case.
        @(posedge test_clk);
        write_enable = 1'b1;
        write_data = 8'hCC;
        write_addr = 3'b011; //==> Register X3
        reg_addr_1 = 3'b011;
        #20
        write_enable = 1'b0;
        assert(reg_data_1 == 8'hCC && reg_data_2 == 8'hBB) else $fatal("Test Case 4 failed");

        //Test Case 5 - Write to register X4 with reg_data_1 unchanged from the previous test case.
        @(posedge test_clk);
        write_enable = 1'b1;
        write_data = 8'hDD;
        write_addr = 3'b100; //==> Register X4
        reg_addr_2 = 3'b100;
        #20
        write_enable = 1'b0;
        assert(reg_data_1 == 8'hCC && reg_data_2 == 8'hDD) else $fatal("Test Case 5 failed");


        //Test Case 6 - Write to register X4 with no permission to write on it.
        @(posedge test_clk);
        write_enable = 1'b0;
        write_data = 8'hFF;
        write_addr = 3'b100;
        #10
        assert(reg_data_1 == 8'hCC && reg_data_2 == 8'hDD) else $fatal("Test Case 6 failed");

        //Test Case 7 - Write to register X5 with reg_data_2 unchanged from X4 register writing test case.
        @(posedge test_clk);
        write_enable = 1'b1;
        write_data = 8'hEE;
        write_addr = 3'b101; //==> Register X5
        reg_addr_1 = 3'b101;
        #20
        write_enable = 1'b0;
        assert(reg_data_1 == 8'hEE && reg_data_2 == 8'hDD) else $fatal("Test Case 7 failed");

        //Test Case 8 - Write to register X6 with reg_data_1 unchanged from the previous test case.
        @(posedge test_clk);
        write_enable = 1'b1;
        write_data = 8'hFF;
        write_addr = 3'b110; //==> Register X6
        reg_addr_2 = 3'b110;
        #20
        write_enable = 1'b0;
        assert(reg_data_1 == 8'hEE && reg_data_2 == 8'hFF) else $fatal("Test Case 8 failed");

        //Test Case 9 - Write to register X7 with reg_data_2 unchanged from the previous test case.
        @(posedge test_clk);
        write_enable = 1'b1;
        write_data = 8'h11;
        write_addr = 3'b111; //==> Register X7
        reg_addr_1 = 3'b111;
        #20
        write_enable = 1'b0;
        assert(reg_data_1 == 8'h11 && reg_data_2 == 8'hFF) else $fatal("Test Case 9 failed");


        /*
            Set #2: Reading from the previous set registers.
                This set of test cases covers the reading of the values previously set on the register
                of the register bank being tested.
                All the values read must match the values set on the test cases above.
        */

        //Test Case 10 - Reading the current value from the registers X1 and X2
        @(posedge test_clk);
        reg_addr_1 = 3'b001; //Register X1
        reg_addr_2 = 3'b010; //Register X2
        #10
        assert(reg_data_1 == 8'hAA && reg_data_2 == 8'hBB) else $fatal("Test Case 10 failed");

        //Test Case 11 - Reading the current value from the registers X3 and X4
        @(posedge test_clk);
        reg_addr_1 = 3'b011; //Register X3
        reg_addr_2 = 3'b100; //Register X4
        #10
        assert(reg_data_1 == 8'hCC && reg_data_2 == 8'hDD) else $fatal("Test Case 11 failed");

        //Test Case 12 - Reading the current value from the registers X5 and X6
        @(posedge test_clk);
        reg_addr_1 = 3'b101; //Register X5
        reg_addr_2 = 3'b110; //Register X6
        #10
        assert(reg_data_1 == 8'hEE && reg_data_2 == 8'hFF) else $fatal("Test Case 12 failed");

        //Test Case 13 - Reading the current value from the registers X7 and X0
        @(posedge test_clk);
        reg_addr_1 = 3'b111; //Register X7
        reg_addr_2 = 3'b000; //Register X1
        #10
        assert(reg_data_1 == 8'h11 && reg_data_2 == 8'h00) else $fatal("Test Case 13 failed");

        /* 
            Set#3: Resetting all the registers from the register bank
                The next set of tests covers a bulk reset on all of the registers from the
                register bank under test, followed by assertions that the registers were
                zeroed indeed.
        */

        @(posedge test_clk);
        //Setting the reset process.
        test_reset = 1'b1;
        #10
        test_reset = 1'b0;
        #10

        //Test Case 14 - Reading the current value from the registers X1 and X2 after the reset process.
        @(posedge test_clk);
        reg_addr_1 = 3'b001; //Register X1
        reg_addr_2 = 3'b010; //Register X2
        #10
        assert(reg_data_1 == 8'h00 && reg_data_2 == 8'h00) else $fatal("Test Case 14 failed");

        //Test Case 15 - Reading the current value from the registers X3 and X4 after the reset process.
        @(posedge test_clk);
        reg_addr_1 = 3'b011; //Register X3
        reg_addr_2 = 3'b100; //Register X4
        #10
        assert(reg_data_1 == 8'h00 && reg_data_2 == 8'h00) else $fatal("Test Case 15 failed");

        //Test Case 16 - Reading the current value from the registers X5 and X6 after the reset process.
        @(posedge test_clk);
        reg_addr_1 = 3'b101; //Register X5
        reg_addr_2 = 3'b110; //Register X6
        #10
        assert(reg_data_1 == 8'h00 && reg_data_2 == 8'h00) else $fatal("Test Case 16 failed");

        //Test Case 17 - Reading the current value from the registers X7 and X1 after the reset process.
        @(posedge test_clk);
        reg_addr_1 = 3'b111; //Register X7
        reg_addr_2 = 3'b000; //Register X0
        #10
        assert(reg_data_1 == 8'h00 && reg_data_2 == 8'h00) else $fatal("Test Case 17 failed");

        #10 $finish;
    end

    initial
    begin
      $display("                Tempo               Entradas LUT                                    Saídas");
      $display("                         clk  rst  we3   wa3   ra1    ra2        wd3                rd1         rd2");
      $display("                ====   =================================================        =====================");
      /* $monitor($time,"      %b    %b    %b    %b   %b    %b      %b         %b      %b", test_clk, test_reset, write_enable, 
                                                                    write_addr, reg_addr_1, reg_addr_2, write_data, 
                                                                    reg_data_1, reg_data_2);
 */    end

    always@(posedge test_clk)begin
      $display($time,"      %b    %b    %b    %b   %b    %b      %b         %b      %b", test_clk, test_reset, write_enable, 
                                                                    write_addr, reg_addr_1, reg_addr_2, write_data, 
                                                                    reg_data_1, reg_data_2);
    end



endmodule

hdl_intro_files/practice_03/register8_bank_tb.vcd
$version Generated by VerilatedVcd $end
$timescale 1ps $end
 $scope module TOP $end
  $scope module register8_bank_tb $end
   $var wire 1 8 test_clk $end
   $var wire 1 # test_reset $end
   $var wire 1 $ write_enable $end
   $var wire 8 % write_data [7:0] $end
   $var wire 3 & write_addr [2:0] $end
   $var wire 3 ' reg_addr_1 [2:0] $end
   $var wire 3 ( reg_addr_2 [2:0] $end
   $var wire 8 9 reg_data_1 [7:0] $end
   $var wire 8 : reg_data_2 [7:0] $end
   $scope module dut $end
    $var wire 1 8 clk $end
    $var wire 1 # rst $end
    $var wire 1 $ write_enable $end
    $var wire 3 & write_addr [2:0] $end
    $var wire 3 ' reg_addr_1 [2:0] $end
    $var wire 3 ( reg_addr_2 [2:0] $end
    $var wire 8 % write_data [7:0] $end
    $var wire 8 9 reg_data_1 [7:0] $end
    $var wire 8 : reg_data_2 [7:0] $end
    $var wire 8 ) X1_in_word [7:0] $end
    $var wire 8 * X2_in_word [7:0] $end
    $var wire 8 + X3_in_word [7:0] $end
    $var wire 8 , X4_in_word [7:0] $end
    $var wire 8 - X5_in_word [7:0] $end
    $var wire 8 . X6_in_word [7:0] $end
    $var wire 8 / X7_in_word [7:0] $end
    $var wire 8 0 X0_out_word [7:0] $end
    $var wire 8 1 X1_out_word [7:0] $end
    $var wire 8 2 X2_out_word [7:0] $end
    $var wire 8 3 X3_out_word [7:0] $end
    $var wire 8 4 X4_out_word [7:0] $end
    $var wire 8 5 X5_out_word [7:0] $end
    $var wire 8 6 X6_out_word [7:0] $end
    $var wire 8 7 X7_out_word [7:0] $end
    $scope module X0 $end
     $var wire 1 8 clk $end
     $var wire 1 # reset $end
     $var wire 8 ; in_word [7:0] $end
     $var wire 8 0 out_word [7:0] $end
    $upscope $end
    $scope module X1 $end
     $var wire 1 8 clk $end
     $var wire 1 # reset $end
     $var wire 8 ) in_word [7:0] $end
     $var wire 8 1 out_word [7:0] $end
    $upscope $end
    $scope module X2 $end
     $var wire 1 8 clk $end
     $var wire 1 # reset $end
     $var wire 8 * in_word [7:0] $end
     $var wire 8 2 out_word [7:0] $end
    $upscope $end
    $scope module X3 $end
     $var wire 1 8 clk $end
     $var wire 1 # reset $end
     $var wire 8 + in_word [7:0] $end
     $var wire 8 3 out_word [7:0] $end
    $upscope $end
    $scope module X4 $end
     $var wire 1 8 clk $end
     $var wire 1 # reset $end
     $var wire 8 , in_word [7:0] $end
     $var wire 8 4 out_word [7:0] $end
    $upscope $end
    $scope module X5 $end
     $var wire 1 8 clk $end
     $var wire 1 # reset $end
     $var wire 8 - in_word [7:0] $end
     $var wire 8 5 out_word [7:0] $end
    $upscope $end
    $scope module X6 $end
     $var wire 1 8 clk $end
     $var wire 1 # reset $end
     $var wire 8 . in_word [7:0] $end
     $var wire 8 6 out_word [7:0] $end
    $upscope $end
    $scope module X7 $end
     $var wire 1 8 clk $end
     $var wire 1 # reset $end
     $var wire 8 / in_word [7:0] $end
     $var wire 8 7 out_word [7:0] $end
    $upscope $end
   $upscope $end
  $upscope $end
 $upscope $end
$enddefinitions $end


#0
0#
0$
b00000000 %
b000 &
b000 '
b000 (
b00000000 )
b00000000 *
b00000000 +
b00000000 ,
b00000000 -
b00000000 .
b00000000 /
b00000000 0
b00000000 1
b00000000 2
b00000000 3
b00000000 4
b00000000 5
b00000000 6
b00000000 7
08
b00000000 9
b00000000 :
b00000000 ;
#5000
1#
18
#10000
0#
08
#15000
18
#20000
08
#25000
1$
b10101010 %
b001 &
b001 '
b10101010 )
18
#30000
08
#35000
b10101010 1
18
b10101010 9
#40000
08
#45000
0$
18
#50000
08
#55000
1$
b10111011 %
b010 &
b010 (
b10111011 *
18
#60000
08
#65000
b10111011 2
18
b10111011 :
#70000
08
#75000
0$
18
#80000
08
#85000
b11111111 %
b001 &
18
#90000
08
#95000
18
#100000
08
#105000
1$
b11001100 %
b011 &
b011 '
b11001100 +
18
b00000000 9
#110000
08
#115000
b11001100 3
18
b11001100 9
#120000
08
#125000
0$
18
#130000
08
#135000
1$
b11011101 %
b100 &
b100 (
b11011101 ,
18
b00000000 :
#140000
08
#145000
b11011101 4
18
b11011101 :
#150000
08
#155000
0$
18
#160000
08
#165000
b11111111 %
18
#170000
08
#175000
18
#180000
08
#185000
1$
b11101110 %
b101 &
b101 '
b11101110 -
18
b00000000 9
#190000
08
#195000
b11101110 5
18
b11101110 9
#200000
08
#205000
0$
18
#210000
08
#215000
1$
b11111111 %
b110 &
b110 (
b11111111 .
18
b00000000 :
#220000
08
#225000
b11111111 6
18
b11111111 :
#230000
08
#235000
0$
18
#240000
08
#245000
1$
b00010001 %
b111 &
b111 '
b00010001 /
18
b00000000 9
#250000
08
#255000
b00010001 7
18
b00010001 9
#260000
08
#265000
0$
18
#270000
08
#275000
b001 '
b010 (
18
b10101010 9
b10111011 :
#280000
08
#285000
18
#290000
08
#295000
b011 '
b100 (
18
b11001100 9
b11011101 :
#300000
08
#305000
18
#310000
08
#315000
b101 '
b110 (
18
b11101110 9
b11111111 :
#320000
08
#325000
18
#330000
08
#335000
b111 '
b000 (
18
b00010001 9
b00000000 :
#340000
08
#345000
18
#350000
08
#355000
1#
b00000000 )
b00000000 *
b00000000 +
b00000000 ,
b00000000 -
b00000000 .
b00000000 /
b00000000 1
b00000000 2
b00000000 3
b00000000 4
b00000000 5
b00000000 6
b00000000 7
18
b00000000 9
#360000
08
#365000
0#
18
#370000
08
#375000
18
#380000
08
#385000
b001 '
b010 (
18
#390000
08
#395000
18
#400000
08
#405000
b011 '
b100 (
18
#410000
08
#415000
18
#420000
08
#425000
b101 '
b110 (
18
#430000
08
#435000
18
#440000
08
#445000
b111 '
b000 (
18
