digital_logic/misc/aula_09/exercicio_01/pulse_detector.sv
`timescale 1ns/1ns

module pulse_detector (
    input logic clk, 
    input logic rst,
    input logic a_signal, b_signal,

    output logic seq_a, seq_b
);


typedef enum { INITIAL_STATE=0, COUNTS_A=1, COUNTS_B=2, WATCH_INPUTS=3,
               SEND_SIG_A=4, SEND_SIG_B=5} internal_states;


internal_states current_state_ff, next_state_comb;

logic [2:0] count_a, count_b;
logic rise_a, rise_b;


always_ff @(posedge clk) begin
    current_state_ff <= next_state_comb;
end

always_ff @(posedge a_signal or negedge a_signal) begin
    rise_a <= a_signal ? 1'b1 : 1'b0; 
end

always_ff @(posedge b_signal or negedge b_signal) begin
    rise_b <= b_signal ? 1'b1 : 1'b0; 
end

always_comb begin

    next_state_comb = current_state_ff;

    seq_a = 0;
    seq_b = 0;

    if(rst) begin
        next_state_comb = INITIAL_STATE;
    end
    
    else begin
        case(current_state_ff)
            INITIAL_STATE: begin
                count_a = '0;
                count_b = '0;

                next_state_comb = WATCH_INPUTS;                
                // if(a_signal)
                //     next_state_comb = COUNTS_A;
                // else if(b_signal)
                //     next_state_comb = COUNTS_B;
            end

            WATCH_INPUTS: begin
                if(rise_a) begin
                    next_state_comb = COUNTS_A;
                end
                else if(rise_b) begin
                    next_state_comb = COUNTS_B;
                end
                else
                    next_state_comb = WATCH_INPUTS;
            end


            COUNTS_A: begin
               count_a = count_a + 1;
               count_b = 0;
               if (count_a == 3)
                    next_state_comb = SEND_SIG_A;
                else
                    next_state_comb = WATCH_INPUTS;
            end

            COUNTS_B: begin
               count_b = count_b + 1;
               count_a = 0;
               if (count_b == 3)
                    next_state_comb = SEND_SIG_B;
               else 
                    next_state_comb = WATCH_INPUTS;
            end

            SEND_SIG_A: begin
                seq_a = 1;
                next_state_comb = INITIAL_STATE;
            end

            SEND_SIG_B: begin
                seq_b = 1;
                next_state_comb = INITIAL_STATE;
            end

        endcase
    end
end

    
endmodule

digital_logic/misc/aula_09/exercicio_01/pulse_detector_tb.sv
/* verilator lint_off UNUSEDSIGNAL */
`timescale 1ns/1ns

module pulse_detector_tb();

    logic dut_clk;
    logic mock_reset = 0;
    logic mock_a = 0; 
    logic mock_b = 0;
    logic dut_seq_a, dut_seq_b;

    initial
    begin
        dut_clk = 1;
        forever #1 dut_clk = ~dut_clk;
    end

    pulse_detector dut (
        .clk(dut_clk),
        .rst(mock_reset),
        .a_signal(mock_a),
        .b_signal(mock_b),
        .seq_a(dut_seq_a),
        .seq_b(dut_seq_b)
    );

    initial
    begin
        $dumpfile("pulse_detector_tb.vcd");
        $dumpvars(0, pulse_detector);

        mock_reset = 1;
        #2;
        mock_reset = 0;

        @(posedge dut_clk);
        mock_a = 1;
        #2;
        mock_a = 0;

        @(posedge dut_clk);
        mock_a = 1;
        #2;
        mock_a = 0;
        
        @(posedge dut_clk);
        mock_a = 1;
        #2;
        mock_a = 0;
        
        #10; //Changing the set of state changes
        
        /*
        //Testing rising B
        @(posedge dut_clk);
        mock_b = 1;
        #1
        mock_b = 0;

        @(posedge dut_clk);
        mock_b = 1;
        #1
        mock_b = 0;
        
        @(posedge dut_clk);
        mock_b = 1;
        #1
        mock_b = 0;

        #10; //Changing the set of state changes
        
        @(posedge dut_clk);
        mock_a = 1; 
        #5
        mock_a = 0;

        // #10
        @(posedge dut_clk);
        mock_a = 1;
        #5
        mock_a = 0;

        // #10
        @(posedge dut_clk);
        mock_b = 1;
        #5
        mock_b = 0;

        */

        #30;
        $finish;

    end


    // initial
    // begin
    //   $display("                Tempo   Entradas LUT        Saídas");
    //   $display("                         A   B   C   D       OUT");
    //   $display("                ====   ================      =======");
    //   $monitor($time,"     %b   %b   %b   %b        %b", A, B, C, D, OUT);
    // end


endmodule

digital_logic/misc/aula_09/exercicio_01/pulse_detector_tb.vcd
$version Generated by VerilatedVcd $end
$timescale 1ns $end
 $scope module TOP $end
  $scope module pulse_detector_tb $end
   $var wire 1 $ dut_clk $end
   $var wire 1 % mock_reset $end
   $var wire 1 & mock_a $end
   $var wire 1 # mock_b $end
   $var wire 1 ' dut_seq_a $end
   $var wire 1 ( dut_seq_b $end
   $scope module dut $end
    $var wire 1 $ clk $end
    $var wire 1 % rst $end
    $var wire 1 & a_signal $end
    $var wire 1 # b_signal $end
    $var wire 1 ' seq_a $end
    $var wire 1 ( seq_b $end
    $var wire 32 ) current_state_ff [31:0] $end
    $var wire 32 * next_state_comb [31:0] $end
    $var wire 3 + count_a [2:0] $end
    $var wire 3 , count_b [2:0] $end
    $var wire 1 - rise_a $end
    $var wire 1 . rise_b $end
   $upscope $end
  $upscope $end
 $upscope $end
$enddefinitions $end


#0
0#
1$
1%
0&
0'
0(
b00000000000000000000000000000000 )
b00000000000000000000000000000000 *
b000 +
b000 ,
0-
0.
#1
0$
#2
1$
0%
b00000000000000000000000000000011 )
b00000000000000000000000000000011 *
#3
0$
#4
1$
1&
b00000000000000000000000000000001 *
1-
#5
0$
#6
1$
0&
b00000000000000000000000000000001 )
b00000000000000000000000000000011 *
b001 +
0-
#7
0$
b00000000000000000000000000000100 *
b011 +
#8
1$
1&
b00000000000000000000000000000011 )
b00000000000000000000000000000001 *
b101 +
1-
#9
0$
#10
1$
0&
b00000000000000000000000000000001 )
b00000000000000000000000000000011 *
b110 +
0-
#11
0$
b000 +
#12
1$
1&
b00000000000000000000000000000011 )
b00000000000000000000000000000001 *
b010 +
1-
#13
0$
#14
1$
0&
b00000000000000000000000000000001 )
b00000000000000000000000000000100 *
b011 +
0-
#15
0$
b00000000000000000000000000000011 *
b101 +
#16
1$
b00000000000000000000000000000011 )
b111 +
