arch_digital_sys/MIPSsinglecycleprocessor/mipssingle.sv
/* verilator lint_off DECLFILENAME */
/* verilator lint_off VARHIDDEN */
/* verilator lint_off WIDTHEXPAND */
/* verilator lint_off WIDTHTRUNC */
/* verilator lint_off UNUSEDSIGNAL */
/* verilator lint_off INITIALDLY */
/* verilator lint_off COMBDLY */
// mips.sv
// From Section 7.6 of Digital Design & Computer Architecture
// Updated to SystemVerilog 26 July 2011 David_Harris@hmc.edu
`timescale 1ns/1ps
module testbench();

  logic        clk;
  logic        reset;

  logic [31:0] writedata, dataadr;
  logic        memwrite;

  // instantiate device to be tested
  top dut(clk, reset, writedata, dataadr, memwrite);
  
  // initialize test
  initial
    begin
      $dumpfile("mipssingle.vcd");
      $dumpvars(0, testbench);
      reset <= 1; # 22; reset <= 0;
    end

  // generate clock to sequence tests
  always
    begin
      clk <= 1; # 5; clk <= 0; # 5;
    end
  int count = 0; 
  // check results
  always @(negedge clk)
    begin
      if(memwrite) begin
        if(dataadr === 84 & writedata === 7) begin
          $display("Simulation succeeded");
          $stop;
        end else if (dataadr !== 80) begin
          $display("Simulation failed");
          $stop;
        end
      end

      // count <= count + 1;
      // if(count > 100000) begin
      //   $display("Simulation failed");
      //   $stop;
      // end
    end
endmodule

module top(input  logic        clk, reset, 
           output logic [31:0] writedata, dataadr, 
           output logic        memwrite);

  logic [31:0] pc, instr, readdata;
  
  // instantiate processor and memories
  mips mips(clk, reset, pc, instr, memwrite, dataadr, 
            writedata, readdata);
  imem imem(pc[7:2], instr);
  dmem dmem(clk, memwrite, dataadr, writedata, readdata);
endmodule

module dmem(input  logic        clk, we,
            input  logic [31:0] a, wd,
            output logic [31:0] rd);

  logic [31:0] RAM[63:0];

  assign rd = RAM[a[31:2]]; // word aligned

  always_ff @(posedge clk)
    if (we) RAM[a[31:2]] <= wd;
endmodule

module imem(input  logic [5:0] a,
            output logic [31:0] rd);

  logic [31:0] RAM[63:0];

  initial
      $readmemh("memfile.dat",RAM);

  assign rd = RAM[a]; // word aligned
endmodule

module mips(input  logic        clk, reset,
            output logic [31:0] pc,
            input  logic [31:0] instr,
            output logic        memwrite,
            output logic [31:0] aluout, writedata,
            input  logic [31:0] readdata);

  logic       memtoreg, alusrc, regdst, 
              regwrite, jump, pcsrc, zero;
  logic [2:0] alucontrol;

  controller c(instr[31:26], instr[5:0], zero,
               memtoreg, memwrite, pcsrc,
               alusrc, regdst, regwrite, jump,
               alucontrol);
  datapath dp(clk, reset, memtoreg, pcsrc,
              alusrc, regdst, regwrite, jump,
              alucontrol,
              zero, pc, instr,
              aluout, writedata, readdata);
endmodule

module controller(input  logic [5:0] op, funct,
                  input  logic       zero,
                  output logic       memtoreg, memwrite,
                  output logic       pcsrc, alusrc,
                  output logic       regdst, regwrite,
                  output logic       jump,
                  output logic [2:0] alucontrol);

  logic [1:0] aluop;
  logic       branch;

  maindec md(op, memtoreg, memwrite, branch,
             alusrc, regdst, regwrite, jump, aluop);
  aludec  ad(funct, aluop, alucontrol);

  assign pcsrc = branch & zero;
endmodule

module maindec(input  logic [5:0] op,
               output logic       memtoreg, memwrite,
               output logic       branch, alusrc,
               output logic       regdst, regwrite,
               output logic       jump,
               output logic [1:0] aluop);

  logic [8:0] controls;

  assign {regwrite, regdst, alusrc, branch, memwrite,
          memtoreg, jump, aluop} = controls;

  always_comb
    case(op)
      6'b000000: controls <= 9'b110000010; // RTYPE
      6'b100011: controls <= 9'b101001000; // LW
      6'b101011: controls <= 9'b001010000; // SW
      6'b000100: controls <= 9'b000100001; // BEQ
      6'b001000: controls <= 9'b101000000; // ADDI
      6'b000010: controls <= 9'b000000100; // J
      default:   controls <= 9'bxxxxxxxxx; // illegal op
    endcase
endmodule

module aludec(input  logic [5:0] funct,
              input  logic [1:0] aluop,
              output logic [2:0] alucontrol);

  always_comb
    case(aluop)
      2'b00: alucontrol <= 3'b010;  // add (for lw/sw/addi)
      2'b01: alucontrol <= 3'b110;  // sub (for beq)
      default: case(funct)          // R-type instructions
          6'b100000: alucontrol <= 3'b010; // add
          6'b100010: alucontrol <= 3'b110; // sub
          6'b100100: alucontrol <= 3'b000; // and
          6'b100101: alucontrol <= 3'b001; // or
          6'b101010: alucontrol <= 3'b111; // slt
          default:   alucontrol <= 3'bxxx; // ???
        endcase
    endcase
endmodule

module datapath(input  logic        clk, reset,
                input  logic        memtoreg, pcsrc,
                input  logic        alusrc, regdst,
                input  logic        regwrite, jump,
                input  logic [2:0]  alucontrol,
                output logic        zero,
                output logic [31:0] pc,
                input  logic [31:0] instr,
                output logic [31:0] aluout, writedata,
                input  logic [31:0] readdata);

  logic [4:0]  writereg;
  logic [31:0] pcnext, pcnextbr, pcplus4, pcbranch;
  logic [31:0] signimm, signimmsh;
  logic [31:0] srca, srcb;
  logic [31:0] result;

  // next PC logic
  flopr #(32) pcreg(clk, reset, pcnext, pc);
  adder       pcadd1(pc, 32'b100, pcplus4);
  sl2         immsh(signimm, signimmsh);
  adder       pcadd2(pcplus4, signimmsh, pcbranch);
  mux2 #(32)  pcbrmux(pcplus4, pcbranch, pcsrc, pcnextbr);
  mux2 #(32)  pcmux(pcnextbr, {pcplus4[31:28], 
                    instr[25:0], 2'b00}, jump, pcnext);

  // register file logic
  regfile     rf(clk, regwrite, instr[25:21], instr[20:16], 
                 writereg, result, srca, writedata);
  mux2 #(5)   wrmux(instr[20:16], instr[15:11],
                    regdst, writereg);
  mux2 #(32)  resmux(aluout, readdata, memtoreg, result);
  signext     se(instr[15:0], signimm);

  // ALU logic
  mux2 #(32)  srcbmux(writedata, signimm, alusrc, srcb);
  alu         alu(srca, srcb, alucontrol, aluout, zero);
endmodule

module regfile(input  logic        clk, 
               input  logic        we3, 
               input  logic [4:0]  ra1, ra2, wa3, 
               input  logic [31:0] wd3, 
               output logic [31:0] rd1, rd2);

  logic [31:0] rf[31:0];

  // three ported register file
  // read two ports combinationally
  // write third port on rising edge of clk
  // register 0 hardwired to 0
  // note: for pipelined processor, write third port
  // on falling edge of clk

  always_ff @(posedge clk)
    if (we3) rf[wa3] <= wd3;	

  assign rd1 = (ra1 != 0) ? rf[ra1] : 0;
  assign rd2 = (ra2 != 0) ? rf[ra2] : 0;
endmodule

module adder(input  logic [31:0] a, b,
             output logic [31:0] y);

  assign y = a + b;
endmodule

module sl2(input  logic [31:0] a,
           output logic [31:0] y);

  // shift left by 2
  assign y = {a[29:0], 2'b00};
endmodule

module signext(input  logic [15:0] a,
               output logic [31:0] y);
              
  assign y = {{16{a[15]}}, a};
endmodule

module flopr #(parameter WIDTH = 8)
              (input  logic             clk, reset,
               input  logic [WIDTH-1:0] d, 
               output logic [WIDTH-1:0] q);

  always_ff @(posedge clk, posedge reset)
    if (reset) q <= 0;
    else       q <= d;
endmodule

module mux2 #(parameter WIDTH = 8)
             (input  logic [WIDTH-1:0] d0, d1, 
              input  logic             s, 
              output logic [WIDTH-1:0] y);

  assign y = s ? d1 : d0; 
endmodule

module alu(input  logic [31:0] a, b,
           input  logic [2:0]  alucontrol,
           output logic [31:0] result,
           output logic        zero);

  logic [31:0] condinvb, sum;

  assign condinvb = alucontrol[2] ? ~b : b;
  assign sum = a + condinvb + alucontrol[2];

  always_comb
    case (alucontrol[1:0])
      2'b00: result = a & b;
      2'b01: result = a | b;
      2'b10: result = sum;
      2'b11: result = sum[31];
    endcase

  assign zero = (result == 32'b0);
endmodule

arch_digital_sys/MIPSsinglecycleprocessor/mipssingle.vcd
$version Generated by VerilatedVcd $end
$timescale 1ps $end
 $scope module TOP $end
  $scope module testbench $end
   $var wire 1 b clk $end
   $var wire 1 c reset $end
   $var wire 32 \ writedata [31:0] $end
   $var wire 32 ] dataadr [31:0] $end
   $var wire 1 C memwrite $end
   $var wire 32 j count [31:0] $end
   $scope module dut $end
    $var wire 1 b clk $end
    $var wire 1 c reset $end
    $var wire 32 \ writedata [31:0] $end
    $var wire 32 ] dataadr [31:0] $end
    $var wire 1 C memwrite $end
    $var wire 32 D pc [31:0] $end
    $var wire 32 E instr [31:0] $end
    $var wire 32 d readdata [31:0] $end
    $scope module dmem $end
     $var wire 1 b clk $end
     $var wire 1 C we $end
     $var wire 32 ] a [31:0] $end
     $var wire 32 \ wd [31:0] $end
     $var wire 32 d rd [31:0] $end
    $upscope $end
    $scope module imem $end
     $var wire 6 F a [5:0] $end
     $var wire 32 E rd [31:0] $end
    $upscope $end
    $scope module mips $end
     $var wire 1 b clk $end
     $var wire 1 c reset $end
     $var wire 32 D pc [31:0] $end
     $var wire 32 E instr [31:0] $end
     $var wire 1 C memwrite $end
     $var wire 32 ] aluout [31:0] $end
     $var wire 32 \ writedata [31:0] $end
     $var wire 32 d readdata [31:0] $end
     $var wire 1 G memtoreg $end
     $var wire 1 H alusrc $end
     $var wire 1 I regdst $end
     $var wire 1 J regwrite $end
     $var wire 1 K jump $end
     $var wire 1 e pcsrc $end
     $var wire 1 ^ zero $end
     $var wire 3 L alucontrol [2:0] $end
     $scope module c $end
      $var wire 6 M op [5:0] $end
      $var wire 6 N funct [5:0] $end
      $var wire 1 ^ zero $end
      $var wire 1 G memtoreg $end
      $var wire 1 C memwrite $end
      $var wire 1 e pcsrc $end
      $var wire 1 H alusrc $end
      $var wire 1 I regdst $end
      $var wire 1 J regwrite $end
      $var wire 1 K jump $end
      $var wire 3 L alucontrol [2:0] $end
      $var wire 2 O aluop [1:0] $end
      $var wire 1 P branch $end
      $scope module ad $end
       $var wire 6 N funct [5:0] $end
       $var wire 2 O aluop [1:0] $end
       $var wire 3 L alucontrol [2:0] $end
      $upscope $end
      $scope module md $end
       $var wire 6 M op [5:0] $end
       $var wire 1 G memtoreg $end
       $var wire 1 C memwrite $end
       $var wire 1 P branch $end
       $var wire 1 H alusrc $end
       $var wire 1 I regdst $end
       $var wire 1 J regwrite $end
       $var wire 1 K jump $end
       $var wire 2 O aluop [1:0] $end
       $var wire 9 Q controls [8:0] $end
      $upscope $end
     $upscope $end
     $scope module dp $end
      $var wire 1 b clk $end
      $var wire 1 c reset $end
      $var wire 1 G memtoreg $end
      $var wire 1 e pcsrc $end
      $var wire 1 H alusrc $end
      $var wire 1 I regdst $end
      $var wire 1 J regwrite $end
      $var wire 1 K jump $end
      $var wire 3 L alucontrol [2:0] $end
      $var wire 1 ^ zero $end
      $var wire 32 D pc [31:0] $end
      $var wire 32 E instr [31:0] $end
      $var wire 32 ] aluout [31:0] $end
      $var wire 32 \ writedata [31:0] $end
      $var wire 32 d readdata [31:0] $end
      $var wire 5 R writereg [4:0] $end
      $var wire 32 f pcnext [31:0] $end
      $var wire 32 g pcnextbr [31:0] $end
      $var wire 32 S pcplus4 [31:0] $end
      $var wire 32 T pcbranch [31:0] $end
      $var wire 32 U signimm [31:0] $end
      $var wire 32 V signimmsh [31:0] $end
      $var wire 32 _ srca [31:0] $end
      $var wire 32 ` srcb [31:0] $end
      $var wire 32 h result [31:0] $end
      $scope module alu $end
       $var wire 32 _ a [31:0] $end
       $var wire 32 ` b [31:0] $end
       $var wire 3 L alucontrol [2:0] $end
       $var wire 32 ] result [31:0] $end
       $var wire 1 ^ zero $end
       $var wire 32 i condinvb [31:0] $end
       $var wire 32 a sum [31:0] $end
      $upscope $end
      $scope module immsh $end
       $var wire 32 U a [31:0] $end
       $var wire 32 V y [31:0] $end
      $upscope $end
      $scope module pcadd1 $end
       $var wire 32 D a [31:0] $end
       $var wire 32 k b [31:0] $end
       $var wire 32 S y [31:0] $end
      $upscope $end
      $scope module pcadd2 $end
       $var wire 32 S a [31:0] $end
       $var wire 32 V b [31:0] $end
       $var wire 32 T y [31:0] $end
      $upscope $end
      $scope module pcbrmux $end
       $var wire 32 l WIDTH [31:0] $end
       $var wire 32 S d0 [31:0] $end
       $var wire 32 T d1 [31:0] $end
       $var wire 1 e s $end
       $var wire 32 g y [31:0] $end
      $upscope $end
      $scope module pcmux $end
       $var wire 32 l WIDTH [31:0] $end
       $var wire 32 g d0 [31:0] $end
       $var wire 32 W d1 [31:0] $end
       $var wire 1 K s $end
       $var wire 32 f y [31:0] $end
      $upscope $end
      $scope module pcreg $end
       $var wire 32 l WIDTH [31:0] $end
       $var wire 1 b clk $end
       $var wire 1 c reset $end
       $var wire 32 f d [31:0] $end
       $var wire 32 D q [31:0] $end
      $upscope $end
      $scope module resmux $end
       $var wire 32 l WIDTH [31:0] $end
       $var wire 32 ] d0 [31:0] $end
       $var wire 32 d d1 [31:0] $end
       $var wire 1 G s $end
       $var wire 32 h y [31:0] $end
      $upscope $end
      $scope module rf $end
       $var wire 1 b clk $end
       $var wire 1 J we3 $end
       $var wire 5 X ra1 [4:0] $end
       $var wire 5 Y ra2 [4:0] $end
       $var wire 5 R wa3 [4:0] $end
       $var wire 32 h wd3 [31:0] $end
       $var wire 32 _ rd1 [31:0] $end
       $var wire 32 \ rd2 [31:0] $end
       $var wire 32 # rf[0] [31:0] $end
       $var wire 32 $ rf[1] [31:0] $end
       $var wire 32 % rf[2] [31:0] $end
       $var wire 32 & rf[3] [31:0] $end
       $var wire 32 ' rf[4] [31:0] $end
       $var wire 32 ( rf[5] [31:0] $end
       $var wire 32 ) rf[6] [31:0] $end
       $var wire 32 * rf[7] [31:0] $end
       $var wire 32 + rf[8] [31:0] $end
       $var wire 32 , rf[9] [31:0] $end
       $var wire 32 - rf[10] [31:0] $end
       $var wire 32 . rf[11] [31:0] $end
       $var wire 32 / rf[12] [31:0] $end
       $var wire 32 0 rf[13] [31:0] $end
       $var wire 32 1 rf[14] [31:0] $end
       $var wire 32 2 rf[15] [31:0] $end
       $var wire 32 3 rf[16] [31:0] $end
       $var wire 32 4 rf[17] [31:0] $end
       $var wire 32 5 rf[18] [31:0] $end
       $var wire 32 6 rf[19] [31:0] $end
       $var wire 32 7 rf[20] [31:0] $end
       $var wire 32 8 rf[21] [31:0] $end
       $var wire 32 9 rf[22] [31:0] $end
       $var wire 32 : rf[23] [31:0] $end
       $var wire 32 ; rf[24] [31:0] $end
       $var wire 32 < rf[25] [31:0] $end
       $var wire 32 = rf[26] [31:0] $end
       $var wire 32 > rf[27] [31:0] $end
       $var wire 32 ? rf[28] [31:0] $end
       $var wire 32 @ rf[29] [31:0] $end
       $var wire 32 A rf[30] [31:0] $end
       $var wire 32 B rf[31] [31:0] $end
      $upscope $end
      $scope module se $end
       $var wire 16 Z a [15:0] $end
       $var wire 32 U y [31:0] $end
      $upscope $end
      $scope module srcbmux $end
       $var wire 32 l WIDTH [31:0] $end
       $var wire 32 \ d0 [31:0] $end
       $var wire 32 U d1 [31:0] $end
       $var wire 1 H s $end
       $var wire 32 ` y [31:0] $end
      $upscope $end
      $scope module wrmux $end
       $var wire 32 m WIDTH [31:0] $end
       $var wire 5 Y d0 [4:0] $end
       $var wire 5 [ d1 [4:0] $end
       $var wire 1 I s $end
       $var wire 5 R y [4:0] $end
      $upscope $end
     $upscope $end
    $upscope $end
   $upscope $end
  $upscope $end
 $upscope $end
$enddefinitions $end


#0
b00000000000000000000000000000000 #
b00000000000000000000000000000000 $
b00000000000000000000000000000000 %
b00000000000000000000000000000000 &
b00000000000000000000000000000000 '
b00000000000000000000000000000000 (
b00000000000000000000000000000000 )
b00000000000000000000000000000000 *
b00000000000000000000000000000000 +
b00000000000000000000000000000000 ,
b00000000000000000000000000000000 -
b00000000000000000000000000000000 .
b00000000000000000000000000000000 /
b00000000000000000000000000000000 0
b00000000000000000000000000000000 1
b00000000000000000000000000000000 2
b00000000000000000000000000000000 3
b00000000000000000000000000000000 4
b00000000000000000000000000000000 5
b00000000000000000000000000000000 6
b00000000000000000000000000000000 7
b00000000000000000000000000000000 8
b00000000000000000000000000000000 9
b00000000000000000000000000000000 :
b00000000000000000000000000000000 ;
b00000000000000000000000000000000 <
b00000000000000000000000000000000 =
b00000000000000000000000000000000 >
b00000000000000000000000000000000 ?
b00000000000000000000000000000000 @
b00000000000000000000000000000000 A
b00000000000000000000000000000000 B
0C
b00000000000000000000000000000000 D
b00100000000000100000000000000101 E
b000000 F
0G
1H
0I
1J
0K
b010 L
b001000 M
b000101 N
b00 O
0P
b101000000 Q
b00010 R
b00000000000000000000000000000100 S
b00000000000000000000000000011000 T
b00000000000000000000000000000101 U
b00000000000000000000000000010100 V
b00000000000010000000000000010100 W
b00000 X
b00010 Y
b0000000000000101 Z
b00000 [
b00000000000000000000000000000000 \
b00000000000000000000000000000101 ]
0^
b00000000000000000000000000000000 _
b00000000000000000000000000000101 `
b00000000000000000000000000000101 a
0b
1c
b00000000000000000000000000000000 d
0e
b00000000000000000000000000000100 f
b00000000000000000000000000000100 g
b00000000000000000000000000000101 h
b00000000000000000000000000000101 i
b00000000000000000000000000000000 j
b00000000000000000000000000000100 k
b00000000000000000000000000100000 l
b00000000000000000000000000000101 m
#5000
#10000
b00000000000000000000000000000101 %
b00000000000000000000000000000101 \
1b
#15000
0b
#20000
1b
#22000
0c
#25000
0b
#30000
b00000000000000000000000000000100 D
b00100000000000110000000000001100 E
b000001 F
b001100 N
b00011 R
b00000000000000000000000000001000 S
b00000000000000000000000000111000 T
b00000000000000000000000000001100 U
b00000000000000000000000000110000 V
b00000000000011000000000000110000 W
b00011 Y
b0000000000001100 Z
b00000000000000000000000000000000 \
b00000000000000000000000000001100 ]
b00000000000000000000000000001100 `
b00000000000000000000000000001100 a
1b
b00000000000000000000000000001000 f
b00000000000000000000000000001000 g
b00000000000000000000000000001100 h
b00000000000000000000000000001100 i
#35000
0b
#40000
b00000000000000000000000000001100 &
b00000000000000000000000000001000 D
b00100000011001111111111111110111 E
b000010 F
b110111 N
b00111 R
b00000000000000000000000000001100 S
b11111111111111111111111111101000 T
b11111111111111111111111111110111 U
b11111111111111111111111111011100 V
b00000001100111111111111111011100 W
b00011 X
b00111 Y
b1111111111110111 Z
b11111 [
b00000000000000000000000000000011 ]
b00000000000000000000000000001100 _
b11111111111111111111111111110111 `
b00000000000000000000000000000011 a
1b
b00000000000000000000000000001100 f
b00000000000000000000000000001100 g
b00000000000000000000000000000011 h
b11111111111111111111111111110111 i
#45000
0b
#50000
b00000000000000000000000000000011 *
b00000000000000000000000000001100 D
b00000000111000100010000000100101 E
b000011 F
0H
1I
b001 L
b000000 M
b100101 N
b10 O
b110000010 Q
b00100 R
b00000000000000000000000000010000 S
b00000000000000001000000010100100 T
b00000000000000000010000000100101 U
b00000000000000001000000010010100 V
b00000011100010001000000010010100 W
b00111 X
b00010 Y
b0010000000100101 Z
b00100 [
b00000000000000000000000000000101 \
b00000000000000000000000000000111 ]
b00000000000000000000000000000011 _
b00000000000000000000000000000101 `
b00000000000000000000000000001000 a
1b
b00000000000000000000000000010000 f
b00000000000000000000000000010000 g
b00000000000000000000000000000111 h
b00000000000000000000000000000101 i
#55000
0b
#60000
b00000000000000000000000000000111 '
b00000000000000000000000000010000 D
b00000000011001000010100000100100 E
b000100 F
b000 L
b100100 N
b00101 R
b00000000000000000000000000010100 S
b00000000000000001010000010100100 T
b00000000000000000010100000100100 U
b00000000000000001010000010010000 V
b00000001100100001010000010010000 W
b00011 X
b00100 Y
b0010100000100100 Z
b00101 [
b00000000000000000000000000000111 \
b00000000000000000000000000000100 ]
b00000000000000000000000000001100 _
b00000000000000000000000000000111 `
b00000000000000000000000000010011 a
1b
b00000000000000000000000000010100 f
b00000000000000000000000000010100 g
b00000000000000000000000000000100 h
b00000000000000000000000000000111 i
#65000
0b
#70000
b00000000000000000000000000000100 (
b00000000000000000000000000010100 D
b00000000101001000010100000100000 E
b000101 F
b010 L
b100000 N
b00000000000000000000000000011000 S
b00000000000000001010000010011000 T
b00000000000000000010100000100000 U
b00000000000000001010000010000000 V
b00000010100100001010000010000000 W
b00101 X
b0010100000100000 Z
b00000000000000000000000000001011 ]
b00000000000000000000000000000100 _
b00000000000000000000000000001011 a
1b
b00000000000000000000000000011000 f
b00000000000000000000000000011000 g
b00000000000000000000000000001011 h
#75000
0b
#80000
b00000000000000000000000000001011 (
b00000000000000000000000000011000 D
b00010000101001110000000000001010 E
b000110 F
0I
0J
b110 L
b000100 M
b001010 N
b01 O
1P
b000100001 Q
b00111 R
b00000000000000000000000000011100 S
b00000000000000000000000001000100 T
b00000000000000000000000000001010 U
b00000000000000000000000000101000 V
b00000010100111000000000000101000 W
b00111 Y
b0000000000001010 Z
b00000 [
b00000000000000000000000000000011 \
b00000000000000000000000000001000 ]
b00000000000000000000000000001011 _
b00000000000000000000000000000011 `
b00000000000000000000000000001000 a
1b
b00000000000000000000000000011100 f
b00000000000000000000000000011100 g
b00000000000000000000000000001000 h
b11111111111111111111111111111100 i
#85000
0b
#90000
b00000000000000000000000000011100 D
b00000000011001000010000000101010 E
b000111 F
1I
1J
b111 L
b000000 M
b101010 N
b10 O
0P
b110000010 Q
b00100 R
b00000000000000000000000000100000 S
b00000000000000001000000011001000 T
b00000000000000000010000000101010 U
b00000000000000001000000010101000 V
b00000001100100001000000010101000 W
b00011 X
b00100 Y
b0010000000101010 Z
b00100 [
b00000000000000000000000000000111 \
b00000000000000000000000000000000 ]
1^
b00000000000000000000000000001100 _
b00000000000000000000000000000111 `
b00000000000000000000000000000101 a
1b
b00000000000000000000000000100000 f
b00000000000000000000000000100000 g
b00000000000000000000000000000000 h
b11111111111111111111111111111000 i
#95000
0b
#100000
b00000000000000000000000000000000 '
b00000000000000000000000000100000 D
b00010000100000000000000000000001 E
b001000 F
0I
0J
b110 L
b000100 M
b000001 N
b01 O
1P
b000100001 Q
b00000 R
b00000000000000000000000000100100 S
b00000000000000000000000000101000 T
b00000000000000000000000000000001 U
b00000000000000000000000000000100 V
b00000010000000000000000000000100 W
b00100 X
b00000 Y
b0000000000000001 Z
b00000 [
b00000000000000000000000000000000 \
b00000000000000000000000000000000 _
b00000000000000000000000000000000 `
b00000000000000000000000000000000 a
1b
1e
b00000000000000000000000000101000 f
b00000000000000000000000000101000 g
b11111111111111111111111111111111 i
#105000
0b
#110000
b00000000000000000000000000101000 D
b00000000111000100010000000101010 E
b001010 F
1I
1J
b111 L
b000000 M
b101010 N
b10 O
0P
b110000010 Q
b00100 R
b00000000000000000000000000101100 S
b00000000000000001000000011010100 T
b00000000000000000010000000101010 U
b00000000000000001000000010101000 V
b00000011100010001000000010101000 W
b00111 X
b00010 Y
b0010000000101010 Z
b00100 [
b00000000000000000000000000000101 \
b00000000000000000000000000000001 ]
0^
b00000000000000000000000000000011 _
b00000000000000000000000000000101 `
b11111111111111111111111111111110 a
1b
0e
b00000000000000000000000000101100 f
b00000000000000000000000000101100 g
b00000000000000000000000000000001 h
b11111111111111111111111111111010 i
#115000
0b
#120000
b00000000000000000000000000000001 '
b00000000000000000000000000101100 D
b00000000100001010011100000100000 E
b001011 F
b010 L
b100000 N
b00111 R
b00000000000000000000000000110000 S
b00000000000000001110000010110000 T
b00000000000000000011100000100000 U
b00000000000000001110000010000000 V
b00000010000101001110000010000000 W
b00100 X
b00101 Y
b0011100000100000 Z
b00111 [
b00000000000000000000000000001011 \
b00000000000000000000000000001100 ]
b00000000000000000000000000000001 _
b00000000000000000000000000001011 `
b00000000000000000000000000001100 a
1b
b00000000000000000000000000110000 f
b00000000000000000000000000110000 g
b00000000000000000000000000001100 h
b00000000000000000000000000001011 i
#125000
0b
#130000
b00000000000000000000000000001100 *
b00000000000000000000000000110000 D
b00000000111000100011100000100010 E
b001100 F
b110 L
b100010 N
b00000000000000000000000000110100 S
b00000000000000001110000010111100 T
b00000000000000000011100000100010 U
b00000000000000001110000010001000 V
b00000011100010001110000010001000 W
b00111 X
b00010 Y
b0011100000100010 Z
b00000000000000000000000000000101 \
b00000000000000000000000000000111 ]
b00000000000000000000000000001100 _
b00000000000000000000000000000101 `
b00000000000000000000000000000111 a
1b
b00000000000000000000000000110100 f
b00000000000000000000000000110100 g
b00000000000000000000000000000111 h
b11111111111111111111111111111010 i
#135000
0b
#140000
b00000000000000000000000000000111 *
1C
b00000000000000000000000000110100 D
b10101100011001110000000001000100 E
b001101 F
1H
0I
0J
b010 L
b101011 M
b000100 N
b00 O
b001010000 Q
b00000000000000000000000000111000 S
b00000000000000000000000101001000 T
b00000000000000000000000001000100 U
b00000000000000000000000100010000 V
b00000001100111000000000100010000 W
b00011 X
b00111 Y
b0000000001000100 Z
b00000 [
b00000000000000000000000000000111 \
b00000000000000000000000001010000 ]
b00000000000000000000000001000100 `
b00000000000000000000000001010000 a
1b
b00000000000000000000000000111000 f
b00000000000000000000000000111000 g
b00000000000000000000000001010000 h
b00000000000000000000000001000100 i
#145000
0b
#150000
0C
b00000000000000000000000000111000 D
b10001100000000100000000001010000 E
b001110 F
1G
1J
b100011 M
b010000 N
b101001000 Q
b00010 R
b00000000000000000000000000111100 S
b00000000000000000000000101111100 T
b00000000000000000000000001010000 U
b00000000000000000000000101000000 V
b00000000000010000000000101000000 W
b00000 X
b00010 Y
b0000000001010000 Z
b00000000000000000000000000000101 \
b00000000000000000000000000000000 _
b00000000000000000000000001010000 `
1b
b00000000000000000000000000000111 d
b00000000000000000000000000111100 f
b00000000000000000000000000111100 g
b00000000000000000000000000000111 h
b00000000000000000000000001010000 i
#155000
0b
#160000
b00000000000000000000000000000111 %
b00000000000000000000000000111100 D
b00001000000000000000000000010001 E
b001111 F
0G
0H
0J
1K
b000010 M
b010001 N
b000000100 Q
b00000 R
b00000000000000000000000001000000 S
b00000000000000000000000010000100 T
b00000000000000000000000000010001 U
b00000000000000000000000001000100 V
b00000000000000000000000001000100 W
b00000 Y
b0000000000010001 Z
b00000000000000000000000000000000 \
b00000000000000000000000000000000 ]
1^
b00000000000000000000000000000000 `
b00000000000000000000000000000000 a
1b
b00000000000000000000000000000000 d
b00000000000000000000000001000100 f
b00000000000000000000000001000000 g
b00000000000000000000000000000000 h
b00000000000000000000000000000000 i
#165000
0b
#170000
1C
b00000000000000000000000001000100 D
b10101100000000100000000001010100 E
b010001 F
1H
0K
b101011 M
b010100 N
b001010000 Q
b00010 R
b00000000000000000000000001001000 S
b00000000000000000000000110011000 T
b00000000000000000000000001010100 U
b00000000000000000000000101010000 V
b00000000000010000000000101010000 W
b00010 Y
b0000000001010100 Z
b00000000000000000000000000000111 \
b00000000000000000000000001010100 ]
0^
b00000000000000000000000001010100 `
b00000000000000000000000001010100 a
1b
b00000000000000000000000001001000 f
b00000000000000000000000001001000 g
b00000000000000000000000001010100 h
b00000000000000000000000001010100 i
